Workbook
Name \0: #REF!
Name \a: #REF!
Name \b: #N/A
Name \c: #N/A
Name \d: #REF!
Name \e: #REF!
Name \f: #N/A
Name \g: #N/A
Name \h: #N/A
Name \i: #REF!
Name \j: #N/A
Name \m: #REF!
Name \n: #REF!
Name \p: #N/A
Name \PAG1: #REF!
Name \PAG10: #REF!
Name \PAG11: #REF!
Name \PAG13: #REF!
Name \PAG14: #REF!
Name \PAG2: #REF!
Name \PAG3: #REF!
Name \PAG4: #REF!
Name \PAG5: #REF!
Name \PAG6: #REF!
Name \PAG7: #REF!
Name \PAG8: #REF!
Name \PAG9: #REF!
Name \q: #REF!
Name \r: #N/A
Name \s: #N/A
Name \t: #N/A
Name \u: #N/A
Name \v: #N/A
Name \x: #N/A
Name \z: #N/A
Name _: #REF!
Name ________________pl056: #REF!
Name _______________pl056: #REF!
Name ______________pl056: #REF!
Name _____________pl056: #REF!
Name ____________pl056: #REF!
Name ___________pl056: #REF!
Name __________pl056: #REF!
Name _________pl056: #REF!
Name ________pl056: #REF!
Name _______pl056: #REF!
Name ______COD1: #REF!
Name ______COD10: #REF!
Name ______COD11: #REF!
Name ______COD13: #REF!
Name ______COD138: #REF!
Name ______COD140: #REF!
Name ______COD144: #REF!
Name ______COD146: #REF!
Name ______COD149: #REF!
Name ______COD152: #REF!
Name ______COD154: #REF!
Name ______COD155: #REF!
Name ______COD156: #REF!
Name ______COD157: #REF!

Sheet PAINEL
O1: QTD SS
O2: =GETPIVOTDATA("STATUS. ENVIO",$B$5) -> #REF!
A3: (Tudo) | B3: TOMADOR | C3: (Tudo) | F3: TOMADOR | G3: (Tudo) | I3: TOMADOR | J3: (Tudo) | L3: TOMADOR | M3: (Tudo) | O3: TOMADOR | P3: (Tudo)
A5: R$ MEDIDO | F5: Rótulos de Linha | G5: Contagem de STATUS DEMANDA | I5: Rótulos de Linha | J5: Contagem de STATUS PRIMÁRIO (EC) | L5: Rótulos de Linha | M5: Contagem de STATUS SECUNDÁRIO (EC) | O5: R$ APROVADO | P5: R$ MEDIDO | Q5: R$ SALDO
A6: 2.120337e+08 | F6: CANCELADA | G6: 2 | I6: APROVADO | J6: 31 | L6: CANCELADA | M6: 2 | O6: 25645358 | P6: 14843092 | Q6: 10802266
F7: CONCLUÍDA | G7: 14 | I7: ON HOLD | J7: 3 | L7: EM PLANEJ. | M7: 1
F8: EM ANDAMENTO | G8: 17 | I8: FISCALIZ. | J8: 1 | L8: RETORNO OK | M8: 31
F9: EM PLANEJAMENTO | G9: 1 | I9: CANCELADA | J9: 2 | L9: ON HOLD | M9: 3
F10: ON HOLD | G10: 3 | I10: Total Geral | J10: 37 | L10: Total Geral | M10: 37
F11: Total Geral | G11: 37

Sheet INTEGRADO
E1: QTD SS | U1: FÍSICO | AE1: Hh
E2: =SUBTOTAL(9,A:A) -> 17
A3: CONT. | B3: Nº SS | C3: ID | DESCRIÇÃO DA DEMANDA | D3: TIPO | E3: TOMADOR | F3: STATUS DEMANDA | G3: ESTIMATIVA DE CUSTOS | O3: CRONOGRAMA | V3: ACOMPANHAMENTO FÍSICO | AB3: =SUBTOTAL(1,TB_INTEGRADA[DESVIO (%)]) -> -0.064717647 | AC3: =SUBTOTAL(9,TB_INTEGRADA[M.O PREV.]) -> 60 | AD3: =SUBTOTAL(9,TB_INTEGRADA[M.O REAL]) -> 64 | AF3: MECÂNICA | AJ3: CIVIL | AN3: ELÉTRICA | AR3: PINTURA | AV3: TOTAIS | AZ3: =SUBTOTAL(9,TB_INTEGRADA[R$ APROVADO]) -> 20337631 | BA3: =SUBTOTAL(9,TB_INTEGRADA[R$ MEDIDO ]) -> 9535364.5 | BB3: =SUBTOTAL(9,TB_INTEGRADA[R$ SALDO ]) -> 10802266
G4: ÚLTIMA REVISÃO | H4: ÚLTIMO ENVIO | I4: ÚLTIMA APROV. | J4: PRÓX. ENVIO | K4: STATUS ENVIO | L4: STATUS PRIMÁRIO | M4: AGUARD. RETORNO | N4: STATUS SECUNDÁRIO | O4: ÚLTIMA REVISÃO | P4: ÚLTIMO ENVIO | Q4: ÚLTIMA APROV. | R4: PRÓX. ENVIO | S4: STATUS ENVIO | T4: STATUS PRIMÁRIO | V4: TÉRM. LB | W4: TÉRM. TD | X4: DESVIO (d) | Y4: PREV (%) | Z4: REAL (%) | AA4: DESVIO ANT (%) ANT | AB4: DESVIO ATUAL (%) ATUAL | AC4: M.O PREV. | AD4: M.O REAL | AF4: ORÇADO | AG4: ORÇ DIG | AH4: PLANEJ | AI4: REALIZ | AJ4: ORÇADO | AK4: ORÇ DIG | AL4: PLANEJ | AM4: REALIZ | AN4: ORÇADO | AO4: ORÇ DIG | AP4: PLANEJ | AQ4: REALIZ | AR4: ORÇADO | AS4: ORÇ DIG | AT4: PLANEJ | AU4: REALIZ | AV4: ORÇADO | AW4: PLANEJ | AX4: REALIZ | AY4: % EXEC | AZ4: R$ APROVADO | BA4: R$ MEDIDO | BB4: R$ SALDO
A5: CONT. | B5: Nº SS | C5: ID | TÍTULO DA DEMANDA | D5: TIPO | E5: TOMADOR | F5: STATUS DEMANDA | G5: REVISÃO (EC) | H5: DATA ENVIO. (EC) | I5: DATA APROV. (EC) | J5: PRÓX. ENVIO | K5: STATUS ENVIO | L5: STATUS PRIMÁRIO (EC) | M5: AGUARD. RETORNO | N5: STATUS SECUNDÁRIO (EC) | O5: REVISÃO (CR) | P5: DATA ENVIO. (CR) | Q5: DATA APROV. (CR) | R5: PRÓX. ENVIO2 | S5: STATUS ENVIO | T5: STATUS PRIMÁRIO (EC) | U5: FÍSICO | V5: TÉRMINO LB | W5: TÉRM. TD | X5: DESVIO (d) | Y5: PREV (%) | Z5: REAL (%) | AA5: DESVIO (%) ANT | AB5: DESVIO (%) | AC5: M.O PREV. | AD5: M.O REAL | AE5: CONTR HH | AF5: ORÇADO | AG5: ORÇ DIG | AH5: PLANEJ | AI5: REALIZ | AJ5: ORÇADO1 | AK5: ORÇ DIG1 | AL5: PLANEJ1 | AM5: REALIZ1 | AN5: ORÇADO2 | AO5: ORÇ DIG2 | AP5: PLANEJ2 | AQ5: REALIZ2 | AR5: ORÇADO3 | AS5: ORÇ DIG3 | AT5: PLANEJ3 | AU5: REALIZ3 | AV5: ORÇADO4 | AW5: PLANEJ4 | AX5: REALIZ4 | AY5: % EXEC | AZ5: R$ APROVADO | BA5: R$ MEDIDO | BB5: R$ SALDO
A6: =IF(COUNTIFS($B$5:B6,TB_INTEGRADA[[#This Row],[Nº SS]])<>1,"",COUNTIFS($B$5:B6,TB_INTEGRADA[[#This Row],[Nº SS]])) -> 1 | B6: SS-01/2025 | C6: =_xlfn.XLOOKUP(TB_INTEGRADA[[#This Row],[Nº SS]],'CONTROLE EC'!B:B,'CONTROLE EC'!C:C,"",0,1) -> -- IMPLANTAÇÃO ÁREA I (EDIVIT, UTG-SUL, TIMS) | D6: =_xlfn.XLOOKUP(TB_INTEGRADA[[#This Row],[Nº SS]],'CONTROLE CRONOG'!B:B,'CONTROLE CRONOG'!D:D,"",0,1) -> ADM | E6: =_xlfn.XLOOKUP(TB_INTEGRADA[[#This Row],[Nº SS]],'CONTROLE EC'!B:B,'CONTROLE EC'!E:E,"",0,1) -> EDIVIT | F6: =_xlfn.XLOOKUP(TB_INTEGRADA[[#This Row],[Nº SS]],'CONTROLE EC'!B:B,'CONTROLE EC'!F:F,"",0,1) -> EM ANDAMENTO | G6: =_xlfn.XLOOKUP(TB_INTEGRADA[[#This Row],[Nº SS]],'CONTROLE EC'!B:B,'CONTROLE EC'!R:R,"",0,1) -> REV.00 | H6: =IF(TB_INTEGRADA[[#This Row],[REVISÃO (EC)]]="","",_xlfn.XLOOKUP(TB_INTEGRADA[[#This Row],[Nº SS]],'CONTROLE EC'!B:B,'CONTROLE EC'!S:S,"",0,1)) -> N/A | I6: =IF(TB_INTEGRADA[[#This Row],[REVISÃO (EC)]]="","",_xlfn.XLOOKUP(TB_INTEGRADA[[#This Row],[Nº SS]],'CONTROLE EC'!B:B,'CONTROLE EC'!U:U,"",0,1)) -> N/A | J6: {=IF(TB_INTEGRADA[[#This Row],[DATA ENVIO. (EC)]]=IFERROR(INDEX('CONTROLE EC'!G6:Q6,MATCH(2,1/('CONTROLE EC'!G6:Q6<>""))),""),"",IFERROR(INDEX('CONTROLE EC'!G6:Q6,MATCH(2,1/('CONTROLE EC'!G6:Q6<>""))),""))} | K6: =IF(TB_INTEGRADA[[#This Row],[STATUS DEMANDA]]="NÃO EMITIDA SAMC","S/ EMISSÃO",_xlfn.XLOOKUP(TB_INTEGRADA[[#This Row],[Nº SS]],'CONTROLE EC'!B:B,'CONTROLE EC'!T:T,"",0,-1)) -> ENTREGUE | L6: =IF(TB_INTEGRADA[[#This Row],[STATUS DEMANDA]]="NÃO EMITIDA SAMC","S/ EMISSÃO",IF(TB_INTEGRADA[[#This Row],[STATUS DEMANDA]]="ON HOLD","ON HOLD",IF(TB_INTEGRADA[[#This Row],[STATUS DEMANDA]]="CANCELADA","CANCELADA",IF(TB_INTEGRADA[[#This Row],[DATA APROV. (EC)]]=0,"FISCALIZ.",IF(TB_INTEGRADA[[#This Row],[DATA APROV. (EC)]]="","PEND. FISCALIZ.",IF(TB_INTEGRADA[[#This Row],[DATA APROV. (EC)]]="N/A","APROVADO",IF(TB_INTEGRADA[[#This Row],[REVISÃO (EC)]]="","",_xlfn.XLOOKUP(TB_INTEGRADA[[#This Row],[Nº SS]],'CONTROLE EC'!B:B,'CONTROLE EC'!V:V,"",0,1)))))))) -> APROVADO | M6: {=IFERROR(_xlfn.IFS(TB_INTEGRADA[[#This Row],[STATUS DEMANDA]]="CANCELADA",0,TB_INTEGRADA[[#This Row],[DATA APROV. (EC)]]="",TODAY()-TB_INTEGRADA[[#This Row],[DATA ENVIO. (EC)]],TB_INTEGRADA[[#This Row],[DATA APROV. (EC)]]>=TB_INTEGRADA[[#This Row],[DATA ENVIO. (EC)]],0,TB_INTEGRADA[[#This Row],[DATA ENVIO. (EC)]]="",0,TB_INTEGRADA[[#This Row],[DATA ENVIO. (EC)]]>TB_INTEGRADA[[#This Row],[DATA APROV. (EC)]],TODAY()-TB_INTEGRADA[[#This Row],[DATA ENVIO. (EC)]]),"")} -> 0 | N6: =IF(TB_INTEGRADA[[#This Row],[STATUS DEMANDA]]="NÃO EMITIDA SAMC","S/ EMISSÃO",IF(TB_INTEGRADA[[#This Row],[STATUS DEMANDA]]="ON HOLD","ON HOLD",IF(F6="CANCELADA","CANCELADA",IF(L6="REPROVADO","EM PLANEJ.",IF(K6<>"ENTREGUE","EM PLANEJ.",IF(H6="","EM PLANEJ.",IF(I6="","FISCALIZ.",IF(M6<0,"EM PLANEJ.",IF(TB_INTEGRADA[[#This Row],[DATA APROV. (EC)]]>=TB_INTEGRADA[[#This Row],[DATA ENVIO. (EC)]],"RETORNO OK","FISCALIZ."))))))))) -> RETORNO OK | O6: =_xlfn.XLOOKUP(TB_INTEGRADA[[#This Row],[Nº SS]],'CONTROLE CRONOG'!B:B,'CONTROLE CRONOG'!R:R,"",0,1) -> REV.00 | P6: =IF(TB_INTEGRADA[[#This Row],[REVISÃO (CR)]]="","",_xlfn.XLOOKUP(TB_INTEGRADA[[#This Row],[Nº SS]],'CONTROLE CRONOG'!B:B,'CONTROLE CRONOG'!S:S,"",0,1)) -> N/A | Q6: =IF(TB_INTEGRADA[[#This Row],[REVISÃO (CR)]]="","",_xlfn.XLOOKUP(TB_INTEGRADA[[#This Row],[Nº SS]],'CONTROLE CRONOG'!B:B,'CONTROLE CRONOG'!U:U,"",0,1)) -> N/A | R6: {=IF(TB_INTEGRADA[[#This Row],[DATA ENVIO. (CR)]]=IFERROR(INDEX('CONTROLE CRONOG'!G6:Q6,MATCH(2,1/('CONTROLE CRONOG'!G6:Q6<>""))),""),"",IFERROR(INDEX('CONTROLE CRONOG'!G6:Q6,MATCH(2,1/('CONTROLE CRONOG'!G6:Q6<>""))),""))} | S6: =_xlfn.XLOOKUP(TB_INTEGRADA[[#This Row],[Nº SS]],'CONTROLE CRONOG'!B:B,'CONTROLE CRONOG'!T:T,"",0,-1) -> ENTREGUE | T6: =IF(TB_INTEGRADA[[#This Row],[STATUS DEMANDA]]="ON HOLD","ON HOLD",IF(TB_INTEGRADA[[#This Row],[STATUS DEMANDA]]="CANCELADA","CANCELADA",IF(TB_INTEGRADA[[#This Row],[DATA APROV. (CR)]]=0,"FISCALIZ.",IF(TB_INTEGRADA[[#This Row],[DATA APROV. (CR)]]="N/A","APROVADO",IF(TB_INTEGRADA[[#This Row],[REVISÃO (CR)]]="","",_xlfn.XLOOKUP(TB_INTEGRADA[[#This Row],[Nº SS]],'CONTROLE CRONOG'!B:B,'CONTROLE CRONOG'!V:V,"",0,1)))))) -> APROVADO | X6: =IFERROR(TB_INTEGRADA[[#This Row],[TÉRM. TD]]-TB_INTEGRADA[[#This Row],[TÉRMINO LB]],0) -> 0 | AB6: =IFERROR(TB_INTEGRADA[[#This Row],[REAL (%)]]-TB_INTEGRADA[[#This Row],[PREV (%)]],0) -> 0 | AF6: =IF(TB_INTEGRADA[[#This Row],[TOMADOR]]="EDIVIT",TB_INTEGRADA[[#This Row],[ORÇ DIG]]*1.38,IF(TB_INTEGRADA[[#This Row],[TOMADOR]]="UTGC",TB_INTEGRADA[[#This Row],[ORÇ DIG]]*1.47,IF(TB_INTEGRADA[[#This Row],[TOMADOR]]="TIMS",TB_INTEGRADA[[#This Row],[ORÇ DIG]]*1.34,IF(TB_INTEGRADA[[#This Row],[TOMADOR]]="UTGSUL",TB_INTEGRADA[[#This Row],[ORÇ DIG]]*1.37,IF(TB_INTEGRADA[[#This Row],[TOMADOR]]="REGAP",TB_INTEGRADA[[#This Row],[ORÇ DIG]]*1.36,IF(TB_INTEGRADA[[#This Row],[TOMADOR]]="UTEIBI",TB_INTEGRADA[[#This Row],[ORÇ DIG]]*1.5,"S/TOMADOR")))))) -> 0 | AH6: =SUMIFS(Tb_HhPLAN[Hh DISC],Tb_HhPLAN[SS],TB_INTEGRADA[[#This Row],[Nº SS]],Tb_HhPLAN[DISCIPLINA],"MEC") -> 0 | AI6: =SUMIFS(Hh_EXE_TOTAL[Hh],Hh_EXE_TOTAL[Nº SS],TB_INTEGRADA[[#This Row],[Nº SS]],Hh_EXE_TOTAL[DISCIPLINA],"MEC") -> 0 | AJ6: =IF(TB_INTEGRADA[[#This Row],[TOMADOR]]="EDIVIT",TB_INTEGRADA[[#This Row],[ORÇ DIG1]]*1.38,IF(TB_INTEGRADA[[#This Row],[TOMADOR]]="UTGC",TB_INTEGRADA[[#This Row],[ORÇ DIG1]]*1.47,IF(TB_INTEGRADA[[#This Row],[TOMADOR]]="TIMS",TB_INTEGRADA[[#This Row],[ORÇ DIG1]]*1.34,IF(TB_INTEGRADA[[#This Row],[TOMADOR]]="UTGSUL",TB_INTEGRADA[[#This Row],[ORÇ DIG1]]*1.37,IF(TB_INTEGRADA[[#This Row],[TOMADOR]]="REGAP",TB_INTEGRADA[[#This Row],[ORÇ DIG1]]*1.36,IF(TB_INTEGRADA[[#This Row],[TOMADOR]]="UTEIBI",TB_INTEGRADA[[#This Row],[ORÇ DIG1]]*1.5,"S/TOMADOR")))))) -> 0 | AL6: =SUMIFS(Tb_HhPLAN[Hh DISC],Tb_HhPLAN[SS],TB_INTEGRADA[[#This Row],[Nº SS]],Tb_HhPLAN[DISCIPLINA],"CIVIL") -> 0 | AM6: =SUMIFS(Hh_EXE_TOTAL[Hh],Hh_EXE_TOTAL[Nº SS],TB_INTEGRADA[[#This Row],[Nº SS]],Hh_EXE_TOTAL[DISCIPLINA],"CIVIL") -> 0 | AN6: =IF(TB_INTEGRADA[[#This Row],[TOMADOR]]="EDIVIT",TB_INTEGRADA[[#This Row],[ORÇ DIG2]]*1.38,IF(TB_INTEGRADA[[#This Row],[TOMADOR]]="UTGC",TB_INTEGRADA[[#This Row],[ORÇ DIG2]]*1.47,IF(TB_INTEGRADA[[#This Row],[TOMADOR]]="TIMS",TB_INTEGRADA[[#This Row],[ORÇ DIG2]]*1.34,IF(TB_INTEGRADA[[#This Row],[TOMADOR]]="UTGSUL",TB_INTEGRADA[[#This Row],[ORÇ DIG2]]*1.37,IF(TB_INTEGRADA[[#This Row],[TOMADOR]]="REGAP",TB_INTEGRADA[[#This Row],[ORÇ DIG2]]*1.36,IF(TB_INTEGRADA[[#This Row],[TOMADOR]]="UTEIBI",TB_INTEGRADA[[#This Row],[ORÇ DIG2]]*1.5,"S/TOMADOR")))))) -> 0 | AP6: =SUMIFS(Tb_HhPLAN[Hh DISC],Tb_HhPLAN[SS],TB_INTEGRADA[[#This Row],[Nº SS]],Tb_HhPLAN[DISCIPLINA],"ELÉT") -> 0 | AQ6: =SUMIFS(Hh_EXE_TOTAL[Hh],Hh_EXE_TOTAL[Nº SS],TB_INTEGRADA[[#This Row],[Nº SS]],Hh_EXE_TOTAL[DISCIPLINA],"ELÉT") -> 0 | AR6: =IF(TB_INTEGRADA[[#This Row],[TOMADOR]]="EDIVIT",TB_INTEGRADA[[#This Row],[ORÇ DIG3]]*1.38,IF(TB_INTEGRADA[[#This Row],[TOMADOR]]="UTGC",TB_INTEGRADA[[#This Row],[ORÇ DIG3]]*1.47,IF(TB_INTEGRADA[[#This Row],[TOMADOR]]="TIMS",TB_INTEGRADA[[#This Row],[ORÇ DIG3]]*1.34,IF(TB_INTEGRADA[[#This Row],[TOMADOR]]="UTGSUL",TB_INTEGRADA[[#This Row],[ORÇ DIG3]]*1.37,IF(TB_INTEGRADA[[#This Row],[TOMADOR]]="REGAP",TB_INTEGRADA[[#This Row],[ORÇ DIG3]]*1.36,IF(TB_INTEGRADA[[#This Row],[TOMADOR]]="UTEIBI",TB_INTEGRADA[[#This Row],[ORÇ DIG3]]*1.5,"S/TOMADOR")))))) -> 0 | AT6: =SUMIFS(Tb_HhPLAN[Hh DISC],Tb_HhPLAN[SS],TB_INTEGRADA[[#This Row],[Nº SS]],Tb_HhPLAN[DISCIPLINA],"PINT") -> 0 | AU6: =SUMIFS(Hh_EXE_TOTAL[Hh],Hh_EXE_TOTAL[Nº SS],TB_INTEGRADA[[#This Row],[Nº SS]],Hh_EXE_TOTAL[DISCIPLINA],"PINT") -> 0 | AV6: =TB_INTEGRADA[[#This Row],[ORÇADO]]+TB_INTEGRADA[[#This Row],[ORÇADO1]]+TB_INTEGRADA[[#This Row],[ORÇADO2]]+TB_INTEGRADA[[#This Row],[ORÇADO3]] -> 0 | AW6: =TB_INTEGRADA[[#This Row],[PLANEJ]]+TB_INTEGRADA[[#This Row],[PLANEJ1]]+TB_INTEGRADA[[#This Row],[PLANEJ2]]+TB_INTEGRADA[[#This Row],[PLANEJ3]] -> 0 | AX6: =TB_INTEGRADA[[#This Row],[REALIZ]]+TB_INTEGRADA[[#This Row],[REALIZ1]]+TB_INTEGRADA[[#This Row],[REALIZ2]]+TB_INTEGRADA[[#This Row],[REALIZ3]] -> 0 | AZ6: =_xlfn.XLOOKUP(TB_INTEGRADA[[#This Row],[Nº SS]],'CONTROLE EC'!B:B,'CONTROLE EC'!W:W,"",0,1) -> 7940511.1 | BA6: =_xlfn.XLOOKUP(TB_INTEGRADA[[#This Row],[Nº SS]],'CONTROLE EC'!B:B,'CONTROLE EC'!X:X,"",0,1) -> 2080364.8 | BB6: =_xlfn.XLOOKUP(TB_INTEGRADA[[#This Row],[Nº SS]],'CONTROLE EC'!B:B,'CONTROLE EC'!Y:Y,"",0,1) -> 5860146.3
A7: =IF(COUNTIFS($B$5:B7,TB_INTEGRADA[[#This Row],[Nº SS]])<>1,"",COUNTIFS($B$5:B7,TB_INTEGRADA[[#This Row],[Nº SS]])) -> 1 | B7: SS-02/2025 | C7: =_xlfn.XLOOKUP(TB_INTEGRADA[[#This Row],[Nº SS]],'CONTROLE EC'!B:B,'CONTROLE EC'!C:C,"",0,1) -> -- IMPLANTAÇÃO ÁREA II (UTGC) | D7: =_xlfn.XLOOKUP(TB_INTEGRADA[[#This Row],[Nº SS]],'CONTROLE CRONOG'!B:B,'CONTROLE CRONOG'!D:D,"",0,1) -> ADM | E7: =_xlfn.XLOOKUP(TB_INTEGRADA[[#This Row],[Nº SS]],'CONTROLE EC'!B:B,'CONTROLE EC'!E:E,"",0,1) -> UTGC | F7: =_xlfn.XLOOKUP(TB_INTEGRADA[[#This Row],[Nº SS]],'CONTROLE EC'!B:B,'CONTROLE EC'!F:F,"",0,1) -> EM ANDAMENTO | G7: =_xlfn.XLOOKUP(TB_INTEGRADA[[#This Row],[Nº SS]],'CONTROLE EC'!B:B,'CONTROLE EC'!R:R,"",0,1) -> REV.00 | H7: =IF(TB_INTEGRADA[[#This Row],[REVISÃO (EC)]]="","",_xlfn.XLOOKUP(TB_INTEGRADA[[#This Row],[Nº SS]],'CONTROLE EC'!B:B,'CONTROLE EC'!S:S,"",0,1)) -> N/A | I7: =IF(TB_INTEGRADA[[#This Row],[REVISÃO (EC)]]="","",_xlfn.XLOOKUP(TB_INTEGRADA[[#This Row],[Nº SS]],'CONTROLE EC'!B:B,'CONTROLE EC'!U:U,"",0,1)) -> N/A | J7: {=IF(TB_INTEGRADA[[#This Row],[DATA ENVIO. (EC)]]=IFERROR(INDEX('CONTROLE EC'!G7:Q7,MATCH(2,1/('CONTROLE EC'!G7:Q7<>""))),""),"",IFERROR(INDEX('CONTROLE EC'!G7:Q7,MATCH(2,1/('CONTROLE EC'!G7:Q7<>""))),""))} | K7: =IF(TB_INTEGRADA[[#This Row],[STATUS DEMANDA]]="NÃO EMITIDA SAMC","S/ EMISSÃO",_xlfn.XLOOKUP(TB_INTEGRADA[[#This Row],[Nº SS]],'CONTROLE EC'!B:B,'CONTROLE EC'!T:T,"",0,-1)) -> ENTREGUE | L7: =IF(TB_INTEGRADA[[#This Row],[STATUS DEMANDA]]="NÃO EMITIDA SAMC","S/ EMISSÃO",IF(TB_INTEGRADA[[#This Row],[STATUS DEMANDA]]="ON HOLD","ON HOLD",IF(TB_INTEGRADA[[#This Row],[STATUS DEMANDA]]="CANCELADA","CANCELADA",IF(TB_INTEGRADA[[#This Row],[DATA APROV. (EC)]]=0,"FISCALIZ.",IF(TB_INTEGRADA[[#This Row],[DATA APROV. (EC)]]="","PEND. FISCALIZ.",IF(TB_INTEGRADA[[#This Row],[DATA APROV. (EC)]]="N/A","APROVADO",IF(TB_INTEGRADA[[#This Row],[REVISÃO (EC)]]="","",_xlfn.XLOOKUP(TB_INTEGRADA[[#This Row],[Nº SS]],'CONTROLE EC'!B:B,'CONTROLE EC'!V:V,"",0,1)))))))) -> APROVADO | M7: {=IFERROR(_xlfn.IFS(TB_INTEGRADA[[#This Row],[STATUS DEMANDA]]="CANCELADA",0,TB_INTEGRADA[[#This Row],[DATA APROV. (EC)]]="",TODAY()-TB_INTEGRADA[[#This Row],[DATA ENVIO. (EC)]],TB_INTEGRADA[[#This Row],[DATA APROV. (EC)]]>=TB_INTEGRADA[[#This Row],[DATA ENVIO. (EC)]],0,TB_INTEGRADA[[#This Row],[DATA ENVIO. (EC)]]="",0,TB_INTEGRADA[[#This Row],[DATA ENVIO. (EC)]]>TB_INTEGRADA[[#This Row],[DATA APROV. (EC)]],TODAY()-TB_INTEGRADA[[#This Row],[DATA ENVIO. (EC)]]),"")} -> 0 | N7: =IF(TB_INTEGRADA[[#This Row],[STATUS DEMANDA]]="NÃO EMITIDA SAMC","S/ EMISSÃO",IF(TB_INTEGRADA[[#This Row],[STATUS DEMANDA]]="ON HOLD","ON HOLD",IF(F7="CANCELADA","CANCELADA",IF(L7="REPROVADO","EM PLANEJ.",IF(K7<>"ENTREGUE","EM PLANEJ.",IF(H7="","EM PLANEJ.",IF(I7="","FISCALIZ.",IF(M7<0,"EM PLANEJ.",IF(TB_INTEGRADA[[#This Row],[DATA APROV. (EC)]]>=TB_INTEGRADA[[#This Row],[DATA ENVIO. (EC)]],"RETORNO OK","FISCALIZ."))))))))) -> RETORNO OK | O7: =_xlfn.XLOOKUP(TB_INTEGRADA[[#This Row],[Nº SS]],'CONTROLE CRONOG'!B:B,'CONTROLE CRONOG'!R:R,"",0,1) -> REV.00 | P7: =IF(TB_INTEGRADA[[#This Row],[REVISÃO (CR)]]="","",_xlfn.XLOOKUP(TB_INTEGRADA[[#This Row],[Nº SS]],'CONTROLE CRONOG'!B:B,'CONTROLE CRONOG'!S:S,"",0,1)) -> N/A | Q7: =IF(TB_INTEGRADA[[#This Row],[REVISÃO (CR)]]="","",_xlfn.XLOOKUP(TB_INTEGRADA[[#This Row],[Nº SS]],'CONTROLE CRONOG'!B:B,'CONTROLE CRONOG'!U:U,"",0,1)) -> N/A | R7: {=IF(TB_INTEGRADA[[#This Row],[DATA ENVIO. (CR)]]=IFERROR(INDEX('CONTROLE CRONOG'!G7:Q7,MATCH(2,1/('CONTROLE CRONOG'!G7:Q7<>""))),""),"",IFERROR(INDEX('CONTROLE CRONOG'!G7:Q7,MATCH(2,1/('CONTROLE CRONOG'!G7:Q7<>""))),""))} | S7: =_xlfn.XLOOKUP(TB_INTEGRADA[[#This Row],[Nº SS]],'CONTROLE CRONOG'!B:B,'CONTROLE CRONOG'!T:T,"",0,-1) -> ENTREGUE | T7: =IF(TB_INTEGRADA[[#This Row],[STATUS DEMANDA]]="ON HOLD","ON HOLD",IF(TB_INTEGRADA[[#This Row],[STATUS DEMANDA]]="CANCELADA","CANCELADA",IF(TB_INTEGRADA[[#This Row],[DATA APROV. (CR)]]=0,"FISCALIZ.",IF(TB_INTEGRADA[[#This Row],[DATA APROV. (CR)]]="N/A","APROVADO",IF(TB_INTEGRADA[[#This Row],[REVISÃO (CR)]]="","",_xlfn.XLOOKUP(TB_INTEGRADA[[#This Row],[Nº SS]],'CONTROLE CRONOG'!B:B,'CONTROLE CRONOG'!V:V,"",0,1)))))) -> APROVADO | X7: =IFERROR(TB_INTEGRADA[[#This Row],[TÉRM. TD]]-TB_INTEGRADA[[#This Row],[TÉRMINO LB]],0) -> 0 | AB7: =IFERROR(TB_INTEGRADA[[#This Row],[REAL (%)]]-TB_INTEGRADA[[#This Row],[PREV (%)]],0) -> 0 | AF7: =IF(TB_INTEGRADA[[#This Row],[TOMADOR]]="EDIVIT",TB_INTEGRADA[[#This Row],[ORÇ DIG]]*1.38,IF(TB_INTEGRADA[[#This Row],[TOMADOR]]="UTGC",TB_INTEGRADA[[#This Row],[ORÇ DIG]]*1.47,IF(TB_INTEGRADA[[#This Row],[TOMADOR]]="TIMS",TB_INTEGRADA[[#This Row],[ORÇ DIG]]*1.34,IF(TB_INTEGRADA[[#This Row],[TOMADOR]]="UTGSUL",TB_INTEGRADA[[#This Row],[ORÇ DIG]]*1.37,IF(TB_INTEGRADA[[#This Row],[TOMADOR]]="REGAP",TB_INTEGRADA[[#This Row],[ORÇ DIG]]*1.36,IF(TB_INTEGRADA[[#This Row],[TOMADOR]]="UTEIBI",TB_INTEGRADA[[#This Row],[ORÇ DIG]]*1.5,"S/TOMADOR")))))) -> 0 | AH7: =SUMIFS(Tb_HhPLAN[Hh DISC],Tb_HhPLAN[SS],TB_INTEGRADA[[#This Row],[Nº SS]],Tb_HhPLAN[DISCIPLINA],"MEC") -> 0 | AI7: =SUMIFS(Hh_EXE_TOTAL[Hh],Hh_EXE_TOTAL[Nº SS],TB_INTEGRADA[[#This Row],[Nº SS]],Hh_EXE_TOTAL[DISCIPLINA],"MEC") -> 0 | AJ7: =IF(TB_INTEGRADA[[#This Row],[TOMADOR]]="EDIVIT",TB_INTEGRADA[[#This Row],[ORÇ DIG1]]*1.38,IF(TB_INTEGRADA[[#This Row],[TOMADOR]]="UTGC",TB_INTEGRADA[[#This Row],[ORÇ DIG1]]*1.47,IF(TB_INTEGRADA[[#This Row],[TOMADOR]]="TIMS",TB_INTEGRADA[[#This Row],[ORÇ DIG1]]*1.34,IF(TB_INTEGRADA[[#This Row],[TOMADOR]]="UTGSUL",TB_INTEGRADA[[#This Row],[ORÇ DIG1]]*1.37,IF(TB_INTEGRADA[[#This Row],[TOMADOR]]="REGAP",TB_INTEGRADA[[#This Row],[ORÇ DIG1]]*1.36,IF(TB_INTEGRADA[[#This Row],[TOMADOR]]="UTEIBI",TB_INTEGRADA[[#This Row],[ORÇ DIG1]]*1.5,"S/TOMADOR")))))) -> 0 | AL7: =SUMIFS(Tb_HhPLAN[Hh DISC],Tb_HhPLAN[SS],TB_INTEGRADA[[#This Row],[Nº SS]],Tb_HhPLAN[DISCIPLINA],"CIVIL") -> 0 | AM7: =SUMIFS(Hh_EXE_TOTAL[Hh],Hh_EXE_TOTAL[Nº SS],TB_INTEGRADA[[#This Row],[Nº SS]],Hh_EXE_TOTAL[DISCIPLINA],"CIVIL") -> 0 | AN7: =IF(TB_INTEGRADA[[#This Row],[TOMADOR]]="EDIVIT",TB_INTEGRADA[[#This Row],[ORÇ DIG2]]*1.38,IF(TB_INTEGRADA[[#This Row],[TOMADOR]]="UTGC",TB_INTEGRADA[[#This Row],[ORÇ DIG2]]*1.47,IF(TB_INTEGRADA[[#This Row],[TOMADOR]]="TIMS",TB_INTEGRADA[[#This Row],[ORÇ DIG2]]*1.34,IF(TB_INTEGRADA[[#This Row],[TOMADOR]]="UTGSUL",TB_INTEGRADA[[#This Row],[ORÇ DIG2]]*1.37,IF(TB_INTEGRADA[[#This Row],[TOMADOR]]="REGAP",TB_INTEGRADA[[#This Row],[ORÇ DIG2]]*1.36,IF(TB_INTEGRADA[[#This Row],[TOMADOR]]="UTEIBI",TB_INTEGRADA[[#This Row],[ORÇ DIG2]]*1.5,"S/TOMADOR")))))) -> 0 | AP7: =SUMIFS(Tb_HhPLAN[Hh DISC],Tb_HhPLAN[SS],TB_INTEGRADA[[#This Row],[Nº SS]],Tb_HhPLAN[DISCIPLINA],"ELÉT") -> 0 | AQ7: =SUMIFS(Hh_EXE_TOTAL[Hh],Hh_EXE_TOTAL[Nº SS],TB_INTEGRADA[[#This Row],[Nº SS]],Hh_EXE_TOTAL[DISCIPLINA],"ELÉT") -> 0 | AR7: =IF(TB_INTEGRADA[[#This Row],[TOMADOR]]="EDIVIT",TB_INTEGRADA[[#This Row],[ORÇ DIG3]]*1.38,IF(TB_INTEGRADA[[#This Row],[TOMADOR]]="UTGC",TB_INTEGRADA[[#This Row],[ORÇ DIG3]]*1.47,IF(TB_INTEGRADA[[#This Row],[TOMADOR]]="TIMS",TB_INTEGRADA[[#This Row],[ORÇ DIG3]]*1.34,IF(TB_INTEGRADA[[#This Row],[TOMADOR]]="UTGSUL",TB_INTEGRADA[[#This Row],[ORÇ DIG3]]*1.37,IF(TB_INTEGRADA[[#This Row],[TOMADOR]]="REGAP",TB_INTEGRADA[[#This Row],[ORÇ DIG3]]*1.36,IF(TB_INTEGRADA[[#This Row],[TOMADOR]]="UTEIBI",TB_INTEGRADA[[#This Row],[ORÇ DIG3]]*1.5,"S/TOMADOR")))))) -> 0 | AT7: =SUMIFS(Tb_HhPLAN[Hh DISC],Tb_HhPLAN[SS],TB_INTEGRADA[[#This Row],[Nº SS]],Tb_HhPLAN[DISCIPLINA],"PINT") -> 0 | AU7: =SUMIFS(Hh_EXE_TOTAL[Hh],Hh_EXE_TOTAL[Nº SS],TB_INTEGRADA[[#This Row],[Nº SS]],Hh_EXE_TOTAL[DISCIPLINA],"PINT") -> 0 | AV7: =TB_INTEGRADA[[#This Row],[ORÇADO]]+TB_INTEGRADA[[#This Row],[ORÇADO1]]+TB_INTEGRADA[[#This Row],[ORÇADO2]]+TB_INTEGRADA[[#This Row],[ORÇADO3]] -> 0 | AW7: =TB_INTEGRADA[[#This Row],[PLANEJ]]+TB_INTEGRADA[[#This Row],[PLANEJ1]]+TB_INTEGRADA[[#This Row],[PLANEJ2]]+TB_INTEGRADA[[#This Row],[PLANEJ3]] -> 0 | AX7: =TB_INTEGRADA[[#This Row],[REALIZ]]+TB_INTEGRADA[[#This Row],[REALIZ1]]+TB_INTEGRADA[[#This Row],[REALIZ2]]+TB_INTEGRADA[[#This Row],[REALIZ3]] -> 0 | AZ7: =_xlfn.XLOOKUP(TB_INTEGRADA[[#This Row],[Nº SS]],'CONTROLE EC'!B:B,'CONTROLE EC'!W:W,"",0,1) -> 10320001 | BA7: =_xlfn.XLOOKUP(TB_INTEGRADA[[#This Row],[Nº SS]],'CONTROLE EC'!B:B,'CONTROLE EC'!X:X,"",0,1) -> 3321231.8 | BB7: =_xlfn.XLOOKUP(TB_INTEGRADA[[#This Row],[Nº SS]],'CONTROLE EC'!B:B,'CONTROLE EC'!Y:Y,"",0,1) -> 6998769.5
A8: =IF(COUNTIFS($B$5:B8,TB_INTEGRADA[[#This Row],[Nº SS]])<>1,"",COUNTIFS($B$5:B8,TB_INTEGRADA[[#This Row],[Nº SS]])) -> 1 | B8: SS-03/2025 | C8: =_xlfn.XLOOKUP(TB_INTEGRADA[[#This Row],[Nº SS]],'CONTROLE EC'!B:B,'CONTROLE EC'!C:C,"",0,1) -> -- IMPLANTAÇÃO ÁREA III (REGAP, UTE-IBT) | D8: =_xlfn.XLOOKUP(TB_INTEGRADA[[#This Row],[Nº SS]],'CONTROLE CRONOG'!B:B,'CONTROLE CRONOG'!D:D,"",0,1) -> ADM | E8: =_xlfn.XLOOKUP(TB_INTEGRADA[[#This Row],[Nº SS]],'CONTROLE EC'!B:B,'CONTROLE EC'!E:E,"",0,1) -> REGAP | F8: =_xlfn.XLOOKUP(TB_INTEGRADA[[#This Row],[Nº SS]],'CONTROLE EC'!B:B,'CONTROLE EC'!F:F,"",0,1) -> NÃO EMITIDA SAMC | G8: =_xlfn.XLOOKUP(TB_INTEGRADA[[#This Row],[Nº SS]],'CONTROLE EC'!B:B,'CONTROLE EC'!R:R,"",0,1) | H8: =IF(TB_INTEGRADA[[#This Row],[REVISÃO (EC)]]="","",_xlfn.XLOOKUP(TB_INTEGRADA[[#This Row],[Nº SS]],'CONTROLE EC'!B:B,'CONTROLE EC'!S:S,"",0,1)) | I8: =IF(TB_INTEGRADA[[#This Row],[REVISÃO (EC)]]="","",_xlfn.XLOOKUP(TB_INTEGRADA[[#This Row],[Nº SS]],'CONTROLE EC'!B:B,'CONTROLE EC'!U:U,"",0,1)) | J8: {=IF(TB_INTEGRADA[[#This Row],[DATA ENVIO. (EC)]]=IFERROR(INDEX('CONTROLE EC'!G8:Q8,MATCH(2,1/('CONTROLE EC'!G8:Q8<>""))),""),"",IFERROR(INDEX('CONTROLE EC'!G8:Q8,MATCH(2,1/('CONTROLE EC'!G8:Q8<>""))),""))} | K8: =IF(TB_INTEGRADA[[#This Row],[STATUS DEMANDA]]="NÃO EMITIDA SAMC","S/ EMISSÃO",_xlfn.XLOOKUP(TB_INTEGRADA[[#This Row],[Nº SS]],'CONTROLE EC'!B:B,'CONTROLE EC'!T:T,"",0,-1)) -> S/ EMISSÃO | L8: =IF(TB_INTEGRADA[[#This Row],[STATUS DEMANDA]]="NÃO EMITIDA SAMC","S/ EMISSÃO",IF(TB_INTEGRADA[[#This Row],[STATUS DEMANDA]]="ON HOLD","ON HOLD",IF(TB_INTEGRADA[[#This Row],[STATUS DEMANDA]]="CANCELADA","CANCELADA",IF(TB_INTEGRADA[[#This Row],[DATA APROV. (EC)]]=0,"FISCALIZ.",IF(TB_INTEGRADA[[#This Row],[DATA APROV. (EC)]]="","PEND. FISCALIZ.",IF(TB_INTEGRADA[[#This Row],[DATA APROV. (EC)]]="N/A","APROVADO",IF(TB_INTEGRADA[[#This Row],[REVISÃO (EC)]]="","",_xlfn.XLOOKUP(TB_INTEGRADA[[#This Row],[Nº SS]],'CONTROLE EC'!B:B,'CONTROLE EC'!V:V,"",0,1)))))))) -> S/ EMISSÃO | M8: {=IFERROR(_xlfn.IFS(TB_INTEGRADA[[#This Row],[STATUS DEMANDA]]="CANCELADA",0,TB_INTEGRADA[[#This Row],[DATA APROV. (EC)]]="",TODAY()-TB_INTEGRADA[[#This Row],[DATA ENVIO. (EC)]],TB_INTEGRADA[[#This Row],[DATA APROV. (EC)]]>=TB_INTEGRADA[[#This Row],[DATA ENVIO. (EC)]],0,TB_INTEGRADA[[#This Row],[DATA ENVIO. (EC)]]="",0,TB_INTEGRADA[[#This Row],[DATA ENVIO. (EC)]]>TB_INTEGRADA[[#This Row],[DATA APROV. (EC)]],TODAY()-TB_INTEGRADA[[#This Row],[DATA ENVIO. (EC)]]),"")} | N8: =IF(TB_INTEGRADA[[#This Row],[STATUS DEMANDA]]="NÃO EMITIDA SAMC","S/ EMISSÃO",IF(TB_INTEGRADA[[#This Row],[STATUS DEMANDA]]="ON HOLD","ON HOLD",IF(F8="CANCELADA","CANCELADA",IF(L8="REPROVADO","EM PLANEJ.",IF(K8<>"ENTREGUE","EM PLANEJ.",IF(H8="","EM PLANEJ.",IF(I8="","FISCALIZ.",IF(M8<0,"EM PLANEJ.",IF(TB_INTEGRADA[[#This Row],[DATA APROV. (EC)]]>=TB_INTEGRADA[[#This Row],[DATA ENVIO. (EC)]],"RETORNO OK","FISCALIZ."))))))))) -> S/ EMISSÃO | O8: =_xlfn.XLOOKUP(TB_INTEGRADA[[#This Row],[Nº SS]],'CONTROLE CRONOG'!B:B,'CONTROLE CRONOG'!R:R,"",0,1) | P8: =IF(TB_INTEGRADA[[#This Row],[REVISÃO (CR)]]="","",_xlfn.XLOOKUP(TB_INTEGRADA[[#This Row],[Nº SS]],'CONTROLE CRONOG'!B:B,'CONTROLE CRONOG'!S:S,"",0,1)) | Q8: =IF(TB_INTEGRADA[[#This Row],[REVISÃO (CR)]]="","",_xlfn.XLOOKUP(TB_INTEGRADA[[#This Row],[Nº SS]],'CONTROLE CRONOG'!B:B,'CONTROLE CRONOG'!U:U,"",0,1)) | R8: {=IF(TB_INTEGRADA[[#This Row],[DATA ENVIO. (CR)]]=IFERROR(INDEX('CONTROLE CRONOG'!G8:Q8,MATCH(2,1/('CONTROLE CRONOG'!G8:Q8<>""))),""),"",IFERROR(INDEX('CONTROLE CRONOG'!G8:Q8,MATCH(2,1/('CONTROLE CRONOG'!G8:Q8<>""))),""))} | S8: =_xlfn.XLOOKUP(TB_INTEGRADA[[#This Row],[Nº SS]],'CONTROLE CRONOG'!B:B,'CONTROLE CRONOG'!T:T,"",0,-1) -> PENDENTE | T8: =IF(TB_INTEGRADA[[#This Row],[STATUS DEMANDA]]="ON HOLD","ON HOLD",IF(TB_INTEGRADA[[#This Row],[STATUS DEMANDA]]="CANCELADA","CANCELADA",IF(TB_INTEGRADA[[#This Row],[DATA APROV. (CR)]]=0,"FISCALIZ.",IF(TB_INTEGRADA[[#This Row],[DATA APROV. (CR)]]="N/A","APROVADO",IF(TB_INTEGRADA[[#This Row],[REVISÃO (CR)]]="","",_xlfn.XLOOKUP(TB_INTEGRADA[[#This Row],[Nº SS]],'CONTROLE CRONOG'!B:B,'CONTROLE CRONOG'!V:V,"",0,1)))))) | X8: =IFERROR(TB_INTEGRADA[[#This Row],[TÉRM. TD]]-TB_INTEGRADA[[#This Row],[TÉRMINO LB]],0) -> 0 | AB8: =IFERROR(TB_INTEGRADA[[#This Row],[REAL (%)]]-TB_INTEGRADA[[#This Row],[PREV (%)]],0) -> 0 | AF8: =IF(TB_INTEGRADA[[#This Row],[TOMADOR]]="EDIVIT",TB_INTEGRADA[[#This Row],[ORÇ DIG]]*1.38,IF(TB_INTEGRADA[[#This Row],[TOMADOR]]="UTGC",TB_INTEGRADA[[#This Row],[ORÇ DIG]]*1.47,IF(TB_INTEGRADA[[#This Row],[TOMADOR]]="TIMS",TB_INTEGRADA[[#This Row],[ORÇ DIG]]*1.34,IF(TB_INTEGRADA[[#This Row],[TOMADOR]]="UTGSUL",TB_INTEGRADA[[#This Row],[ORÇ DIG]]*1.37,IF(TB_INTEGRADA[[#This Row],[TOMADOR]]="REGAP",TB_INTEGRADA[[#This Row],[ORÇ DIG]]*1.36,IF(TB_INTEGRADA[[#This Row],[TOMADOR]]="UTEIBI",TB_INTEGRADA[[#This Row],[ORÇ DIG]]*1.5,"S/TOMADOR")))))) -> 0 | AH8: =SUMIFS(Tb_HhPLAN[Hh DISC],Tb_HhPLAN[SS],TB_INTEGRADA[[#This Row],[Nº SS]],Tb_HhPLAN[DISCIPLINA],"MEC") -> 0 | AI8: =SUMIFS(Hh_EXE_TOTAL[Hh],Hh_EXE_TOTAL[Nº SS],TB_INTEGRADA[[#This Row],[Nº SS]],Hh_EXE_TOTAL[DISCIPLINA],"MEC") -> 0 | AJ8: =IF(TB_INTEGRADA[[#This Row],[TOMADOR]]="EDIVIT",TB_INTEGRADA[[#This Row],[ORÇ DIG1]]*1.38,IF(TB_INTEGRADA[[#This Row],[TOMADOR]]="UTGC",TB_INTEGRADA[[#This Row],[ORÇ DIG1]]*1.47,IF(TB_INTEGRADA[[#This Row],[TOMADOR]]="TIMS",TB_INTEGRADA[[#This Row],[ORÇ DIG1]]*1.34,IF(TB_INTEGRADA[[#This Row],[TOMADOR]]="UTGSUL",TB_INTEGRADA[[#This Row],[ORÇ DIG1]]*1.37,IF(TB_INTEGRADA[[#This Row],[TOMADOR]]="REGAP",TB_INTEGRADA[[#This Row],[ORÇ DIG1]]*1.36,IF(TB_INTEGRADA[[#This Row],[TOMADOR]]="UTEIBI",TB_INTEGRADA[[#This Row],[ORÇ DIG1]]*1.5,"S/TOMADOR")))))) -> 0 | AL8: =SUMIFS(Tb_HhPLAN[Hh DISC],Tb_HhPLAN[SS],TB_INTEGRADA[[#This Row],[Nº SS]],Tb_HhPLAN[DISCIPLINA],"CIVIL") -> 0 | AM8: =SUMIFS(Hh_EXE_TOTAL[Hh],Hh_EXE_TOTAL[Nº SS],TB_INTEGRADA[[#This Row],[Nº SS]],Hh_EXE_TOTAL[DISCIPLINA],"CIVIL") -> 0 | AN8: =IF(TB_INTEGRADA[[#This Row],[TOMADOR]]="EDIVIT",TB_INTEGRADA[[#This Row],[ORÇ DIG2]]*1.38,IF(TB_INTEGRADA[[#This Row],[TOMADOR]]="UTGC",TB_INTEGRADA[[#This Row],[ORÇ DIG2]]*1.47,IF(TB_INTEGRADA[[#This Row],[TOMADOR]]="TIMS",TB_INTEGRADA[[#This Row],[ORÇ DIG2]]*1.34,IF(TB_INTEGRADA[[#This Row],[TOMADOR]]="UTGSUL",TB_INTEGRADA[[#This Row],[ORÇ DIG2]]*1.37,IF(TB_INTEGRADA[[#This Row],[TOMADOR]]="REGAP",TB_INTEGRADA[[#This Row],[ORÇ DIG2]]*1.36,IF(TB_INTEGRADA[[#This Row],[TOMADOR]]="UTEIBI",TB_INTEGRADA[[#This Row],[ORÇ DIG2]]*1.5,"S/TOMADOR")))))) -> 0 | AP8: =SUMIFS(Tb_HhPLAN[Hh DISC],Tb_HhPLAN[SS],TB_INTEGRADA[[#This Row],[Nº SS]],Tb_HhPLAN[DISCIPLINA],"ELÉT") -> 0 | AQ8: =SUMIFS(Hh_EXE_TOTAL[Hh],Hh_EXE_TOTAL[Nº SS],TB_INTEGRADA[[#This Row],[Nº SS]],Hh_EXE_TOTAL[DISCIPLINA],"ELÉT") -> 0 | AR8: =IF(TB_INTEGRADA[[#This Row],[TOMADOR]]="EDIVIT",TB_INTEGRADA[[#This Row],[ORÇ DIG3]]*1.38,IF(TB_INTEGRADA[[#This Row],[TOMADOR]]="UTGC",TB_INTEGRADA[[#This Row],[ORÇ DIG3]]*1.47,IF(TB_INTEGRADA[[#This Row],[TOMADOR]]="TIMS",TB_INTEGRADA[[#This Row],[ORÇ DIG3]]*1.34,IF(TB_INTEGRADA[[#This Row],[TOMADOR]]="UTGSUL",TB_INTEGRADA[[#This Row],[ORÇ DIG3]]*1.37,IF(TB_INTEGRADA[[#This Row],[TOMADOR]]="REGAP",TB_INTEGRADA[[#This Row],[ORÇ DIG3]]*1.36,IF(TB_INTEGRADA[[#This Row],[TOMADOR]]="UTEIBI",TB_INTEGRADA[[#This Row],[ORÇ DIG3]]*1.5,"S/TOMADOR")))))) -> 0 | AT8: =SUMIFS(Tb_HhPLAN[Hh DISC],Tb_HhPLAN[SS],TB_INTEGRADA[[#This Row],[Nº SS]],Tb_HhPLAN[DISCIPLINA],"PINT") -> 0 | AU8: =SUMIFS(Hh_EXE_TOTAL[Hh],Hh_EXE_TOTAL[Nº SS],TB_INTEGRADA[[#This Row],[Nº SS]],Hh_EXE_TOTAL[DISCIPLINA],"PINT") -> 0 | AV8: =TB_INTEGRADA[[#This Row],[ORÇADO]]+TB_INTEGRADA[[#This Row],[ORÇADO1]]+TB_INTEGRADA[[#This Row],[ORÇADO2]]+TB_INTEGRADA[[#This Row],[ORÇADO3]] -> 0 | AW8: =TB_INTEGRADA[[#This Row],[PLANEJ]]+TB_INTEGRADA[[#This Row],[PLANEJ1]]+TB_INTEGRADA[[#This Row],[PLANEJ2]]+TB_INTEGRADA[[#This Row],[PLANEJ3]] -> 0 | AX8: =TB_INTEGRADA[[#This Row],[REALIZ]]+TB_INTEGRADA[[#This Row],[REALIZ1]]+TB_INTEGRADA[[#This Row],[REALIZ2]]+TB_INTEGRADA[[#This Row],[REALIZ3]] -> 0 | AZ8: =_xlfn.XLOOKUP(TB_INTEGRADA[[#This Row],[Nº SS]],'CONTROLE EC'!B:B,'CONTROLE EC'!W:W,"",0,1) -> 0 | BA8: =_xlfn.XLOOKUP(TB_INTEGRADA[[#This Row],[Nº SS]],'CONTROLE EC'!B:B,'CONTROLE EC'!X:X,"",0,1) -> 0 | BB8: =_xlfn.XLOOKUP(TB_INTEGRADA[[#This Row],[Nº SS]],'CONTROLE EC'!B:B,'CONTROLE EC'!Y:Y,"",0,1) -> 0
A9: =IF(COUNTIFS($B$5:B9,TB_INTEGRADA[[#This Row],[Nº SS]])<>1,"",COUNTIFS($B$5:B9,TB_INTEGRADA[[#This Row],[Nº SS]])) -> 1 | B9: SS-04/2025 | C9: =_xlfn.XLOOKUP(TB_INTEGRADA[[#This Row],[Nº SS]],'CONTROLE EC'!B:B,'CONTROLE EC'!C:C,"",0,1) -> 24-0651-ES - MONTAGEM DO GALPÃO DA UPGN-2 | D9: =_xlfn.XLOOKUP(TB_INTEGRADA[[#This Row],[Nº SS]],'CONTROLE CRONOG'!B:B,'CONTROLE CRONOG'!D:D,"",0,1) -> SERVIÇO | E9: =_xlfn.XLOOKUP(TB_INTEGRADA[[#This Row],[Nº SS]],'CONTROLE EC'!B:B,'CONTROLE EC'!E:E,"",0,1) -> UTGC | F9: =_xlfn.XLOOKUP(TB_INTEGRADA[[#This Row],[Nº SS]],'CONTROLE EC'!B:B,'CONTROLE EC'!F:F,"",0,1) -> EM ANDAMENTO | G9: =_xlfn.XLOOKUP(TB_INTEGRADA[[#This Row],[Nº SS]],'CONTROLE EC'!B:B,'CONTROLE EC'!R:R,"",0,1) -> REV.05 | H9: =IF(TB_INTEGRADA[[#This Row],[REVISÃO (EC)]]="","",_xlfn.XLOOKUP(TB_INTEGRADA[[#This Row],[Nº SS]],'CONTROLE EC'!B:B,'CONTROLE EC'!S:S,"",0,1)) -> 45953 | I9: =IF(TB_INTEGRADA[[#This Row],[REVISÃO (EC)]]="","",_xlfn.XLOOKUP(TB_INTEGRADA[[#This Row],[Nº SS]],'CONTROLE EC'!B:B,'CONTROLE EC'!U:U,"",0,1)) -> 45954 | J9: {=IF(TB_INTEGRADA[[#This Row],[DATA ENVIO. (EC)]]=IFERROR(INDEX('CONTROLE EC'!G9:Q9,MATCH(2,1/('CONTROLE EC'!G9:Q9<>""))),""),"",IFERROR(INDEX('CONTROLE EC'!G9:Q9,MATCH(2,1/('CONTROLE EC'!G9:Q9<>""))),""))} | K9: =IF(TB_INTEGRADA[[#This Row],[STATUS DEMANDA]]="NÃO EMITIDA SAMC","S/ EMISSÃO",_xlfn.XLOOKUP(TB_INTEGRADA[[#This Row],[Nº SS]],'CONTROLE EC'!B:B,'CONTROLE EC'!T:T,"",0,-1)) -> ENTREGUE | L9: =IF(TB_INTEGRADA[[#This Row],[STATUS DEMANDA]]="NÃO EMITIDA SAMC","S/ EMISSÃO",IF(TB_INTEGRADA[[#This Row],[STATUS DEMANDA]]="ON HOLD","ON HOLD",IF(TB_INTEGRADA[[#This Row],[STATUS DEMANDA]]="CANCELADA","CANCELADA",IF(TB_INTEGRADA[[#This Row],[DATA APROV. (EC)]]=0,"FISCALIZ.",IF(TB_INTEGRADA[[#This Row],[DATA APROV. (EC)]]="","PEND. FISCALIZ.",IF(TB_INTEGRADA[[#This Row],[DATA APROV. (EC)]]="N/A","APROVADO",IF(TB_INTEGRADA[[#This Row],[REVISÃO (EC)]]="","",_xlfn.XLOOKUP(TB_INTEGRADA[[#This Row],[Nº SS]],'CONTROLE EC'!B:B,'CONTROLE EC'!V:V,"",0,1)))))))) -> APROVADO | M9: {=IFERROR(_xlfn.IFS(TB_INTEGRADA[[#This Row],[STATUS DEMANDA]]="CANCELADA",0,TB_INTEGRADA[[#This Row],[DATA APROV. (EC)]]="",TODAY()-TB_INTEGRADA[[#This Row],[DATA ENVIO. (EC)]],TB_INTEGRADA[[#This Row],[DATA APROV. (EC)]]>=TB_INTEGRADA[[#This Row],[DATA ENVIO. (EC)]],0,TB_INTEGRADA[[#This Row],[DATA ENVIO. (EC)]]="",0,TB_INTEGRADA[[#This Row],[DATA ENVIO. (EC)]]>TB_INTEGRADA[[#This Row],[DATA APROV. (EC)]],TODAY()-TB_INTEGRADA[[#This Row],[DATA ENVIO. (EC)]]),"")} -> 0 | N9: =IF(TB_INTEGRADA[[#This Row],[STATUS DEMANDA]]="NÃO EMITIDA SAMC","S/ EMISSÃO",IF(TB_INTEGRADA[[#This Row],[STATUS DEMANDA]]="ON HOLD","ON HOLD",IF(F9="CANCELADA","CANCELADA",IF(L9="REPROVADO","EM PLANEJ.",IF(K9<>"ENTREGUE","EM PLANEJ.",IF(H9="","EM PLANEJ.",IF(I9="","FISCALIZ.",IF(M9<0,"EM PLANEJ.",IF(TB_INTEGRADA[[#This Row],[DATA APROV. (EC)]]>=TB_INTEGRADA[[#This Row],[DATA ENVIO. (EC)]],"RETORNO OK","FISCALIZ."))))))))) -> RETORNO OK | O9: =_xlfn.XLOOKUP(TB_INTEGRADA[[#This Row],[Nº SS]],'CONTROLE CRONOG'!B:B,'CONTROLE CRONOG'!R:R,"",0,1) -> REV.03 | P9: =IF(TB_INTEGRADA[[#This Row],[REVISÃO (CR)]]="","",_xlfn.XLOOKUP(TB_INTEGRADA[[#This Row],[Nº SS]],'CONTROLE CRONOG'!B:B,'CONTROLE CRONOG'!S:S,"",0,1)) -> 45953 | Q9: =IF(TB_INTEGRADA[[#This Row],[REVISÃO (CR)]]="","",_xlfn.XLOOKUP(TB_INTEGRADA[[#This Row],[Nº SS]],'CONTROLE CRONOG'!B:B,'CONTROLE CRONOG'!U:U,"",0,1)) -> 45953 | R9: {=IF(TB_INTEGRADA[[#This Row],[DATA ENVIO. (CR)]]=IFERROR(INDEX('CONTROLE CRONOG'!G9:Q9,MATCH(2,1/('CONTROLE CRONOG'!G9:Q9<>""))),""),"",IFERROR(INDEX('CONTROLE CRONOG'!G9:Q9,MATCH(2,1/('CONTROLE CRONOG'!G9:Q9<>""))),""))} | S9: =_xlfn.XLOOKUP(TB_INTEGRADA[[#This Row],[Nº SS]],'CONTROLE CRONOG'!B:B,'CONTROLE CRONOG'!T:T,"",0,-1) -> ENTREGUE | T9: =IF(TB_INTEGRADA[[#This Row],[STATUS DEMANDA]]="ON HOLD","ON HOLD",IF(TB_INTEGRADA[[#This Row],[STATUS DEMANDA]]="CANCELADA","CANCELADA",IF(TB_INTEGRADA[[#This Row],[DATA APROV. (CR)]]=0,"FISCALIZ.",IF(TB_INTEGRADA[[#This Row],[DATA APROV. (CR)]]="N/A","APROVADO",IF(TB_INTEGRADA[[#This Row],[REVISÃO (CR)]]="","",_xlfn.XLOOKUP(TB_INTEGRADA[[#This Row],[Nº SS]],'CONTROLE CRONOG'!B:B,'CONTROLE CRONOG'!V:V,"",0,1)))))) -> APROVADO | V9: 46197 | W9: 46198 | X9: =IFERROR(TB_INTEGRADA[[#This Row],[TÉRM. TD]]-TB_INTEGRADA[[#This Row],[TÉRMINO LB]],0) -> 1 | Y9: 0.4484 | Z9: 0.4219 | AA9: -0.0152 | AB9: =IFERROR(TB_INTEGRADA[[#This Row],[REAL (%)]]-TB_INTEGRADA[[#This Row],[PREV (%)]],0) -> -0.0265 | AC9: 6 | AD9: 16 | AF9: =IF(TB_INTEGRADA[[#This Row],[TOMADOR]]="EDIVIT",TB_INTEGRADA[[#This Row],[ORÇ DIG]]*1.38,IF(TB_INTEGRADA[[#This Row],[TOMADOR]]="UTGC",TB_INTEGRADA[[#This Row],[ORÇ DIG]]*1.47,IF(TB_INTEGRADA[[#This Row],[TOMADOR]]="TIMS",TB_INTEGRADA[[#This Row],[ORÇ DIG]]*1.34,IF(TB_INTEGRADA[[#This Row],[TOMADOR]]="UTGSUL",TB_INTEGRADA[[#This Row],[ORÇ DIG]]*1.37,IF(TB_INTEGRADA[[#This Row],[TOMADOR]]="REGAP",TB_INTEGRADA[[#This Row],[ORÇ DIG]]*1.36,IF(TB_INTEGRADA[[#This Row],[TOMADOR]]="UTEIBI",TB_INTEGRADA[[#This Row],[ORÇ DIG]]*1.5,"S/TOMADOR")))))) -> 8862.4242 | AG9: 6028.86 | AH9: =SUMIFS(Tb_HhPLAN[Hh DISC],Tb_HhPLAN[SS],TB_INTEGRADA[[#This Row],[Nº SS]],Tb_HhPLAN[DISCIPLINA],"MEC") -> 5356.0441 | AI9: =SUMIFS(Hh_EXE_TOTAL[Hh],Hh_EXE_TOTAL[Nº SS],TB_INTEGRADA[[#This Row],[Nº SS]],Hh_EXE_TOTAL[DISCIPLINA],"MEC") -> 4618.2781 | AJ9: =IF(TB_INTEGRADA[[#This Row],[TOMADOR]]="EDIVIT",TB_INTEGRADA[[#This Row],[ORÇ DIG1]]*1.38,IF(TB_INTEGRADA[[#This Row],[TOMADOR]]="UTGC",TB_INTEGRADA[[#This Row],[ORÇ DIG1]]*1.47,IF(TB_INTEGRADA[[#This Row],[TOMADOR]]="TIMS",TB_INTEGRADA[[#This Row],[ORÇ DIG1]]*1.34,IF(TB_INTEGRADA[[#This Row],[TOMADOR]]="UTGSUL",TB_INTEGRADA[[#This Row],[ORÇ DIG1]]*1.37,IF(TB_INTEGRADA[[#This Row],[TOMADOR]]="REGAP",TB_INTEGRADA[[#This Row],[ORÇ DIG1]]*1.36,IF(TB_INTEGRADA[[#This Row],[TOMADOR]]="UTEIBI",TB_INTEGRADA[[#This Row],[ORÇ DIG1]]*1.5,"S/TOMADOR")))))) -> 92.4483 | AK9: 62.89 | AL9: =SUMIFS(Tb_HhPLAN[Hh DISC],Tb_HhPLAN[SS],TB_INTEGRADA[[#This Row],[Nº SS]],Tb_HhPLAN[DISCIPLINA],"CIVIL") -> 641.89229 | AM9: =SUMIFS(Hh_EXE_TOTAL[Hh],Hh_EXE_TOTAL[Nº SS],TB_INTEGRADA[[#This Row],[Nº SS]],Hh_EXE_TOTAL[DISCIPLINA],"CIVIL") -> 70.278146 | AN9: =IF(TB_INTEGRADA[[#This Row],[TOMADOR]]="EDIVIT",TB_INTEGRADA[[#This Row],[ORÇ DIG2]]*1.38,IF(TB_INTEGRADA[[#This Row],[TOMADOR]]="UTGC",TB_INTEGRADA[[#This Row],[ORÇ DIG2]]*1.47,IF(TB_INTEGRADA[[#This Row],[TOMADOR]]="TIMS",TB_INTEGRADA[[#This Row],[ORÇ DIG2]]*1.34,IF(TB_INTEGRADA[[#This Row],[TOMADOR]]="UTGSUL",TB_INTEGRADA[[#This Row],[ORÇ DIG2]]*1.37,IF(TB_INTEGRADA[[#This Row],[TOMADOR]]="REGAP",TB_INTEGRADA[[#This Row],[ORÇ DIG2]]*1.36,IF(TB_INTEGRADA[[#This Row],[TOMADOR]]="UTEIBI",TB_INTEGRADA[[#This Row],[ORÇ DIG2]]*1.5,"S/TOMADOR")))))) -> 3410.2383 | AO9: 2319.89 | AP9: =SUMIFS(Tb_HhPLAN[Hh DISC],Tb_HhPLAN[SS],TB_INTEGRADA[[#This Row],[Nº SS]],Tb_HhPLAN[DISCIPLINA],"ELÉT") -> 671.06922 | AQ9: =SUMIFS(Hh_EXE_TOTAL[Hh],Hh_EXE_TOTAL[Nº SS],TB_INTEGRADA[[#This Row],[Nº SS]],Hh_EXE_TOTAL[DISCIPLINA],"ELÉT") -> 421.66887 | AR9: =IF(TB_INTEGRADA[[#This Row],[TOMADOR]]="EDIVIT",TB_INTEGRADA[[#This Row],[ORÇ DIG3]]*1.38,IF(TB_INTEGRADA[[#This Row],[TOMADOR]]="UTGC",TB_INTEGRADA[[#This Row],[ORÇ DIG3]]*1.47,IF(TB_INTEGRADA[[#This Row],[TOMADOR]]="TIMS",TB_INTEGRADA[[#This Row],[ORÇ DIG3]]*1.34,IF(TB_INTEGRADA[[#This Row],[TOMADOR]]="UTGSUL",TB_INTEGRADA[[#This Row],[ORÇ DIG3]]*1.37,IF(TB_INTEGRADA[[#This Row],[TOMADOR]]="REGAP",TB_INTEGRADA[[#This Row],[ORÇ DIG3]]*1.36,IF(TB_INTEGRADA[[#This Row],[TOMADOR]]="UTEIBI",TB_INTEGRADA[[#This Row],[ORÇ DIG3]]*1.5,"S/TOMADOR")))))) -> 10374.54 | AS9: 7057.51 | AT9: =SUMIFS(Tb_HhPLAN[Hh DISC],Tb_HhPLAN[SS],TB_INTEGRADA[[#This Row],[Nº SS]],Tb_HhPLAN[DISCIPLINA],"PINT") -> 2447.2144 | AU9: =SUMIFS(Hh_EXE_TOTAL[Hh],Hh_EXE_TOTAL[Nº SS],TB_INTEGRADA[[#This Row],[Nº SS]],Hh_EXE_TOTAL[DISCIPLINA],"PINT") -> 953.77483 | AV9: =TB_INTEGRADA[[#This Row],[ORÇADO]]+TB_INTEGRADA[[#This Row],[ORÇADO1]]+TB_INTEGRADA[[#This Row],[ORÇADO2]]+TB_INTEGRADA[[#This Row],[ORÇADO3]] -> 22739.65 | AW9: =TB_INTEGRADA[[#This Row],[PLANEJ]]+TB_INTEGRADA[[#This Row],[PLANEJ1]]+TB_INTEGRADA[[#This Row],[PLANEJ2]]+TB_INTEGRADA[[#This Row],[PLANEJ3]] -> 9116.22 | AX9: =TB_INTEGRADA[[#This Row],[REALIZ]]+TB_INTEGRADA[[#This Row],[REALIZ1]]+TB_INTEGRADA[[#This Row],[REALIZ2]]+TB_INTEGRADA[[#This Row],[REALIZ3]] -> 6064 | AY9: =IFERROR(TB_INTEGRADA[[#This Row],[REALIZ4]]/TB_INTEGRADA[[#This Row],[ORÇADO4]],"") -> 0.26667077 | AZ9: =_xlfn.XLOOKUP(TB_INTEGRADA[[#This Row],[Nº SS]],'CONTROLE EC'!B:B,'CONTROLE EC'!W:W,"",0,1) -> 9201249.3 | BA9: =_xlfn.XLOOKUP(TB_INTEGRADA[[#This Row],[Nº SS]],'CONTROLE EC'!B:B,'CONTROLE EC'!X:X,"",0,1) -> 4922668.3 | BB9: =_xlfn.XLOOKUP(TB_INTEGRADA[[#This Row],[Nº SS]],'CONTROLE EC'!B:B,'CONTROLE EC'!Y:Y,"",0,1) -> 4278581
A10: =IF(COUNTIFS($B$5:B10,TB_INTEGRADA[[#This Row],[Nº SS]])<>1,"",COUNTIFS($B$5:B10,TB_INTEGRADA[[#This Row],[Nº SS]])) -> 1 | B10: SS-05/2025 | C10: =_xlfn.XLOOKUP(TB_INTEGRADA[[#This Row],[Nº SS]],'CONTROLE EC'!B:B,'CONTROLE EC'!C:C,"",0,1) -> 23-0706-ES - MANUTENÇÃO DO GALPÃO SECGN | D10: =_xlfn.XLOOKUP(TB_INTEGRADA[[#This Row],[Nº SS]],'CONTROLE CRONOG'!B:B,'CONTROLE CRONOG'!D:D,"",0,1) -> SERVIÇO | E10: =_xlfn.XLOOKUP(TB_INTEGRADA[[#This Row],[Nº SS]],'CONTROLE EC'!B:B,'CONTROLE EC'!E:E,"",0,1) -> UTGC | F10: =_xlfn.XLOOKUP(TB_INTEGRADA[[#This Row],[Nº SS]],'CONTROLE EC'!B:B,'CONTROLE EC'!F:F,"",0,1) -> CONCLUÍDA | G10: =_xlfn.XLOOKUP(TB_INTEGRADA[[#This Row],[Nº SS]],'CONTROLE EC'!B:B,'CONTROLE EC'!R:R,"",0,1) -> REV.03 | H10: =IF(TB_INTEGRADA[[#This Row],[REVISÃO (EC)]]="","",_xlfn.XLOOKUP(TB_INTEGRADA[[#This Row],[Nº SS]],'CONTROLE EC'!B:B,'CONTROLE EC'!S:S,"",0,1)) -> 45932 | I10: =IF(TB_INTEGRADA[[#This Row],[REVISÃO (EC)]]="","",_xlfn.XLOOKUP(TB_INTEGRADA[[#This Row],[Nº SS]],'CONTROLE EC'!B:B,'CONTROLE EC'!U:U,"",0,1)) -> 45932 | J10: {=IF(TB_INTEGRADA[[#This Row],[DATA ENVIO. (EC)]]=IFERROR(INDEX('CONTROLE EC'!G10:Q10,MATCH(2,1/('CONTROLE EC'!G10:Q10<>""))),""),"",IFERROR(INDEX('CONTROLE EC'!G10:Q10,MATCH(2,1/('CONTROLE EC'!G10:Q10<>""))),""))} | K10: =IF(TB_INTEGRADA[[#This Row],[STATUS DEMANDA]]="NÃO EMITIDA SAMC","S/ EMISSÃO",_xlfn.XLOOKUP(TB_INTEGRADA[[#This Row],[Nº SS]],'CONTROLE EC'!B:B,'CONTROLE EC'!T:T,"",0,-1)) -> ENTREGUE | L10: =IF(TB_INTEGRADA[[#This Row],[STATUS DEMANDA]]="NÃO EMITIDA SAMC","S/ EMISSÃO",IF(TB_INTEGRADA[[#This Row],[STATUS DEMANDA]]="ON HOLD","ON HOLD",IF(TB_INTEGRADA[[#This Row],[STATUS DEMANDA]]="CANCELADA","CANCELADA",IF(TB_INTEGRADA[[#This Row],[DATA APROV. (EC)]]=0,"FISCALIZ.",IF(TB_INTEGRADA[[#This Row],[DATA APROV. (EC)]]="","PEND. FISCALIZ.",IF(TB_INTEGRADA[[#This Row],[DATA APROV. (EC)]]="N/A","APROVADO",IF(TB_INTEGRADA[[#This Row],[REVISÃO (EC)]]="","",_xlfn.XLOOKUP(TB_INTEGRADA[[#This Row],[Nº SS]],'CONTROLE EC'!B:B,'CONTROLE EC'!V:V,"",0,1)))))))) -> APROVADO | M10: {=IFERROR(_xlfn.IFS(TB_INTEGRADA[[#This Row],[STATUS DEMANDA]]="CANCELADA",0,TB_INTEGRADA[[#This Row],[DATA APROV. (EC)]]="",TODAY()-TB_INTEGRADA[[#This Row],[DATA ENVIO. (EC)]],TB_INTEGRADA[[#This Row],[DATA APROV. (EC)]]>=TB_INTEGRADA[[#This Row],[DATA ENVIO. (EC)]],0,TB_INTEGRADA[[#This Row],[DATA ENVIO. (EC)]]="",0,TB_INTEGRADA[[#This Row],[DATA ENVIO. (EC)]]>TB_INTEGRADA[[#This Row],[DATA APROV. (EC)]],TODAY()-TB_INTEGRADA[[#This Row],[DATA ENVIO. (EC)]]),"")} -> 0 | N10: =IF(TB_INTEGRADA[[#This Row],[STATUS DEMANDA]]="NÃO EMITIDA SAMC","S/ EMISSÃO",IF(TB_INTEGRADA[[#This Row],[STATUS DEMANDA]]="ON HOLD","ON HOLD",IF(F10="CANCELADA","CANCELADA",IF(L10="REPROVADO","EM PLANEJ.",IF(K10<>"ENTREGUE","EM PLANEJ.",IF(H10="","EM PLANEJ.",IF(I10="","FISCALIZ.",IF(M10<0,"EM PLANEJ.",IF(TB_INTEGRADA[[#This Row],[DATA APROV. (EC)]]>=TB_INTEGRADA[[#This Row],[DATA ENVIO. (EC)]],"RETORNO OK","FISCALIZ."))))))))) -> RETORNO OK | O10: =_xlfn.XLOOKUP(TB_INTEGRADA[[#This Row],[Nº SS]],'CONTROLE CRONOG'!B:B,'CONTROLE CRONOG'!R:R,"",0,1) -> REV.01 | P10: =IF(TB_INTEGRADA[[#This Row],[REVISÃO (CR)]]="","",_xlfn.XLOOKUP(TB_INTEGRADA[[#This Row],[Nº SS]],'CONTROLE CRONOG'!B:B,'CONTROLE CRONOG'!S:S,"",0,1)) -> 45925 | Q10: =IF(TB_INTEGRADA[[#This Row],[REVISÃO (CR)]]="","",_xlfn.XLOOKUP(TB_INTEGRADA[[#This Row],[Nº SS]],'CONTROLE CRONOG'!B:B,'CONTROLE CRONOG'!U:U,"",0,1)) -> 45925 | R10: {=IF(TB_INTEGRADA[[#This Row],[DATA ENVIO. (CR)]]=IFERROR(INDEX('CONTROLE CRONOG'!G10:Q10,MATCH(2,1/('CONTROLE CRONOG'!G10:Q10<>""))),""),"",IFERROR(INDEX('CONTROLE CRONOG'!G10:Q10,MATCH(2,1/('CONTROLE CRONOG'!G10:Q10<>""))),""))} | S10: =_xlfn.XLOOKUP(TB_INTEGRADA[[#This Row],[Nº SS]],'CONTROLE CRONOG'!B:B,'CONTROLE CRONOG'!T:T,"",0,-1) -> ENTREGUE | T10: =IF(TB_INTEGRADA[[#This Row],[STATUS DEMANDA]]="ON HOLD","ON HOLD",IF(TB_INTEGRADA[[#This Row],[STATUS DEMANDA]]="CANCELADA","CANCELADA",IF(TB_INTEGRADA[[#This Row],[DATA APROV. (CR)]]=0,"FISCALIZ.",IF(TB_INTEGRADA[[#This Row],[DATA APROV. (CR)]]="N/A","APROVADO",IF(TB_INTEGRADA[[#This Row],[REVISÃO (CR)]]="","",_xlfn.XLOOKUP(TB_INTEGRADA[[#This Row],[Nº SS]],'CONTROLE CRONOG'!B:B,'CONTROLE CRONOG'!V:V,"",0,1)))))) -> APROVADO | V10: 46009 | W10: 46059 | X10: =IFERROR(TB_INTEGRADA[[#This Row],[TÉRM. TD]]-TB_INTEGRADA[[#This Row],[TÉRMINO LB]],0) -> 50 | Y10: 1 | Z10: 1 | AA10: 0 | AB10: =IFERROR(TB_INTEGRADA[[#This Row],[REAL (%)]]-TB_INTEGRADA[[#This Row],[PREV (%)]],0) -> 0 | AC10: 0 | AD10: 0 | AF10: =IF(TB_INTEGRADA[[#This Row],[TOMADOR]]="EDIVIT",TB_INTEGRADA[[#This Row],[ORÇ DIG]]*1.38,IF(TB_INTEGRADA[[#This Row],[TOMADOR]]="UTGC",TB_INTEGRADA[[#This Row],[ORÇ DIG]]*1.47,IF(TB_INTEGRADA[[#This Row],[TOMADOR]]="TIMS",TB_INTEGRADA[[#This Row],[ORÇ DIG]]*1.34,IF(TB_INTEGRADA[[#This Row],[TOMADOR]]="UTGSUL",TB_INTEGRADA[[#This Row],[ORÇ DIG]]*1.37,IF(TB_INTEGRADA[[#This Row],[TOMADOR]]="REGAP",TB_INTEGRADA[[#This Row],[ORÇ DIG]]*1.36,IF(TB_INTEGRADA[[#This Row],[TOMADOR]]="UTEIBI",TB_INTEGRADA[[#This Row],[ORÇ DIG]]*1.5,"S/TOMADOR")))))) -> 1119.3168 | AG10: 761.44 | AH10: =SUMIFS(Tb_HhPLAN[Hh DISC],Tb_HhPLAN[SS],TB_INTEGRADA[[#This Row],[Nº SS]],Tb_HhPLAN[DISCIPLINA],"MEC") -> 1392 | AI10: =SUMIFS(Hh_EXE_TOTAL[Hh],Hh_EXE_TOTAL[Nº SS],TB_INTEGRADA[[#This Row],[Nº SS]],Hh_EXE_TOTAL[DISCIPLINA],"MEC") -> 3037.0892 | AJ10: =IF(TB_INTEGRADA[[#This Row],[TOMADOR]]="EDIVIT",TB_INTEGRADA[[#This Row],[ORÇ DIG1]]*1.38,IF(TB_INTEGRADA[[#This Row],[TOMADOR]]="UTGC",TB_INTEGRADA[[#This Row],[ORÇ DIG1]]*1.47,IF(TB_INTEGRADA[[#This Row],[TOMADOR]]="TIMS",TB_INTEGRADA[[#This Row],[ORÇ DIG1]]*1.34,IF(TB_INTEGRADA[[#This Row],[TOMADOR]]="UTGSUL",TB_INTEGRADA[[#This Row],[ORÇ DIG1]]*1.37,IF(TB_INTEGRADA[[#This Row],[TOMADOR]]="REGAP",TB_INTEGRADA[[#This Row],[ORÇ DIG1]]*1.36,IF(TB_INTEGRADA[[#This Row],[TOMADOR]]="UTEIBI",TB_INTEGRADA[[#This Row],[ORÇ DIG1]]*1.5,"S/TOMADOR")))))) -> 0 | AK10: 0 | AL10: =SUMIFS(Tb_HhPLAN[Hh DISC],Tb_HhPLAN[SS],TB_INTEGRADA[[#This Row],[Nº SS]],Tb_HhPLAN[DISCIPLINA],"CIVIL") -> 0 | AM10: =SUMIFS(Hh_EXE_TOTAL[Hh],Hh_EXE_TOTAL[Nº SS],TB_INTEGRADA[[#This Row],[Nº SS]],Hh_EXE_TOTAL[DISCIPLINA],"CIVIL") -> 38.322892 | AN10: =IF(TB_INTEGRADA[[#This Row],[TOMADOR]]="EDIVIT",TB_INTEGRADA[[#This Row],[ORÇ DIG2]]*1.38,IF(TB_INTEGRADA[[#This Row],[TOMADOR]]="UTGC",TB_INTEGRADA[[#This Row],[ORÇ DIG2]]*1.47,IF(TB_INTEGRADA[[#This Row],[TOMADOR]]="TIMS",TB_INTEGRADA[[#This Row],[ORÇ DIG2]]*1.34,IF(TB_INTEGRADA[[#This Row],[TOMADOR]]="UTGSUL",TB_INTEGRADA[[#This Row],[ORÇ DIG2]]*1.37,IF(TB_INTEGRADA[[#This Row],[TOMADOR]]="REGAP",TB_INTEGRADA[[#This Row],[ORÇ DIG2]]*1.36,IF(TB_INTEGRADA[[#This Row],[TOMADOR]]="UTEIBI",TB_INTEGRADA[[#This Row],[ORÇ DIG2]]*1.5,"S/TOMADOR")))))) -> 1160.124 | AO10: 789.2 | AP10: =SUMIFS(Tb_HhPLAN[Hh DISC],Tb_HhPLAN[SS],TB_INTEGRADA[[#This Row],[Nº SS]],Tb_HhPLAN[DISCIPLINA],"ELÉT") -> 264 | AQ10: =SUMIFS(Hh_EXE_TOTAL[Hh],Hh_EXE_TOTAL[Nº SS],TB_INTEGRADA[[#This Row],[Nº SS]],Hh_EXE_TOTAL[DISCIPLINA],"ELÉT") -> 584.4241 | AR10: =IF(TB_INTEGRADA[[#This Row],[TOMADOR]]="EDIVIT",TB_INTEGRADA[[#This Row],[ORÇ DIG3]]*1.38,IF(TB_INTEGRADA[[#This Row],[TOMADOR]]="UTGC",TB_INTEGRADA[[#This Row],[ORÇ DIG3]]*1.47,IF(TB_INTEGRADA[[#This Row],[TOMADOR]]="TIMS",TB_INTEGRADA[[#This Row],[ORÇ DIG3]]*1.34,IF(TB_INTEGRADA[[#This Row],[TOMADOR]]="UTGSUL",TB_INTEGRADA[[#This Row],[ORÇ DIG3]]*1.37,IF(TB_INTEGRADA[[#This Row],[TOMADOR]]="REGAP",TB_INTEGRADA[[#This Row],[ORÇ DIG3]]*1.36,IF(TB_INTEGRADA[[#This Row],[TOMADOR]]="UTEIBI",TB_INTEGRADA[[#This Row],[ORÇ DIG3]]*1.5,"S/TOMADOR")))))) -> 552.9993 | AS10: 376.19 | AT10: =SUMIFS(Tb_HhPLAN[Hh DISC],Tb_HhPLAN[SS],TB_INTEGRADA[[#This Row],[Nº SS]],Tb_HhPLAN[DISCIPLINA],"PINT") -> 384 | AU10: =SUMIFS(Hh_EXE_TOTAL[Hh],Hh_EXE_TOTAL[Nº SS],TB_INTEGRADA[[#This Row],[Nº SS]],Hh_EXE_TOTAL[DISCIPLINA],"PINT") -> 316.16386 | AV10: =TB_INTEGRADA[[#This Row],[ORÇADO]]+TB_INTEGRADA[[#This Row],[ORÇADO1]]+TB_INTEGRADA[[#This Row],[ORÇADO2]]+TB_INTEGRADA[[#This Row],[ORÇADO3]] -> 2832.4401 | AW10: =TB_INTEGRADA[[#This Row],[PLANEJ]]+TB_INTEGRADA[[#This Row],[PLANEJ1]]+TB_INTEGRADA[[#This Row],[PLANEJ2]]+TB_INTEGRADA[[#This Row],[PLANEJ3]] -> 2040 | AX10: =TB_INTEGRADA[[#This Row],[REALIZ]]+TB_INTEGRADA[[#This Row],[REALIZ1]]+TB_INTEGRADA[[#This Row],[REALIZ2]]+TB_INTEGRADA[[#This Row],[REALIZ3]] -> 3976 | AY10: =IFERROR(TB_INTEGRADA[[#This Row],[REALIZ4]]/TB_INTEGRADA[[#This Row],[ORÇADO4]],"") -> 1.4037367 | AZ10: =_xlfn.XLOOKUP(TB_INTEGRADA[[#This Row],[Nº SS]],'CONTROLE EC'!B:B,'CONTROLE EC'!W:W,"",0,1) -> 857462.22 | BA10: =_xlfn.XLOOKUP(TB_INTEGRADA[[#This Row],[Nº SS]],'CONTROLE EC'!B:B,'CONTROLE EC'!X:X,"",0,1) -> 857462.22 | BB10: =_xlfn.XLOOKUP(TB_INTEGRADA[[#This Row],[Nº SS]],'CONTROLE EC'!B:B,'CONTROLE EC'!Y:Y,"",0,1) -> 0
A11: =IF(COUNTIFS($B$5:B11,TB_INTEGRADA[[#This Row],[Nº SS]])<>1,"",COUNTIFS($B$5:B11,TB_INTEGRADA[[#This Row],[Nº SS]])) -> 1 | B11: SS-06/2025 | C11: =_xlfn.XLOOKUP(TB_INTEGRADA[[#This Row],[Nº SS]],'CONTROLE EC'!B:B,'CONTROLE EC'!C:C,"",0,1) -> 23-0803-ES - MANUTENÇÃO DO GALPÃO K-14 | D11: =_xlfn.XLOOKUP(TB_INTEGRADA[[#This Row],[Nº SS]],'CONTROLE CRONOG'!B:B,'CONTROLE CRONOG'!D:D,"",0,1) -> SERVIÇO | E11: =_xlfn.XLOOKUP(TB_INTEGRADA[[#This Row],[Nº SS]],'CONTROLE EC'!B:B,'CONTROLE EC'!E:E,"",0,1) -> UTGC | F11: =_xlfn.XLOOKUP(TB_INTEGRADA[[#This Row],[Nº SS]],'CONTROLE EC'!B:B,'CONTROLE EC'!F:F,"",0,1) -> CONCLUÍDA | G11: =_xlfn.XLOOKUP(TB_INTEGRADA[[#This Row],[Nº SS]],'CONTROLE EC'!B:B,'CONTROLE EC'!R:R,"",0,1) -> REV.04 | H11: =IF(TB_INTEGRADA[[#This Row],[REVISÃO (EC)]]="","",_xlfn.XLOOKUP(TB_INTEGRADA[[#This Row],[Nº SS]],'CONTROLE EC'!B:B,'CONTROLE EC'!S:S,"",0,1)) -> 45947 | I11: =IF(TB_INTEGRADA[[#This Row],[REVISÃO (EC)]]="","",_xlfn.XLOOKUP(TB_INTEGRADA[[#This Row],[Nº SS]],'CONTROLE EC'!B:B,'CONTROLE EC'!U:U,"",0,1)) -> 45947 | J11: {=IF(TB_INTEGRADA[[#This Row],[DATA ENVIO. (EC)]]=IFERROR(INDEX('CONTROLE EC'!G11:Q11,MATCH(2,1/('CONTROLE EC'!G11:Q11<>""))),""),"",IFERROR(INDEX('CONTROLE EC'!G11:Q11,MATCH(2,1/('CONTROLE EC'!G11:Q11<>""))),""))} | K11: =IF(TB_INTEGRADA[[#This Row],[STATUS DEMANDA]]="NÃO EMITIDA SAMC","S/ EMISSÃO",_xlfn.XLOOKUP(TB_INTEGRADA[[#This Row],[Nº SS]],'CONTROLE EC'!B:B,'CONTROLE EC'!T:T,"",0,-1)) -> ENTREGUE | L11: =IF(TB_INTEGRADA[[#This Row],[STATUS DEMANDA]]="NÃO EMITIDA SAMC","S/ EMISSÃO",IF(TB_INTEGRADA[[#This Row],[STATUS DEMANDA]]="ON HOLD","ON HOLD",IF(TB_INTEGRADA[[#This Row],[STATUS DEMANDA]]="CANCELADA","CANCELADA",IF(TB_INTEGRADA[[#This Row],[DATA APROV. (EC)]]=0,"FISCALIZ.",IF(TB_INTEGRADA[[#This Row],[DATA APROV. (EC)]]="","PEND. FISCALIZ.",IF(TB_INTEGRADA[[#This Row],[DATA APROV. (EC)]]="N/A","APROVADO",IF(TB_INTEGRADA[[#This Row],[REVISÃO (EC)]]="","",_xlfn.XLOOKUP(TB_INTEGRADA[[#This Row],[Nº SS]],'CONTROLE EC'!B:B,'CONTROLE EC'!V:V,"",0,1)))))))) -> APROVADO | M11: {=IFERROR(_xlfn.IFS(TB_INTEGRADA[[#This Row],[STATUS DEMANDA]]="CANCELADA",0,TB_INTEGRADA[[#This Row],[DATA APROV. (EC)]]="",TODAY()-TB_INTEGRADA[[#This Row],[DATA ENVIO. (EC)]],TB_INTEGRADA[[#This Row],[DATA APROV. (EC)]]>=TB_INTEGRADA[[#This Row],[DATA ENVIO. (EC)]],0,TB_INTEGRADA[[#This Row],[DATA ENVIO. (EC)]]="",0,TB_INTEGRADA[[#This Row],[DATA ENVIO. (EC)]]>TB_INTEGRADA[[#This Row],[DATA APROV. (EC)]],TODAY()-TB_INTEGRADA[[#This Row],[DATA ENVIO. (EC)]]),"")} -> 0 | N11: =IF(TB_INTEGRADA[[#This Row],[STATUS DEMANDA]]="NÃO EMITIDA SAMC","S/ EMISSÃO",IF(TB_INTEGRADA[[#This Row],[STATUS DEMANDA]]="ON HOLD","ON HOLD",IF(F11="CANCELADA","CANCELADA",IF(L11="REPROVADO","EM PLANEJ.",IF(K11<>"ENTREGUE","EM PLANEJ.",IF(H11="","EM PLANEJ.",IF(I11="","FISCALIZ.",IF(M11<0,"EM PLANEJ.",IF(TB_INTEGRADA[[#This Row],[DATA APROV. (EC)]]>=TB_INTEGRADA[[#This Row],[DATA ENVIO. (EC)]],"RETORNO OK","FISCALIZ."))))))))) -> RETORNO OK | O11: =_xlfn.XLOOKUP(TB_INTEGRADA[[#This Row],[Nº SS]],'CONTROLE CRONOG'!B:B,'CONTROLE CRONOG'!R:R,"",0,1) -> REV.03 | P11: =IF(TB_INTEGRADA[[#This Row],[REVISÃO (CR)]]="","",_xlfn.XLOOKUP(TB_INTEGRADA[[#This Row],[Nº SS]],'CONTROLE CRONOG'!B:B,'CONTROLE CRONOG'!S:S,"",0,1)) -> 45952 | Q11: =IF(TB_INTEGRADA[[#This Row],[REVISÃO (CR)]]="","",_xlfn.XLOOKUP(TB_INTEGRADA[[#This Row],[Nº SS]],'CONTROLE CRONOG'!B:B,'CONTROLE CRONOG'!U:U,"",0,1)) -> 45952 | R11: {=IF(TB_INTEGRADA[[#This Row],[DATA ENVIO. (CR)]]=IFERROR(INDEX('CONTROLE CRONOG'!G11:Q11,MATCH(2,1/('CONTROLE CRONOG'!G11:Q11<>""))),""),"",IFERROR(INDEX('CONTROLE CRONOG'!G11:Q11,MATCH(2,1/('CONTROLE CRONOG'!G11:Q11<>""))),""))} | S11: =_xlfn.XLOOKUP(TB_INTEGRADA[[#This Row],[Nº SS]],'CONTROLE CRONOG'!B:B,'CONTROLE CRONOG'!T:T,"",0,-1) -> ENTREGUE | T11: =IF(TB_INTEGRADA[[#This Row],[STATUS DEMANDA]]="ON HOLD","ON HOLD",IF(TB_INTEGRADA[[#This Row],[STATUS DEMANDA]]="CANCELADA","CANCELADA",IF(TB_INTEGRADA[[#This Row],[DATA APROV. (CR)]]=0,"FISCALIZ.",IF(TB_INTEGRADA[[#This Row],[DATA APROV. (CR)]]="N/A","APROVADO",IF(TB_INTEGRADA[[#This Row],[REVISÃO (CR)]]="","",_xlfn.XLOOKUP(TB_INTEGRADA[[#This Row],[Nº SS]],'CONTROLE CRONOG'!B:B,'CONTROLE CRONOG'!V:V,"",0,1)))))) -> APROVADO | V11: 46015 | W11: 46052 | X11: =IFERROR(TB_INTEGRADA[[#This Row],[TÉRM. TD]]-TB_INTEGRADA[[#This Row],[TÉRMINO LB]],0) -> 37 | Y11: 1 | Z11: 1 | AA11: 0 | AB11: =IFERROR(TB_INTEGRADA[[#This Row],[REAL (%)]]-TB_INTEGRADA[[#This Row],[PREV (%)]],0) -> 0 | AC11: 0 | AD11: 0 | AF11: =IF(TB_INTEGRADA[[#This Row],[TOMADOR]]="EDIVIT",TB_INTEGRADA[[#This Row],[ORÇ DIG]]*1.38,IF(TB_INTEGRADA[[#This Row],[TOMADOR]]="UTGC",TB_INTEGRADA[[#This Row],[ORÇ DIG]]*1.47,IF(TB_INTEGRADA[[#This Row],[TOMADOR]]="TIMS",TB_INTEGRADA[[#This Row],[ORÇ DIG]]*1.34,IF(TB_INTEGRADA[[#This Row],[TOMADOR]]="UTGSUL",TB_INTEGRADA[[#This Row],[ORÇ DIG]]*1.37,IF(TB_INTEGRADA[[#This Row],[TOMADOR]]="REGAP",TB_INTEGRADA[[#This Row],[ORÇ DIG]]*1.36,IF(TB_INTEGRADA[[#This Row],[TOMADOR]]="UTEIBI",TB_INTEGRADA[[#This Row],[ORÇ DIG]]*1.5,"S/TOMADOR")))))) -> 957.8373 | AG11: 651.59 | AH11: =SUMIFS(Tb_HhPLAN[Hh DISC],Tb_HhPLAN[SS],TB_INTEGRADA[[#This Row],[Nº SS]],Tb_HhPLAN[DISCIPLINA],"MEC") -> 1240.8547 | AI11: =SUMIFS(Hh_EXE_TOTAL[Hh],Hh_EXE_TOTAL[Nº SS],TB_INTEGRADA[[#This Row],[Nº SS]],Hh_EXE_TOTAL[DISCIPLINA],"MEC") -> 1882.0421 | AJ11: =IF(TB_INTEGRADA[[#This Row],[TOMADOR]]="EDIVIT",TB_INTEGRADA[[#This Row],[ORÇ DIG1]]*1.38,IF(TB_INTEGRADA[[#This Row],[TOMADOR]]="UTGC",TB_INTEGRADA[[#This Row],[ORÇ DIG1]]*1.47,IF(TB_INTEGRADA[[#This Row],[TOMADOR]]="TIMS",TB_INTEGRADA[[#This Row],[ORÇ DIG1]]*1.34,IF(TB_INTEGRADA[[#This Row],[TOMADOR]]="UTGSUL",TB_INTEGRADA[[#This Row],[ORÇ DIG1]]*1.37,IF(TB_INTEGRADA[[#This Row],[TOMADOR]]="REGAP",TB_INTEGRADA[[#This Row],[ORÇ DIG1]]*1.36,IF(TB_INTEGRADA[[#This Row],[TOMADOR]]="UTEIBI",TB_INTEGRADA[[#This Row],[ORÇ DIG1]]*1.5,"S/TOMADOR")))))) -> 0 | AK11: 0 | AL11: =SUMIFS(Tb_HhPLAN[Hh DISC],Tb_HhPLAN[SS],TB_INTEGRADA[[#This Row],[Nº SS]],Tb_HhPLAN[DISCIPLINA],"CIVIL") -> 0 | AM11: =SUMIFS(Hh_EXE_TOTAL[Hh],Hh_EXE_TOTAL[Nº SS],TB_INTEGRADA[[#This Row],[Nº SS]],Hh_EXE_TOTAL[DISCIPLINA],"CIVIL") -> 169.28421 | AN11: =IF(TB_INTEGRADA[[#This Row],[TOMADOR]]="EDIVIT",TB_INTEGRADA[[#This Row],[ORÇ DIG2]]*1.38,IF(TB_INTEGRADA[[#This Row],[TOMADOR]]="UTGC",TB_INTEGRADA[[#This Row],[ORÇ DIG2]]*1.47,IF(TB_INTEGRADA[[#This Row],[TOMADOR]]="TIMS",TB_INTEGRADA[[#This Row],[ORÇ DIG2]]*1.34,IF(TB_INTEGRADA[[#This Row],[TOMADOR]]="UTGSUL",TB_INTEGRADA[[#This Row],[ORÇ DIG2]]*1.37,IF(TB_INTEGRADA[[#This Row],[TOMADOR]]="REGAP",TB_INTEGRADA[[#This Row],[ORÇ DIG2]]*1.36,IF(TB_INTEGRADA[[#This Row],[TOMADOR]]="UTEIBI",TB_INTEGRADA[[#This Row],[ORÇ DIG2]]*1.5,"S/TOMADOR")))))) -> 1795.8402 | AO11: 1221.66 | AP11: =SUMIFS(Tb_HhPLAN[Hh DISC],Tb_HhPLAN[SS],TB_INTEGRADA[[#This Row],[Nº SS]],Tb_HhPLAN[DISCIPLINA],"ELÉT") -> 218.97436 | AQ11: =SUMIFS(Hh_EXE_TOTAL[Hh],Hh_EXE_TOTAL[Nº SS],TB_INTEGRADA[[#This Row],[Nº SS]],Hh_EXE_TOTAL[DISCIPLINA],"ELÉT") -> 876.29474 | AR11: =IF(TB_INTEGRADA[[#This Row],[TOMADOR]]="EDIVIT",TB_INTEGRADA[[#This Row],[ORÇ DIG3]]*1.38,IF(TB_INTEGRADA[[#This Row],[TOMADOR]]="UTGC",TB_INTEGRADA[[#This Row],[ORÇ DIG3]]*1.47,IF(TB_INTEGRADA[[#This Row],[TOMADOR]]="TIMS",TB_INTEGRADA[[#This Row],[ORÇ DIG3]]*1.34,IF(TB_INTEGRADA[[#This Row],[TOMADOR]]="UTGSUL",TB_INTEGRADA[[#This Row],[ORÇ DIG3]]*1.37,IF(TB_INTEGRADA[[#This Row],[TOMADOR]]="REGAP",TB_INTEGRADA[[#This Row],[ORÇ DIG3]]*1.36,IF(TB_INTEGRADA[[#This Row],[TOMADOR]]="UTEIBI",TB_INTEGRADA[[#This Row],[ORÇ DIG3]]*1.5,"S/TOMADOR")))))) -> 413.217 | AS11: 281.1 | AT11: =SUMIFS(Tb_HhPLAN[Hh DISC],Tb_HhPLAN[SS],TB_INTEGRADA[[#This Row],[Nº SS]],Tb_HhPLAN[DISCIPLINA],"PINT") -> 248.17094 | AU11: =SUMIFS(Hh_EXE_TOTAL[Hh],Hh_EXE_TOTAL[Nº SS],TB_INTEGRADA[[#This Row],[Nº SS]],Hh_EXE_TOTAL[DISCIPLINA],"PINT") -> 856.37895 | AV11: =TB_INTEGRADA[[#This Row],[ORÇADO]]+TB_INTEGRADA[[#This Row],[ORÇADO1]]+TB_INTEGRADA[[#This Row],[ORÇADO2]]+TB_INTEGRADA[[#This Row],[ORÇADO3]] -> 3166.8945 | AW11: =TB_INTEGRADA[[#This Row],[PLANEJ]]+TB_INTEGRADA[[#This Row],[PLANEJ1]]+TB_INTEGRADA[[#This Row],[PLANEJ2]]+TB_INTEGRADA[[#This Row],[PLANEJ3]] -> 1708 | AX11: =TB_INTEGRADA[[#This Row],[REALIZ]]+TB_INTEGRADA[[#This Row],[REALIZ1]]+TB_INTEGRADA[[#This Row],[REALIZ2]]+TB_INTEGRADA[[#This Row],[REALIZ3]] -> 3784 | AY11: =IFERROR(TB_INTEGRADA[[#This Row],[REALIZ4]]/TB_INTEGRADA[[#This Row],[ORÇADO4]],"") -> 1.1948614 | AZ11: =_xlfn.XLOOKUP(TB_INTEGRADA[[#This Row],[Nº SS]],'CONTROLE EC'!B:B,'CONTROLE EC'!W:W,"",0,1) -> 1342004 | BA11: =_xlfn.XLOOKUP(TB_INTEGRADA[[#This Row],[Nº SS]],'CONTROLE EC'!B:B,'CONTROLE EC'!X:X,"",0,1) -> 1342004 | BB11: =_xlfn.XLOOKUP(TB_INTEGRADA[[#This Row],[Nº SS]],'CONTROLE EC'!B:B,'CONTROLE EC'!Y:Y,"",0,1) -> 0
A12: =IF(COUNTIFS($B$5:B12,TB_INTEGRADA[[#This Row],[Nº SS]])<>1,"",COUNTIFS($B$5:B12,TB_INTEGRADA[[#This Row],[Nº SS]])) -> 1 | B12: SS-07/2025 | C12: =_xlfn.XLOOKUP(TB_INTEGRADA[[#This Row],[Nº SS]],'CONTROLE EC'!B:B,'CONTROLE EC'!C:C,"",0,1) -> 23-710B-ES - MANUTENÇÃO DO GALPÃO DE BOMBAS DE TRANSFERÊNCIA DE GLP PARA TABR | D12: =_xlfn.XLOOKUP(TB_INTEGRADA[[#This Row],[Nº SS]],'CONTROLE CRONOG'!B:B,'CONTROLE CRONOG'!D:D,"",0,1) -> SERVIÇO | E12: =_xlfn.XLOOKUP(TB_INTEGRADA[[#This Row],[Nº SS]],'CONTROLE EC'!B:B,'CONTROLE EC'!E:E,"",0,1) -> UTGC | F12: =_xlfn.XLOOKUP(TB_INTEGRADA[[#This Row],[Nº SS]],'CONTROLE EC'!B:B,'CONTROLE EC'!F:F,"",0,1) -> CONCLUÍDA | G12: =_xlfn.XLOOKUP(TB_INTEGRADA[[#This Row],[Nº SS]],'CONTROLE EC'!B:B,'CONTROLE EC'!R:R,"",0,1) -> REV.01 | H12: =IF(TB_INTEGRADA[[#This Row],[REVISÃO (EC)]]="","",_xlfn.XLOOKUP(TB_INTEGRADA[[#This Row],[Nº SS]],'CONTROLE EC'!B:B,'CONTROLE EC'!S:S,"",0,1)) -> 45936 | I12: =IF(TB_INTEGRADA[[#This Row],[REVISÃO (EC)]]="","",_xlfn.XLOOKUP(TB_INTEGRADA[[#This Row],[Nº SS]],'CONTROLE EC'!B:B,'CONTROLE EC'!U:U,"",0,1)) -> 45937 | J12: {=IF(TB_INTEGRADA[[#This Row],[DATA ENVIO. (EC)]]=IFERROR(INDEX('CONTROLE EC'!G12:Q12,MATCH(2,1/('CONTROLE EC'!G12:Q12<>""))),""),"",IFERROR(INDEX('CONTROLE EC'!G12:Q12,MATCH(2,1/('CONTROLE EC'!G12:Q12<>""))),""))} | K12: =IF(TB_INTEGRADA[[#This Row],[STATUS DEMANDA]]="NÃO EMITIDA SAMC","S/ EMISSÃO",_xlfn.XLOOKUP(TB_INTEGRADA[[#This Row],[Nº SS]],'CONTROLE EC'!B:B,'CONTROLE EC'!T:T,"",0,-1)) -> ENTREGUE | L12: =IF(TB_INTEGRADA[[#This Row],[STATUS DEMANDA]]="NÃO EMITIDA SAMC","S/ EMISSÃO",IF(TB_INTEGRADA[[#This Row],[STATUS DEMANDA]]="ON HOLD","ON HOLD",IF(TB_INTEGRADA[[#This Row],[STATUS DEMANDA]]="CANCELADA","CANCELADA",IF(TB_INTEGRADA[[#This Row],[DATA APROV. (EC)]]=0,"FISCALIZ.",IF(TB_INTEGRADA[[#This Row],[DATA APROV. (EC)]]="","PEND. FISCALIZ.",IF(TB_INTEGRADA[[#This Row],[DATA APROV. (EC)]]="N/A","APROVADO",IF(TB_INTEGRADA[[#This Row],[REVISÃO (EC)]]="","",_xlfn.XLOOKUP(TB_INTEGRADA[[#This Row],[Nº SS]],'CONTROLE EC'!B:B,'CONTROLE EC'!V:V,"",0,1)))))))) -> APROVADO | M12: {=IFERROR(_xlfn.IFS(TB_INTEGRADA[[#This Row],[STATUS DEMANDA]]="CANCELADA",0,TB_INTEGRADA[[#This Row],[DATA APROV. (EC)]]="",TODAY()-TB_INTEGRADA[[#This Row],[DATA ENVIO. (EC)]],TB_INTEGRADA[[#This Row],[DATA APROV. (EC)]]>=TB_INTEGRADA[[#This Row],[DATA ENVIO. (EC)]],0,TB_INTEGRADA[[#This Row],[DATA ENVIO. (EC)]]="",0,TB_INTEGRADA[[#This Row],[DATA ENVIO. (EC)]]>TB_INTEGRADA[[#This Row],[DATA APROV. (EC)]],TODAY()-TB_INTEGRADA[[#This Row],[DATA ENVIO. (EC)]]),"")} -> 0 | N12: =IF(TB_INTEGRADA[[#This Row],[STATUS DEMANDA]]="NÃO EMITIDA SAMC","S/ EMISSÃO",IF(TB_INTEGRADA[[#This Row],[STATUS DEMANDA]]="ON HOLD","ON HOLD",IF(F12="CANCELADA","CANCELADA",IF(L12="REPROVADO","EM PLANEJ.",IF(K12<>"ENTREGUE","EM PLANEJ.",IF(H12="","EM PLANEJ.",IF(I12="","FISCALIZ.",IF(M12<0,"EM PLANEJ.",IF(TB_INTEGRADA[[#This Row],[DATA APROV. (EC)]]>=TB_INTEGRADA[[#This Row],[DATA ENVIO. (EC)]],"RETORNO OK","FISCALIZ."))))))))) -> RETORNO OK | O12: =_xlfn.XLOOKUP(TB_INTEGRADA[[#This Row],[Nº SS]],'CONTROLE CRONOG'!B:B,'CONTROLE CRONOG'!R:R,"",0,1) -> REV.01 | P12: =IF(TB_INTEGRADA[[#This Row],[REVISÃO (CR)]]="","",_xlfn.XLOOKUP(TB_INTEGRADA[[#This Row],[Nº SS]],'CONTROLE CRONOG'!B:B,'CONTROLE CRONOG'!S:S,"",0,1)) -> 45933 | Q12: =IF(TB_INTEGRADA[[#This Row],[REVISÃO (CR)]]="","",_xlfn.XLOOKUP(TB_INTEGRADA[[#This Row],[Nº SS]],'CONTROLE CRONOG'!B:B,'CONTROLE CRONOG'!U:U,"",0,1)) -> 45936 | R12: {=IF(TB_INTEGRADA[[#This Row],[DATA ENVIO. (CR)]]=IFERROR(INDEX('CONTROLE CRONOG'!G12:Q12,MATCH(2,1/('CONTROLE CRONOG'!G12:Q12<>""))),""),"",IFERROR(INDEX('CONTROLE CRONOG'!G12:Q12,MATCH(2,1/('CONTROLE CRONOG'!G12:Q12<>""))),""))} | S12: =_xlfn.XLOOKUP(TB_INTEGRADA[[#This Row],[Nº SS]],'CONTROLE CRONOG'!B:B,'CONTROLE CRONOG'!T:T,"",0,-1) -> ENTREGUE | T12: =IF(TB_INTEGRADA[[#This Row],[STATUS DEMANDA]]="ON HOLD","ON HOLD",IF(TB_INTEGRADA[[#This Row],[STATUS DEMANDA]]="CANCELADA","CANCELADA",IF(TB_INTEGRADA[[#This Row],[DATA APROV. (CR)]]=0,"FISCALIZ.",IF(TB_INTEGRADA[[#This Row],[DATA APROV. (CR)]]="N/A","APROVADO",IF(TB_INTEGRADA[[#This Row],[REVISÃO (CR)]]="","",_xlfn.XLOOKUP(TB_INTEGRADA[[#This Row],[Nº SS]],'CONTROLE CRONOG'!B:B,'CONTROLE CRONOG'!V:V,"",0,1)))))) -> APROVADO | V12: 46015 | W12: 46013 | X12: =IFERROR(TB_INTEGRADA[[#This Row],[TÉRM. TD]]-TB_INTEGRADA[[#This Row],[TÉRMINO LB]],0) -> -2 | Y12: 1 | Z12: 1 | AA12: 0 | AB12: =IFERROR(TB_INTEGRADA[[#This Row],[REAL (%)]]-TB_INTEGRADA[[#This Row],[PREV (%)]],0) -> 0 | AC12: 0 | AD12: 0 | AF12: =IF(TB_INTEGRADA[[#This Row],[TOMADOR]]="EDIVIT",TB_INTEGRADA[[#This Row],[ORÇ DIG]]*1.38,IF(TB_INTEGRADA[[#This Row],[TOMADOR]]="UTGC",TB_INTEGRADA[[#This Row],[ORÇ DIG]]*1.47,IF(TB_INTEGRADA[[#This Row],[TOMADOR]]="TIMS",TB_INTEGRADA[[#This Row],[ORÇ DIG]]*1.34,IF(TB_INTEGRADA[[#This Row],[TOMADOR]]="UTGSUL",TB_INTEGRADA[[#This Row],[ORÇ DIG]]*1.37,IF(TB_INTEGRADA[[#This Row],[TOMADOR]]="REGAP",TB_INTEGRADA[[#This Row],[ORÇ DIG]]*1.36,IF(TB_INTEGRADA[[#This Row],[TOMADOR]]="UTEIBI",TB_INTEGRADA[[#This Row],[ORÇ DIG]]*1.5,"S/TOMADOR")))))) -> 394.989 | AG12: 268.7 | AH12: =SUMIFS(Tb_HhPLAN[Hh DISC],Tb_HhPLAN[SS],TB_INTEGRADA[[#This Row],[Nº SS]],Tb_HhPLAN[DISCIPLINA],"MEC") -> 1257.4867 | AI12: =SUMIFS(Hh_EXE_TOTAL[Hh],Hh_EXE_TOTAL[Nº SS],TB_INTEGRADA[[#This Row],[Nº SS]],Hh_EXE_TOTAL[DISCIPLINA],"MEC") -> 1617.1728 | AJ12: =IF(TB_INTEGRADA[[#This Row],[TOMADOR]]="EDIVIT",TB_INTEGRADA[[#This Row],[ORÇ DIG1]]*1.38,IF(TB_INTEGRADA[[#This Row],[TOMADOR]]="UTGC",TB_INTEGRADA[[#This Row],[ORÇ DIG1]]*1.47,IF(TB_INTEGRADA[[#This Row],[TOMADOR]]="TIMS",TB_INTEGRADA[[#This Row],[ORÇ DIG1]]*1.34,IF(TB_INTEGRADA[[#This Row],[TOMADOR]]="UTGSUL",TB_INTEGRADA[[#This Row],[ORÇ DIG1]]*1.37,IF(TB_INTEGRADA[[#This Row],[TOMADOR]]="REGAP",TB_INTEGRADA[[#This Row],[ORÇ DIG1]]*1.36,IF(TB_INTEGRADA[[#This Row],[TOMADOR]]="UTEIBI",TB_INTEGRADA[[#This Row],[ORÇ DIG1]]*1.5,"S/TOMADOR")))))) -> 0 | AK12: 0 | AL12: =SUMIFS(Tb_HhPLAN[Hh DISC],Tb_HhPLAN[SS],TB_INTEGRADA[[#This Row],[Nº SS]],Tb_HhPLAN[DISCIPLINA],"CIVIL") -> 0 | AM12: =SUMIFS(Hh_EXE_TOTAL[Hh],Hh_EXE_TOTAL[Nº SS],TB_INTEGRADA[[#This Row],[Nº SS]],Hh_EXE_TOTAL[DISCIPLINA],"CIVIL") -> 33.926702 | AN12: =IF(TB_INTEGRADA[[#This Row],[TOMADOR]]="EDIVIT",TB_INTEGRADA[[#This Row],[ORÇ DIG2]]*1.38,IF(TB_INTEGRADA[[#This Row],[TOMADOR]]="UTGC",TB_INTEGRADA[[#This Row],[ORÇ DIG2]]*1.47,IF(TB_INTEGRADA[[#This Row],[TOMADOR]]="TIMS",TB_INTEGRADA[[#This Row],[ORÇ DIG2]]*1.34,IF(TB_INTEGRADA[[#This Row],[TOMADOR]]="UTGSUL",TB_INTEGRADA[[#This Row],[ORÇ DIG2]]*1.37,IF(TB_INTEGRADA[[#This Row],[TOMADOR]]="REGAP",TB_INTEGRADA[[#This Row],[ORÇ DIG2]]*1.36,IF(TB_INTEGRADA[[#This Row],[TOMADOR]]="UTEIBI",TB_INTEGRADA[[#This Row],[ORÇ DIG2]]*1.5,"S/TOMADOR")))))) -> 1065.1326 | AO12: 724.58 | AP12: =SUMIFS(Tb_HhPLAN[Hh DISC],Tb_HhPLAN[SS],TB_INTEGRADA[[#This Row],[Nº SS]],Tb_HhPLAN[DISCIPLINA],"ELÉT") -> 212.10619 | AQ12: =SUMIFS(Hh_EXE_TOTAL[Hh],Hh_EXE_TOTAL[Nº SS],TB_INTEGRADA[[#This Row],[Nº SS]],Hh_EXE_TOTAL[DISCIPLINA],"ELÉT") -> 237.48691 | AR12: =IF(TB_INTEGRADA[[#This Row],[TOMADOR]]="EDIVIT",TB_INTEGRADA[[#This Row],[ORÇ DIG3]]*1.38,IF(TB_INTEGRADA[[#This Row],[TOMADOR]]="UTGC",TB_INTEGRADA[[#This Row],[ORÇ DIG3]]*1.47,IF(TB_INTEGRADA[[#This Row],[TOMADOR]]="TIMS",TB_INTEGRADA[[#This Row],[ORÇ DIG3]]*1.34,IF(TB_INTEGRADA[[#This Row],[TOMADOR]]="UTGSUL",TB_INTEGRADA[[#This Row],[ORÇ DIG3]]*1.37,IF(TB_INTEGRADA[[#This Row],[TOMADOR]]="REGAP",TB_INTEGRADA[[#This Row],[ORÇ DIG3]]*1.36,IF(TB_INTEGRADA[[#This Row],[TOMADOR]]="UTEIBI",TB_INTEGRADA[[#This Row],[ORÇ DIG3]]*1.5,"S/TOMADOR")))))) -> 228.6732 | AS12: 155.56 | AT12: =SUMIFS(Tb_HhPLAN[Hh DISC],Tb_HhPLAN[SS],TB_INTEGRADA[[#This Row],[Nº SS]],Tb_HhPLAN[DISCIPLINA],"PINT") -> 242.40708 | AU12: =SUMIFS(Hh_EXE_TOTAL[Hh],Hh_EXE_TOTAL[Nº SS],TB_INTEGRADA[[#This Row],[Nº SS]],Hh_EXE_TOTAL[DISCIPLINA],"PINT") -> 271.41361 | AV12: =TB_INTEGRADA[[#This Row],[ORÇADO]]+TB_INTEGRADA[[#This Row],[ORÇADO1]]+TB_INTEGRADA[[#This Row],[ORÇADO2]]+TB_INTEGRADA[[#This Row],[ORÇADO3]] -> 1688.7948 | AW12: =TB_INTEGRADA[[#This Row],[PLANEJ]]+TB_INTEGRADA[[#This Row],[PLANEJ1]]+TB_INTEGRADA[[#This Row],[PLANEJ2]]+TB_INTEGRADA[[#This Row],[PLANEJ3]] -> 1712 | AX12: =TB_INTEGRADA[[#This Row],[REALIZ]]+TB_INTEGRADA[[#This Row],[REALIZ1]]+TB_INTEGRADA[[#This Row],[REALIZ2]]+TB_INTEGRADA[[#This Row],[REALIZ3]] -> 2160 | AY12: =IFERROR(TB_INTEGRADA[[#This Row],[REALIZ4]]/TB_INTEGRADA[[#This Row],[ORÇADO4]],"") -> 1.2790186 | AZ12: =_xlfn.XLOOKUP(TB_INTEGRADA[[#This Row],[Nº SS]],'CONTROLE EC'!B:B,'CONTROLE EC'!W:W,"",0,1) -> 572533.72 | BA12: =_xlfn.XLOOKUP(TB_INTEGRADA[[#This Row],[Nº SS]],'CONTROLE EC'!B:B,'CONTROLE EC'!X:X,"",0,1) -> 572533.72 | BB12: =_xlfn.XLOOKUP(TB_INTEGRADA[[#This Row],[Nº SS]],'CONTROLE EC'!B:B,'CONTROLE EC'!Y:Y,"",0,1) -> 0
A13: =IF(COUNTIFS($B$5:B13,TB_INTEGRADA[[#This Row],[Nº SS]])<>1,"",COUNTIFS($B$5:B13,TB_INTEGRADA[[#This Row],[Nº SS]])) -> 1 | B13: SS-08/2025 | C13: =_xlfn.XLOOKUP(TB_INTEGRADA[[#This Row],[Nº SS]],'CONTROLE EC'!B:B,'CONTROLE EC'!C:C,"",0,1) -> 23-0713-ES - MANUTENÇÃO DO GALPÃO K-02 | D13: =_xlfn.XLOOKUP(TB_INTEGRADA[[#This Row],[Nº SS]],'CONTROLE CRONOG'!B:B,'CONTROLE CRONOG'!D:D,"",0,1) -> SERVIÇO | E13: =_xlfn.XLOOKUP(TB_INTEGRADA[[#This Row],[Nº SS]],'CONTROLE EC'!B:B,'CONTROLE EC'!E:E,"",0,1) -> UTGC | F13: =_xlfn.XLOOKUP(TB_INTEGRADA[[#This Row],[Nº SS]],'CONTROLE EC'!B:B,'CONTROLE EC'!F:F,"",0,1) -> EM ANDAMENTO | G13: =_xlfn.XLOOKUP(TB_INTEGRADA[[#This Row],[Nº SS]],'CONTROLE EC'!B:B,'CONTROLE EC'!R:R,"",0,1) -> REV.01 | H13: =IF(TB_INTEGRADA[[#This Row],[REVISÃO (EC)]]="","",_xlfn.XLOOKUP(TB_INTEGRADA[[#This Row],[Nº SS]],'CONTROLE EC'!B:B,'CONTROLE EC'!S:S,"",0,1)) -> 45949 | I13: =IF(TB_INTEGRADA[[#This Row],[REVISÃO (EC)]]="","",_xlfn.XLOOKUP(TB_INTEGRADA[[#This Row],[Nº SS]],'CONTROLE EC'!B:B,'CONTROLE EC'!U:U,"",0,1)) -> 45952 | J13: {=IF(TB_INTEGRADA[[#This Row],[DATA ENVIO. (EC)]]=IFERROR(INDEX('CONTROLE EC'!G13:Q13,MATCH(2,1/('CONTROLE EC'!G13:Q13<>""))),""),"",IFERROR(INDEX('CONTROLE EC'!G13:Q13,MATCH(2,1/('CONTROLE EC'!G13:Q13<>""))),""))} | K13: =IF(TB_INTEGRADA[[#This Row],[STATUS DEMANDA]]="NÃO EMITIDA SAMC","S/ EMISSÃO",_xlfn.XLOOKUP(TB_INTEGRADA[[#This Row],[Nº SS]],'CONTROLE EC'!B:B,'CONTROLE EC'!T:T,"",0,-1)) -> ENTREGUE | L13: =IF(TB_INTEGRADA[[#This Row],[STATUS DEMANDA]]="NÃO EMITIDA SAMC","S/ EMISSÃO",IF(TB_INTEGRADA[[#This Row],[STATUS DEMANDA]]="ON HOLD","ON HOLD",IF(TB_INTEGRADA[[#This Row],[STATUS DEMANDA]]="CANCELADA","CANCELADA",IF(TB_INTEGRADA[[#This Row],[DATA APROV. (EC)]]=0,"FISCALIZ.",IF(TB_INTEGRADA[[#This Row],[DATA APROV. (EC)]]="","PEND. FISCALIZ.",IF(TB_INTEGRADA[[#This Row],[DATA APROV. (EC)]]="N/A","APROVADO",IF(TB_INTEGRADA[[#This Row],[REVISÃO (EC)]]="","",_xlfn.XLOOKUP(TB_INTEGRADA[[#This Row],[Nº SS]],'CONTROLE EC'!B:B,'CONTROLE EC'!V:V,"",0,1)))))))) -> APROVADO | M13: {=IFERROR(_xlfn.IFS(TB_INTEGRADA[[#This Row],[STATUS DEMANDA]]="CANCELADA",0,TB_INTEGRADA[[#This Row],[DATA APROV. (EC)]]="",TODAY()-TB_INTEGRADA[[#This Row],[DATA ENVIO. (EC)]],TB_INTEGRADA[[#This Row],[DATA APROV. (EC)]]>=TB_INTEGRADA[[#This Row],[DATA ENVIO. (EC)]],0,TB_INTEGRADA[[#This Row],[DATA ENVIO. (EC)]]="",0,TB_INTEGRADA[[#This Row],[DATA ENVIO. (EC)]]>TB_INTEGRADA[[#This Row],[DATA APROV. (EC)]],TODAY()-TB_INTEGRADA[[#This Row],[DATA ENVIO. (EC)]]),"")} -> 0 | N13: =IF(TB_INTEGRADA[[#This Row],[STATUS DEMANDA]]="NÃO EMITIDA SAMC","S/ EMISSÃO",IF(TB_INTEGRADA[[#This Row],[STATUS DEMANDA]]="ON HOLD","ON HOLD",IF(F13="CANCELADA","CANCELADA",IF(L13="REPROVADO","EM PLANEJ.",IF(K13<>"ENTREGUE","EM PLANEJ.",IF(H13="","EM PLANEJ.",IF(I13="","FISCALIZ.",IF(M13<0,"EM PLANEJ.",IF(TB_INTEGRADA[[#This Row],[DATA APROV. (EC)]]>=TB_INTEGRADA[[#This Row],[DATA ENVIO. (EC)]],"RETORNO OK","FISCALIZ."))))))))) -> RETORNO OK | O13: =_xlfn.XLOOKUP(TB_INTEGRADA[[#This Row],[Nº SS]],'CONTROLE CRONOG'!B:B,'CONTROLE CRONOG'!R:R,"",0,1) -> REV.02 | P13: =IF(TB_INTEGRADA[[#This Row],[REVISÃO (CR)]]="","",_xlfn.XLOOKUP(TB_INTEGRADA[[#This Row],[Nº SS]],'CONTROLE CRONOG'!B:B,'CONTROLE CRONOG'!S:S,"",0,1)) -> 45952 | Q13: =IF(TB_INTEGRADA[[#This Row],[REVISÃO (CR)]]="","",_xlfn.XLOOKUP(TB_INTEGRADA[[#This Row],[Nº SS]],'CONTROLE CRONOG'!B:B,'CONTROLE CRONOG'!U:U,"",0,1)) -> 45952 | R13: {=IF(TB_INTEGRADA[[#This Row],[DATA ENVIO. (CR)]]=IFERROR(INDEX('CONTROLE CRONOG'!G13:Q13,MATCH(2,1/('CONTROLE CRONOG'!G13:Q13<>""))),""),"",IFERROR(INDEX('CONTROLE CRONOG'!G13:Q13,MATCH(2,1/('CONTROLE CRONOG'!G13:Q13<>""))),""))} | S13: =_xlfn.XLOOKUP(TB_INTEGRADA[[#This Row],[Nº SS]],'CONTROLE CRONOG'!B:B,'CONTROLE CRONOG'!T:T,"",0,-1) -> ENTREGUE | T13: =IF(TB_INTEGRADA[[#This Row],[STATUS DEMANDA]]="ON HOLD","ON HOLD",IF(TB_INTEGRADA[[#This Row],[STATUS DEMANDA]]="CANCELADA","CANCELADA",IF(TB_INTEGRADA[[#This Row],[DATA APROV. (CR)]]=0,"FISCALIZ.",IF(TB_INTEGRADA[[#This Row],[DATA APROV. (CR)]]="N/A","APROVADO",IF(TB_INTEGRADA[[#This Row],[REVISÃO (CR)]]="","",_xlfn.XLOOKUP(TB_INTEGRADA[[#This Row],[Nº SS]],'CONTROLE CRONOG'!B:B,'CONTROLE CRONOG'!V:V,"",0,1)))))) -> APROVADO | V13: 46108 | W13: 46125 | X13: =IFERROR(TB_INTEGRADA[[#This Row],[TÉRM. TD]]-TB_INTEGRADA[[#This Row],[TÉRMINO LB]],0) -> 17 | Y13: 0.8464 | Z13: 0.5107 | AA13: -0.1164 | AB13: =IFERROR(TB_INTEGRADA[[#This Row],[REAL (%)]]-TB_INTEGRADA[[#This Row],[PREV (%)]],0) -> -0.3357 | AC13: 6 | AD13: 10 | AF13: =IF(TB_INTEGRADA[[#This Row],[TOMADOR]]="EDIVIT",TB_INTEGRADA[[#This Row],[ORÇ DIG]]*1.38,IF(TB_INTEGRADA[[#This Row],[TOMADOR]]="UTGC",TB_INTEGRADA[[#This Row],[ORÇ DIG]]*1.47,IF(TB_INTEGRADA[[#This Row],[TOMADOR]]="TIMS",TB_INTEGRADA[[#This Row],[ORÇ DIG]]*1.34,IF(TB_INTEGRADA[[#This Row],[TOMADOR]]="UTGSUL",TB_INTEGRADA[[#This Row],[ORÇ DIG]]*1.37,IF(TB_INTEGRADA[[#This Row],[TOMADOR]]="REGAP",TB_INTEGRADA[[#This Row],[ORÇ DIG]]*1.36,IF(TB_INTEGRADA[[#This Row],[TOMADOR]]="UTEIBI",TB_INTEGRADA[[#This Row],[ORÇ DIG]]*1.5,"S/TOMADOR")))))) -> 689.7681 | AG13: 469.23 | AH13: =SUMIFS(Tb_HhPLAN[Hh DISC],Tb_HhPLAN[SS],TB_INTEGRADA[[#This Row],[Nº SS]],Tb_HhPLAN[DISCIPLINA],"MEC") -> 665.46667 | AI13: =SUMIFS(Hh_EXE_TOTAL[Hh],Hh_EXE_TOTAL[Nº SS],TB_INTEGRADA[[#This Row],[Nº SS]],Hh_EXE_TOTAL[DISCIPLINA],"MEC") -> 379.77358 | AJ13: =IF(TB_INTEGRADA[[#This Row],[TOMADOR]]="EDIVIT",TB_INTEGRADA[[#This Row],[ORÇ DIG1]]*1.38,IF(TB_INTEGRADA[[#This Row],[TOMADOR]]="UTGC",TB_INTEGRADA[[#This Row],[ORÇ DIG1]]*1.47,IF(TB_INTEGRADA[[#This Row],[TOMADOR]]="TIMS",TB_INTEGRADA[[#This Row],[ORÇ DIG1]]*1.34,IF(TB_INTEGRADA[[#This Row],[TOMADOR]]="UTGSUL",TB_INTEGRADA[[#This Row],[ORÇ DIG1]]*1.37,IF(TB_INTEGRADA[[#This Row],[TOMADOR]]="REGAP",TB_INTEGRADA[[#This Row],[ORÇ DIG1]]*1.36,IF(TB_INTEGRADA[[#This Row],[TOMADOR]]="UTEIBI",TB_INTEGRADA[[#This Row],[ORÇ DIG1]]*1.5,"S/TOMADOR")))))) -> 0 | AK13: 0 | AL13: =SUMIFS(Tb_HhPLAN[Hh DISC],Tb_HhPLAN[SS],TB_INTEGRADA[[#This Row],[Nº SS]],Tb_HhPLAN[DISCIPLINA],"CIVIL") -> 0 | AM13: =SUMIFS(Hh_EXE_TOTAL[Hh],Hh_EXE_TOTAL[Nº SS],TB_INTEGRADA[[#This Row],[Nº SS]],Hh_EXE_TOTAL[DISCIPLINA],"CIVIL") -> 0 | AN13: =IF(TB_INTEGRADA[[#This Row],[TOMADOR]]="EDIVIT",TB_INTEGRADA[[#This Row],[ORÇ DIG2]]*1.38,IF(TB_INTEGRADA[[#This Row],[TOMADOR]]="UTGC",TB_INTEGRADA[[#This Row],[ORÇ DIG2]]*1.47,IF(TB_INTEGRADA[[#This Row],[TOMADOR]]="TIMS",TB_INTEGRADA[[#This Row],[ORÇ DIG2]]*1.34,IF(TB_INTEGRADA[[#This Row],[TOMADOR]]="UTGSUL",TB_INTEGRADA[[#This Row],[ORÇ DIG2]]*1.37,IF(TB_INTEGRADA[[#This Row],[TOMADOR]]="REGAP",TB_INTEGRADA[[#This Row],[ORÇ DIG2]]*1.36,IF(TB_INTEGRADA[[#This Row],[TOMADOR]]="UTEIBI",TB_INTEGRADA[[#This Row],[ORÇ DIG2]]*1.5,"S/TOMADOR")))))) -> 546.3402 | AO13: 371.66 | AP13: =SUMIFS(Tb_HhPLAN[Hh DISC],Tb_HhPLAN[SS],TB_INTEGRADA[[#This Row],[Nº SS]],Tb_HhPLAN[DISCIPLINA],"ELÉT") -> 214.66667 | AQ13: =SUMIFS(Hh_EXE_TOTAL[Hh],Hh_EXE_TOTAL[Nº SS],TB_INTEGRADA[[#This Row],[Nº SS]],Hh_EXE_TOTAL[DISCIPLINA],"ELÉT") -> 102.64151 | AR13: =IF(TB_INTEGRADA[[#This Row],[TOMADOR]]="EDIVIT",TB_INTEGRADA[[#This Row],[ORÇ DIG3]]*1.38,IF(TB_INTEGRADA[[#This Row],[TOMADOR]]="UTGC",TB_INTEGRADA[[#This Row],[ORÇ DIG3]]*1.47,IF(TB_INTEGRADA[[#This Row],[TOMADOR]]="TIMS",TB_INTEGRADA[[#This Row],[ORÇ DIG3]]*1.34,IF(TB_INTEGRADA[[#This Row],[TOMADOR]]="UTGSUL",TB_INTEGRADA[[#This Row],[ORÇ DIG3]]*1.37,IF(TB_INTEGRADA[[#This Row],[TOMADOR]]="REGAP",TB_INTEGRADA[[#This Row],[ORÇ DIG3]]*1.36,IF(TB_INTEGRADA[[#This Row],[TOMADOR]]="UTEIBI",TB_INTEGRADA[[#This Row],[ORÇ DIG3]]*1.5,"S/TOMADOR")))))) -> 62.0487 | AS13: 42.21 | AT13: =SUMIFS(Tb_HhPLAN[Hh DISC],Tb_HhPLAN[SS],TB_INTEGRADA[[#This Row],[Nº SS]],Tb_HhPLAN[DISCIPLINA],"PINT") -> 85.866667 | AU13: =SUMIFS(Hh_EXE_TOTAL[Hh],Hh_EXE_TOTAL[Nº SS],TB_INTEGRADA[[#This Row],[Nº SS]],Hh_EXE_TOTAL[DISCIPLINA],"PINT") -> 61.584906 | AV13: =TB_INTEGRADA[[#This Row],[ORÇADO]]+TB_INTEGRADA[[#This Row],[ORÇADO1]]+TB_INTEGRADA[[#This Row],[ORÇADO2]]+TB_INTEGRADA[[#This Row],[ORÇADO3]] -> 1298.157 | AW13: =TB_INTEGRADA[[#This Row],[PLANEJ]]+TB_INTEGRADA[[#This Row],[PLANEJ1]]+TB_INTEGRADA[[#This Row],[PLANEJ2]]+TB_INTEGRADA[[#This Row],[PLANEJ3]] -> 966 | AX13: =TB_INTEGRADA[[#This Row],[REALIZ]]+TB_INTEGRADA[[#This Row],[REALIZ1]]+TB_INTEGRADA[[#This Row],[REALIZ2]]+TB_INTEGRADA[[#This Row],[REALIZ3]] -> 544 | AY13: =IFERROR(TB_INTEGRADA[[#This Row],[REALIZ4]]/TB_INTEGRADA[[#This Row],[ORÇADO4]],"") -> 0.41905563 | AZ13: =_xlfn.XLOOKUP(TB_INTEGRADA[[#This Row],[Nº SS]],'CONTROLE EC'!B:B,'CONTROLE EC'!W:W,"",0,1) -> 743593.46 | BA13: =_xlfn.XLOOKUP(TB_INTEGRADA[[#This Row],[Nº SS]],'CONTROLE EC'!B:B,'CONTROLE EC'!X:X,"",0,1) -> 371796.73 | BB13: =_xlfn.XLOOKUP(TB_INTEGRADA[[#This Row],[Nº SS]],'CONTROLE EC'!B:B,'CONTROLE EC'!Y:Y,"",0,1) -> 371796.73
A14: =IF(COUNTIFS($B$5:B14,TB_INTEGRADA[[#This Row],[Nº SS]])<>1,"",COUNTIFS($B$5:B14,TB_INTEGRADA[[#This Row],[Nº SS]])) -> 1 | B14: SS-09/2025 | C14: =_xlfn.XLOOKUP(TB_INTEGRADA[[#This Row],[Nº SS]],'CONTROLE EC'!B:B,'CONTROLE EC'!C:C,"",0,1) -> 23-0707-ES - MANUTENÇÃO DO GALPÃO UPGN-3 | D14: =_xlfn.XLOOKUP(TB_INTEGRADA[[#This Row],[Nº SS]],'CONTROLE CRONOG'!B:B,'CONTROLE CRONOG'!D:D,"",0,1) -> SERVIÇO | E14: =_xlfn.XLOOKUP(TB_INTEGRADA[[#This Row],[Nº SS]],'CONTROLE EC'!B:B,'CONTROLE EC'!E:E,"",0,1) -> UTGC | F14: =_xlfn.XLOOKUP(TB_INTEGRADA[[#This Row],[Nº SS]],'CONTROLE EC'!B:B,'CONTROLE EC'!F:F,"",0,1) -> CONCLUÍDA | G14: =_xlfn.XLOOKUP(TB_INTEGRADA[[#This Row],[Nº SS]],'CONTROLE EC'!B:B,'CONTROLE EC'!R:R,"",0,1) -> REV.03 | H14: =IF(TB_INTEGRADA[[#This Row],[REVISÃO (EC)]]="","",_xlfn.XLOOKUP(TB_INTEGRADA[[#This Row],[Nº SS]],'CONTROLE EC'!B:B,'CONTROLE EC'!S:S,"",0,1)) -> 45932 | I14: =IF(TB_INTEGRADA[[#This Row],[REVISÃO (EC)]]="","",_xlfn.XLOOKUP(TB_INTEGRADA[[#This Row],[Nº SS]],'CONTROLE EC'!B:B,'CONTROLE EC'!U:U,"",0,1)) -> 45932 | J14: {=IF(TB_INTEGRADA[[#This Row],[DATA ENVIO. (EC)]]=IFERROR(INDEX('CONTROLE EC'!G14:Q14,MATCH(2,1/('CONTROLE EC'!G14:Q14<>""))),""),"",IFERROR(INDEX('CONTROLE EC'!G14:Q14,MATCH(2,1/('CONTROLE EC'!G14:Q14<>""))),""))} | K14: =IF(TB_INTEGRADA[[#This Row],[STATUS DEMANDA]]="NÃO EMITIDA SAMC","S/ EMISSÃO",_xlfn.XLOOKUP(TB_INTEGRADA[[#This Row],[Nº SS]],'CONTROLE EC'!B:B,'CONTROLE EC'!T:T,"",0,-1)) -> ENTREGUE | L14: =IF(TB_INTEGRADA[[#This Row],[STATUS DEMANDA]]="NÃO EMITIDA SAMC","S/ EMISSÃO",IF(TB_INTEGRADA[[#This Row],[STATUS DEMANDA]]="ON HOLD","ON HOLD",IF(TB_INTEGRADA[[#This Row],[STATUS DEMANDA]]="CANCELADA","CANCELADA",IF(TB_INTEGRADA[[#This Row],[DATA APROV. (EC)]]=0,"FISCALIZ.",IF(TB_INTEGRADA[[#This Row],[DATA APROV. (EC)]]="","PEND. FISCALIZ.",IF(TB_INTEGRADA[[#This Row],[DATA APROV. (EC)]]="N/A","APROVADO",IF(TB_INTEGRADA[[#This Row],[REVISÃO (EC)]]="","",_xlfn.XLOOKUP(TB_INTEGRADA[[#This Row],[Nº SS]],'CONTROLE EC'!B:B,'CONTROLE EC'!V:V,"",0,1)))))))) -> APROVADO | M14: {=IFERROR(_xlfn.IFS(TB_INTEGRADA[[#This Row],[STATUS DEMANDA]]="CANCELADA",0,TB_INTEGRADA[[#This Row],[DATA APROV. (EC)]]="",TODAY()-TB_INTEGRADA[[#This Row],[DATA ENVIO. (EC)]],TB_INTEGRADA[[#This Row],[DATA APROV. (EC)]]>=TB_INTEGRADA[[#This Row],[DATA ENVIO. (EC)]],0,TB_INTEGRADA[[#This Row],[DATA ENVIO. (EC)]]="",0,TB_INTEGRADA[[#This Row],[DATA ENVIO. (EC)]]>TB_INTEGRADA[[#This Row],[DATA APROV. (EC)]],TODAY()-TB_INTEGRADA[[#This Row],[DATA ENVIO. (EC)]]),"")} -> 0 | N14: =IF(TB_INTEGRADA[[#This Row],[STATUS DEMANDA]]="NÃO EMITIDA SAMC","S/ EMISSÃO",IF(TB_INTEGRADA[[#This Row],[STATUS DEMANDA]]="ON HOLD","ON HOLD",IF(F14="CANCELADA","CANCELADA",IF(L14="REPROVADO","EM PLANEJ.",IF(K14<>"ENTREGUE","EM PLANEJ.",IF(H14="","EM PLANEJ.",IF(I14="","FISCALIZ.",IF(M14<0,"EM PLANEJ.",IF(TB_INTEGRADA[[#This Row],[DATA APROV. (EC)]]>=TB_INTEGRADA[[#This Row],[DATA ENVIO. (EC)]],"RETORNO OK","FISCALIZ."))))))))) -> RETORNO OK | O14: =_xlfn.XLOOKUP(TB_INTEGRADA[[#This Row],[Nº SS]],'CONTROLE CRONOG'!B:B,'CONTROLE CRONOG'!R:R,"",0,1) -> REV.02 | P14: =IF(TB_INTEGRADA[[#This Row],[REVISÃO (CR)]]="","",_xlfn.XLOOKUP(TB_INTEGRADA[[#This Row],[Nº SS]],'CONTROLE CRONOG'!B:B,'CONTROLE CRONOG'!S:S,"",0,1)) -> 45924 | Q14: =IF(TB_INTEGRADA[[#This Row],[REVISÃO (CR)]]="","",_xlfn.XLOOKUP(TB_INTEGRADA[[#This Row],[Nº SS]],'CONTROLE CRONOG'!B:B,'CONTROLE CRONOG'!U:U,"",0,1)) -> 45925 | R14: {=IF(TB_INTEGRADA[[#This Row],[DATA ENVIO. (CR)]]=IFERROR(INDEX('CONTROLE CRONOG'!G14:Q14,MATCH(2,1/('CONTROLE CRONOG'!G14:Q14<>""))),""),"",IFERROR(INDEX('CONTROLE CRONOG'!G14:Q14,MATCH(2,1/('CONTROLE CRONOG'!G14:Q14<>""))),""))} | S14: =_xlfn.XLOOKUP(TB_INTEGRADA[[#This Row],[Nº SS]],'CONTROLE CRONOG'!B:B,'CONTROLE CRONOG'!T:T,"",0,-1) -> ENTREGUE | T14: =IF(TB_INTEGRADA[[#This Row],[STATUS DEMANDA]]="ON HOLD","ON HOLD",IF(TB_INTEGRADA[[#This Row],[STATUS DEMANDA]]="CANCELADA","CANCELADA",IF(TB_INTEGRADA[[#This Row],[DATA APROV. (CR)]]=0,"FISCALIZ.",IF(TB_INTEGRADA[[#This Row],[DATA APROV. (CR)]]="N/A","APROVADO",IF(TB_INTEGRADA[[#This Row],[REVISÃO (CR)]]="","",_xlfn.XLOOKUP(TB_INTEGRADA[[#This Row],[Nº SS]],'CONTROLE CRONOG'!B:B,'CONTROLE CRONOG'!V:V,"",0,1)))))) -> APROVADO | V14: 46001 | W14: 46006 | X14: =IFERROR(TB_INTEGRADA[[#This Row],[TÉRM. TD]]-TB_INTEGRADA[[#This Row],[TÉRMINO LB]],0) -> 5 | Y14: 1 | Z14: 1 | AA14: 0 | AB14: =IFERROR(TB_INTEGRADA[[#This Row],[REAL (%)]]-TB_INTEGRADA[[#This Row],[PREV (%)]],0) -> 0 | AC14: 0 | AD14: 0 | AF14: =IF(TB_INTEGRADA[[#This Row],[TOMADOR]]="EDIVIT",TB_INTEGRADA[[#This Row],[ORÇ DIG]]*1.38,IF(TB_INTEGRADA[[#This Row],[TOMADOR]]="UTGC",TB_INTEGRADA[[#This Row],[ORÇ DIG]]*1.47,IF(TB_INTEGRADA[[#This Row],[TOMADOR]]="TIMS",TB_INTEGRADA[[#This Row],[ORÇ DIG]]*1.34,IF(TB_INTEGRADA[[#This Row],[TOMADOR]]="UTGSUL",TB_INTEGRADA[[#This Row],[ORÇ DIG]]*1.37,IF(TB_INTEGRADA[[#This Row],[TOMADOR]]="REGAP",TB_INTEGRADA[[#This Row],[ORÇ DIG]]*1.36,IF(TB_INTEGRADA[[#This Row],[TOMADOR]]="UTEIBI",TB_INTEGRADA[[#This Row],[ORÇ DIG]]*1.5,"S/TOMADOR")))))) -> 912.5907 | AG14: 620.81 | AH14: =SUMIFS(Tb_HhPLAN[Hh DISC],Tb_HhPLAN[SS],TB_INTEGRADA[[#This Row],[Nº SS]],Tb_HhPLAN[DISCIPLINA],"MEC") -> 1326.5612 | AI14: =SUMIFS(Hh_EXE_TOTAL[Hh],Hh_EXE_TOTAL[Nº SS],TB_INTEGRADA[[#This Row],[Nº SS]],Hh_EXE_TOTAL[DISCIPLINA],"MEC") -> 2179.3429 | AJ14: =IF(TB_INTEGRADA[[#This Row],[TOMADOR]]="EDIVIT",TB_INTEGRADA[[#This Row],[ORÇ DIG1]]*1.38,IF(TB_INTEGRADA[[#This Row],[TOMADOR]]="UTGC",TB_INTEGRADA[[#This Row],[ORÇ DIG1]]*1.47,IF(TB_INTEGRADA[[#This Row],[TOMADOR]]="TIMS",TB_INTEGRADA[[#This Row],[ORÇ DIG1]]*1.34,IF(TB_INTEGRADA[[#This Row],[TOMADOR]]="UTGSUL",TB_INTEGRADA[[#This Row],[ORÇ DIG1]]*1.37,IF(TB_INTEGRADA[[#This Row],[TOMADOR]]="REGAP",TB_INTEGRADA[[#This Row],[ORÇ DIG1]]*1.36,IF(TB_INTEGRADA[[#This Row],[TOMADOR]]="UTEIBI",TB_INTEGRADA[[#This Row],[ORÇ DIG1]]*1.5,"S/TOMADOR")))))) -> 0 | AK14: 0 | AL14: =SUMIFS(Tb_HhPLAN[Hh DISC],Tb_HhPLAN[SS],TB_INTEGRADA[[#This Row],[Nº SS]],Tb_HhPLAN[DISCIPLINA],"CIVIL") -> 0 | AM14: =SUMIFS(Hh_EXE_TOTAL[Hh],Hh_EXE_TOTAL[Nº SS],TB_INTEGRADA[[#This Row],[Nº SS]],Hh_EXE_TOTAL[DISCIPLINA],"CIVIL") -> 109.24025 | AN14: =IF(TB_INTEGRADA[[#This Row],[TOMADOR]]="EDIVIT",TB_INTEGRADA[[#This Row],[ORÇ DIG2]]*1.38,IF(TB_INTEGRADA[[#This Row],[TOMADOR]]="UTGC",TB_INTEGRADA[[#This Row],[ORÇ DIG2]]*1.47,IF(TB_INTEGRADA[[#This Row],[TOMADOR]]="TIMS",TB_INTEGRADA[[#This Row],[ORÇ DIG2]]*1.34,IF(TB_INTEGRADA[[#This Row],[TOMADOR]]="UTGSUL",TB_INTEGRADA[[#This Row],[ORÇ DIG2]]*1.37,IF(TB_INTEGRADA[[#This Row],[TOMADOR]]="REGAP",TB_INTEGRADA[[#This Row],[ORÇ DIG2]]*1.36,IF(TB_INTEGRADA[[#This Row],[TOMADOR]]="UTEIBI",TB_INTEGRADA[[#This Row],[ORÇ DIG2]]*1.5,"S/TOMADOR")))))) -> 183.4266 | AO14: 124.78 | AP14: =SUMIFS(Tb_HhPLAN[Hh DISC],Tb_HhPLAN[SS],TB_INTEGRADA[[#This Row],[Nº SS]],Tb_HhPLAN[DISCIPLINA],"ELÉT") -> 215.42446 | AQ14: =SUMIFS(Hh_EXE_TOTAL[Hh],Hh_EXE_TOTAL[Nº SS],TB_INTEGRADA[[#This Row],[Nº SS]],Hh_EXE_TOTAL[DISCIPLINA],"ELÉT") -> 87.392197 | AR14: =IF(TB_INTEGRADA[[#This Row],[TOMADOR]]="EDIVIT",TB_INTEGRADA[[#This Row],[ORÇ DIG3]]*1.38,IF(TB_INTEGRADA[[#This Row],[TOMADOR]]="UTGC",TB_INTEGRADA[[#This Row],[ORÇ DIG3]]*1.47,IF(TB_INTEGRADA[[#This Row],[TOMADOR]]="TIMS",TB_INTEGRADA[[#This Row],[ORÇ DIG3]]*1.34,IF(TB_INTEGRADA[[#This Row],[TOMADOR]]="UTGSUL",TB_INTEGRADA[[#This Row],[ORÇ DIG3]]*1.37,IF(TB_INTEGRADA[[#This Row],[TOMADOR]]="REGAP",TB_INTEGRADA[[#This Row],[ORÇ DIG3]]*1.36,IF(TB_INTEGRADA[[#This Row],[TOMADOR]]="UTEIBI",TB_INTEGRADA[[#This Row],[ORÇ DIG3]]*1.5,"S/TOMADOR")))))) -> 70.5453 | AS14: 47.99 | AT14: =SUMIFS(Tb_HhPLAN[Hh DISC],Tb_HhPLAN[SS],TB_INTEGRADA[[#This Row],[Nº SS]],Tb_HhPLAN[DISCIPLINA],"PINT") -> 34.014388 | AU14: =SUMIFS(Hh_EXE_TOTAL[Hh],Hh_EXE_TOTAL[Nº SS],TB_INTEGRADA[[#This Row],[Nº SS]],Hh_EXE_TOTAL[DISCIPLINA],"PINT") -> 284.02464 | AV14: =TB_INTEGRADA[[#This Row],[ORÇADO]]+TB_INTEGRADA[[#This Row],[ORÇADO1]]+TB_INTEGRADA[[#This Row],[ORÇADO2]]+TB_INTEGRADA[[#This Row],[ORÇADO3]] -> 1166.5626 | AW14: =TB_INTEGRADA[[#This Row],[PLANEJ]]+TB_INTEGRADA[[#This Row],[PLANEJ1]]+TB_INTEGRADA[[#This Row],[PLANEJ2]]+TB_INTEGRADA[[#This Row],[PLANEJ3]] -> 1576 | AX14: =TB_INTEGRADA[[#This Row],[REALIZ]]+TB_INTEGRADA[[#This Row],[REALIZ1]]+TB_INTEGRADA[[#This Row],[REALIZ2]]+TB_INTEGRADA[[#This Row],[REALIZ3]] -> 2660 | AY14: =IFERROR(TB_INTEGRADA[[#This Row],[REALIZ4]]/TB_INTEGRADA[[#This Row],[ORÇADO4]],"") -> 2.2802034 | AZ14: =_xlfn.XLOOKUP(TB_INTEGRADA[[#This Row],[Nº SS]],'CONTROLE EC'!B:B,'CONTROLE EC'!W:W,"",0,1) -> 588935.4 | BA14: =_xlfn.XLOOKUP(TB_INTEGRADA[[#This Row],[Nº SS]],'CONTROLE EC'!B:B,'CONTROLE EC'!X:X,"",0,1) -> 588935.4 | BB14: =_xlfn.XLOOKUP(TB_INTEGRADA[[#This Row],[Nº SS]],'CONTROLE EC'!B:B,'CONTROLE EC'!Y:Y,"",0,1) -> 0
A15: =IF(COUNTIFS($B$5:B15,TB_INTEGRADA[[#This Row],[Nº SS]])<>1,"",COUNTIFS($B$5:B15,TB_INTEGRADA[[#This Row],[Nº SS]])) -> 1 | B15: SS-10/2025 | C15: =_xlfn.XLOOKUP(TB_INTEGRADA[[#This Row],[Nº SS]],'CONTROLE EC'!B:B,'CONTROLE EC'!C:C,"",0,1) -> 24-0096-ES - REFORMA DA COBERTURA DO K-04 | D15: =_xlfn.XLOOKUP(TB_INTEGRADA[[#This Row],[Nº SS]],'CONTROLE CRONOG'!B:B,'CONTROLE CRONOG'!D:D,"",0,1) -> SERVIÇO | E15: =_xlfn.XLOOKUP(TB_INTEGRADA[[#This Row],[Nº SS]],'CONTROLE EC'!B:B,'CONTROLE EC'!E:E,"",0,1) -> UTGC | F15: =_xlfn.XLOOKUP(TB_INTEGRADA[[#This Row],[Nº SS]],'CONTROLE EC'!B:B,'CONTROLE EC'!F:F,"",0,1) -> CONCLUÍDA | G15: =_xlfn.XLOOKUP(TB_INTEGRADA[[#This Row],[Nº SS]],'CONTROLE EC'!B:B,'CONTROLE EC'!R:R,"",0,1) -> REV.04 | H15: =IF(TB_INTEGRADA[[#This Row],[REVISÃO (EC)]]="","",_xlfn.XLOOKUP(TB_INTEGRADA[[#This Row],[Nº SS]],'CONTROLE EC'!B:B,'CONTROLE EC'!S:S,"",0,1)) -> 45954 | I15: =IF(TB_INTEGRADA[[#This Row],[REVISÃO (EC)]]="","",_xlfn.XLOOKUP(TB_INTEGRADA[[#This Row],[Nº SS]],'CONTROLE EC'!B:B,'CONTROLE EC'!U:U,"",0,1)) -> 45954 | J15: {=IF(TB_INTEGRADA[[#This Row],[DATA ENVIO. (EC)]]=IFERROR(INDEX('CONTROLE EC'!G15:Q15,MATCH(2,1/('CONTROLE EC'!G15:Q15<>""))),""),"",IFERROR(INDEX('CONTROLE EC'!G15:Q15,MATCH(2,1/('CONTROLE EC'!G15:Q15<>""))),""))} | K15: =IF(TB_INTEGRADA[[#This Row],[STATUS DEMANDA]]="NÃO EMITIDA SAMC","S/ EMISSÃO",_xlfn.XLOOKUP(TB_INTEGRADA[[#This Row],[Nº SS]],'CONTROLE EC'!B:B,'CONTROLE EC'!T:T,"",0,-1)) -> ENTREGUE | L15: =IF(TB_INTEGRADA[[#This Row],[STATUS DEMANDA]]="NÃO EMITIDA SAMC","S/ EMISSÃO",IF(TB_INTEGRADA[[#This Row],[STATUS DEMANDA]]="ON HOLD","ON HOLD",IF(TB_INTEGRADA[[#This Row],[STATUS DEMANDA]]="CANCELADA","CANCELADA",IF(TB_INTEGRADA[[#This Row],[DATA APROV. (EC)]]=0,"FISCALIZ.",IF(TB_INTEGRADA[[#This Row],[DATA APROV. (EC)]]="","PEND. FISCALIZ.",IF(TB_INTEGRADA[[#This Row],[DATA APROV. (EC)]]="N/A","APROVADO",IF(TB_INTEGRADA[[#This Row],[REVISÃO (EC)]]="","",_xlfn.XLOOKUP(TB_INTEGRADA[[#This Row],[Nº SS]],'CONTROLE EC'!B:B,'CONTROLE EC'!V:V,"",0,1)))))))) -> APROVADO | M15: {=IFERROR(_xlfn.IFS(TB_INTEGRADA[[#This Row],[STATUS DEMANDA]]="CANCELADA",0,TB_INTEGRADA[[#This Row],[DATA APROV. (EC)]]="",TODAY()-TB_INTEGRADA[[#This Row],[DATA ENVIO. (EC)]],TB_INTEGRADA[[#This Row],[DATA APROV. (EC)]]>=TB_INTEGRADA[[#This Row],[DATA ENVIO. (EC)]],0,TB_INTEGRADA[[#This Row],[DATA ENVIO. (EC)]]="",0,TB_INTEGRADA[[#This Row],[DATA ENVIO. (EC)]]>TB_INTEGRADA[[#This Row],[DATA APROV. (EC)]],TODAY()-TB_INTEGRADA[[#This Row],[DATA ENVIO. (EC)]]),"")} -> 0 | N15: =IF(TB_INTEGRADA[[#This Row],[STATUS DEMANDA]]="NÃO EMITIDA SAMC","S/ EMISSÃO",IF(TB_INTEGRADA[[#This Row],[STATUS DEMANDA]]="ON HOLD","ON HOLD",IF(F15="CANCELADA","CANCELADA",IF(L15="REPROVADO","EM PLANEJ.",IF(K15<>"ENTREGUE","EM PLANEJ.",IF(H15="","EM PLANEJ.",IF(I15="","FISCALIZ.",IF(M15<0,"EM PLANEJ.",IF(TB_INTEGRADA[[#This Row],[DATA APROV. (EC)]]>=TB_INTEGRADA[[#This Row],[DATA ENVIO. (EC)]],"RETORNO OK","FISCALIZ."))))))))) -> RETORNO OK | O15: =_xlfn.XLOOKUP(TB_INTEGRADA[[#This Row],[Nº SS]],'CONTROLE CRONOG'!B:B,'CONTROLE CRONOG'!R:R,"",0,1) -> REV.03 | P15: =IF(TB_INTEGRADA[[#This Row],[REVISÃO (CR)]]="","",_xlfn.XLOOKUP(TB_INTEGRADA[[#This Row],[Nº SS]],'CONTROLE CRONOG'!B:B,'CONTROLE CRONOG'!S:S,"",0,1)) -> 45954 | Q15: =IF(TB_INTEGRADA[[#This Row],[REVISÃO (CR)]]="","",_xlfn.XLOOKUP(TB_INTEGRADA[[#This Row],[Nº SS]],'CONTROLE CRONOG'!B:B,'CONTROLE CRONOG'!U:U,"",0,1)) -> 45954 | R15: {=IF(TB_INTEGRADA[[#This Row],[DATA ENVIO. (CR)]]=IFERROR(INDEX('CONTROLE CRONOG'!G15:Q15,MATCH(2,1/('CONTROLE CRONOG'!G15:Q15<>""))),""),"",IFERROR(INDEX('CONTROLE CRONOG'!G15:Q15,MATCH(2,1/('CONTROLE CRONOG'!G15:Q15<>""))),""))} | S15: =_xlfn.XLOOKUP(TB_INTEGRADA[[#This Row],[Nº SS]],'CONTROLE CRONOG'!B:B,'CONTROLE CRONOG'!T:T,"",0,-1) -> ENTREGUE | T15: =IF(TB_INTEGRADA[[#This Row],[STATUS DEMANDA]]="ON HOLD","ON HOLD",IF(TB_INTEGRADA[[#This Row],[STATUS DEMANDA]]="CANCELADA","CANCELADA",IF(TB_INTEGRADA[[#This Row],[DATA APROV. (CR)]]=0,"FISCALIZ.",IF(TB_INTEGRADA[[#This Row],[DATA APROV. (CR)]]="N/A","APROVADO",IF(TB_INTEGRADA[[#This Row],[REVISÃO (CR)]]="","",_xlfn.XLOOKUP(TB_INTEGRADA[[#This Row],[Nº SS]],'CONTROLE CRONOG'!B:B,'CONTROLE CRONOG'!V:V,"",0,1)))))) -> APROVADO | V15: 46063 | W15: 46031 | X15: =IFERROR(TB_INTEGRADA[[#This Row],[TÉRM. TD]]-TB_INTEGRADA[[#This Row],[TÉRMINO LB]],0) -> -32 | Y15: 0.5919 | Z15: 1 | AA15: 0.4081 | AB15: =IFERROR(TB_INTEGRADA[[#This Row],[REAL (%)]]-TB_INTEGRADA[[#This Row],[PREV (%)]],0) -> 0.4081 | AC15: 0 | AD15: 0 | AF15: =IF(TB_INTEGRADA[[#This Row],[TOMADOR]]="EDIVIT",TB_INTEGRADA[[#This Row],[ORÇ DIG]]*1.38,IF(TB_INTEGRADA[[#This Row],[TOMADOR]]="UTGC",TB_INTEGRADA[[#This Row],[ORÇ DIG]]*1.47,IF(TB_INTEGRADA[[#This Row],[TOMADOR]]="TIMS",TB_INTEGRADA[[#This Row],[ORÇ DIG]]*1.34,IF(TB_INTEGRADA[[#This Row],[TOMADOR]]="UTGSUL",TB_INTEGRADA[[#This Row],[ORÇ DIG]]*1.37,IF(TB_INTEGRADA[[#This Row],[TOMADOR]]="REGAP",TB_INTEGRADA[[#This Row],[ORÇ DIG]]*1.36,IF(TB_INTEGRADA[[#This Row],[TOMADOR]]="UTEIBI",TB_INTEGRADA[[#This Row],[ORÇ DIG]]*1.5,"S/TOMADOR")))))) -> 519.6744 | AG15: 353.52 | AH15: =SUMIFS(Tb_HhPLAN[Hh DISC],Tb_HhPLAN[SS],TB_INTEGRADA[[#This Row],[Nº SS]],Tb_HhPLAN[DISCIPLINA],"MEC") -> 734.18605 | AI15: =SUMIFS(Hh_EXE_TOTAL[Hh],Hh_EXE_TOTAL[Nº SS],TB_INTEGRADA[[#This Row],[Nº SS]],Hh_EXE_TOTAL[DISCIPLINA],"MEC") -> 501.04348 | AJ15: =IF(TB_INTEGRADA[[#This Row],[TOMADOR]]="EDIVIT",TB_INTEGRADA[[#This Row],[ORÇ DIG1]]*1.38,IF(TB_INTEGRADA[[#This Row],[TOMADOR]]="UTGC",TB_INTEGRADA[[#This Row],[ORÇ DIG1]]*1.47,IF(TB_INTEGRADA[[#This Row],[TOMADOR]]="TIMS",TB_INTEGRADA[[#This Row],[ORÇ DIG1]]*1.34,IF(TB_INTEGRADA[[#This Row],[TOMADOR]]="UTGSUL",TB_INTEGRADA[[#This Row],[ORÇ DIG1]]*1.37,IF(TB_INTEGRADA[[#This Row],[TOMADOR]]="REGAP",TB_INTEGRADA[[#This Row],[ORÇ DIG1]]*1.36,IF(TB_INTEGRADA[[#This Row],[TOMADOR]]="UTEIBI",TB_INTEGRADA[[#This Row],[ORÇ DIG1]]*1.5,"S/TOMADOR")))))) -> 287.3115 | AK15: 195.45 | AL15: =SUMIFS(Tb_HhPLAN[Hh DISC],Tb_HhPLAN[SS],TB_INTEGRADA[[#This Row],[Nº SS]],Tb_HhPLAN[DISCIPLINA],"CIVIL") -> 320.37209 | AM15: =SUMIFS(Hh_EXE_TOTAL[Hh],Hh_EXE_TOTAL[Nº SS],TB_INTEGRADA[[#This Row],[Nº SS]],Hh_EXE_TOTAL[DISCIPLINA],"CIVIL") -> 23.304348 | AN15: =IF(TB_INTEGRADA[[#This Row],[TOMADOR]]="EDIVIT",TB_INTEGRADA[[#This Row],[ORÇ DIG2]]*1.38,IF(TB_INTEGRADA[[#This Row],[TOMADOR]]="UTGC",TB_INTEGRADA[[#This Row],[ORÇ DIG2]]*1.47,IF(TB_INTEGRADA[[#This Row],[TOMADOR]]="TIMS",TB_INTEGRADA[[#This Row],[ORÇ DIG2]]*1.34,IF(TB_INTEGRADA[[#This Row],[TOMADOR]]="UTGSUL",TB_INTEGRADA[[#This Row],[ORÇ DIG2]]*1.37,IF(TB_INTEGRADA[[#This Row],[TOMADOR]]="REGAP",TB_INTEGRADA[[#This Row],[ORÇ DIG2]]*1.36,IF(TB_INTEGRADA[[#This Row],[TOMADOR]]="UTEIBI",TB_INTEGRADA[[#This Row],[ORÇ DIG2]]*1.5,"S/TOMADOR")))))) -> 266.5845 | AO15: 181.35 | AP15: =SUMIFS(Tb_HhPLAN[Hh DISC],Tb_HhPLAN[SS],TB_INTEGRADA[[#This Row],[Nº SS]],Tb_HhPLAN[DISCIPLINA],"ELÉT") -> 93.44186 | AQ15: =SUMIFS(Hh_EXE_TOTAL[Hh],Hh_EXE_TOTAL[Nº SS],TB_INTEGRADA[[#This Row],[Nº SS]],Hh_EXE_TOTAL[DISCIPLINA],"ELÉT") -> 11.652174 | AR15: =IF(TB_INTEGRADA[[#This Row],[TOMADOR]]="EDIVIT",TB_INTEGRADA[[#This Row],[ORÇ DIG3]]*1.38,IF(TB_INTEGRADA[[#This Row],[TOMADOR]]="UTGC",TB_INTEGRADA[[#This Row],[ORÇ DIG3]]*1.47,IF(TB_INTEGRADA[[#This Row],[TOMADOR]]="TIMS",TB_INTEGRADA[[#This Row],[ORÇ DIG3]]*1.34,IF(TB_INTEGRADA[[#This Row],[TOMADOR]]="UTGSUL",TB_INTEGRADA[[#This Row],[ORÇ DIG3]]*1.37,IF(TB_INTEGRADA[[#This Row],[TOMADOR]]="REGAP",TB_INTEGRADA[[#This Row],[ORÇ DIG3]]*1.36,IF(TB_INTEGRADA[[#This Row],[TOMADOR]]="UTEIBI",TB_INTEGRADA[[#This Row],[ORÇ DIG3]]*1.5,"S/TOMADOR")))))) -> 72.2652 | AS15: 49.16 | AT15: =SUMIFS(Tb_HhPLAN[Hh DISC],Tb_HhPLAN[SS],TB_INTEGRADA[[#This Row],[Nº SS]],Tb_HhPLAN[DISCIPLINA],"PINT") -> 0 | AU15: =SUMIFS(Hh_EXE_TOTAL[Hh],Hh_EXE_TOTAL[Nº SS],TB_INTEGRADA[[#This Row],[Nº SS]],Hh_EXE_TOTAL[DISCIPLINA],"PINT") -> 0 | AV15: =TB_INTEGRADA[[#This Row],[ORÇADO]]+TB_INTEGRADA[[#This Row],[ORÇADO1]]+TB_INTEGRADA[[#This Row],[ORÇADO2]]+TB_INTEGRADA[[#This Row],[ORÇADO3]] -> 1145.8356 | AW15: =TB_INTEGRADA[[#This Row],[PLANEJ]]+TB_INTEGRADA[[#This Row],[PLANEJ1]]+TB_INTEGRADA[[#This Row],[PLANEJ2]]+TB_INTEGRADA[[#This Row],[PLANEJ3]] -> 1148 | AX15: =TB_INTEGRADA[[#This Row],[REALIZ]]+TB_INTEGRADA[[#This Row],[REALIZ1]]+TB_INTEGRADA[[#This Row],[REALIZ2]]+TB_INTEGRADA[[#This Row],[REALIZ3]] -> 536 | AY15: =IFERROR(TB_INTEGRADA[[#This Row],[REALIZ4]]/TB_INTEGRADA[[#This Row],[ORÇADO4]],"") -> 0.46778089 | AZ15: =_xlfn.XLOOKUP(TB_INTEGRADA[[#This Row],[Nº SS]],'CONTROLE EC'!B:B,'CONTROLE EC'!W:W,"",0,1) -> 364522.27 | BA15: =_xlfn.XLOOKUP(TB_INTEGRADA[[#This Row],[Nº SS]],'CONTROLE EC'!B:B,'CONTROLE EC'!X:X,"",0,1) -> 364522.27 | BB15: =_xlfn.XLOOKUP(TB_INTEGRADA[[#This Row],[Nº SS]],'CONTROLE EC'!B:B,'CONTROLE EC'!Y:Y,"",0,1) -> 0
A16: =IF(COUNTIFS($B$5:B16,TB_INTEGRADA[[#This Row],[Nº SS]])<>1,"",COUNTIFS($B$5:B16,TB_INTEGRADA[[#This Row],[Nº SS]])) -> 1 | B16: SS-11/2025 | C16: =_xlfn.XLOOKUP(TB_INTEGRADA[[#This Row],[Nº SS]],'CONTROLE EC'!B:B,'CONTROLE EC'!C:C,"",0,1) -> 21-0007-ES - DESMONTAGEM DO GALPÃO DA UPCGN-1 | D16: =_xlfn.XLOOKUP(TB_INTEGRADA[[#This Row],[Nº SS]],'CONTROLE CRONOG'!B:B,'CONTROLE CRONOG'!D:D,"",0,1) -> SERVIÇO | E16: =_xlfn.XLOOKUP(TB_INTEGRADA[[#This Row],[Nº SS]],'CONTROLE EC'!B:B,'CONTROLE EC'!E:E,"",0,1) -> UTGC | F16: =_xlfn.XLOOKUP(TB_INTEGRADA[[#This Row],[Nº SS]],'CONTROLE EC'!B:B,'CONTROLE EC'!F:F,"",0,1) -> CONCLUÍDA | G16: =_xlfn.XLOOKUP(TB_INTEGRADA[[#This Row],[Nº SS]],'CONTROLE EC'!B:B,'CONTROLE EC'!R:R,"",0,1) -> REV.06 | H16: =IF(TB_INTEGRADA[[#This Row],[REVISÃO (EC)]]="","",_xlfn.XLOOKUP(TB_INTEGRADA[[#This Row],[Nº SS]],'CONTROLE EC'!B:B,'CONTROLE EC'!S:S,"",0,1)) -> 45932 | I16: =IF(TB_INTEGRADA[[#This Row],[REVISÃO (EC)]]="","",_xlfn.XLOOKUP(TB_INTEGRADA[[#This Row],[Nº SS]],'CONTROLE EC'!B:B,'CONTROLE EC'!U:U,"",0,1)) -> 45932 | J16: {=IF(TB_INTEGRADA[[#This Row],[DATA ENVIO. (EC)]]=IFERROR(INDEX('CONTROLE EC'!G16:Q16,MATCH(2,1/('CONTROLE EC'!G16:Q16<>""))),""),"",IFERROR(INDEX('CONTROLE EC'!G16:Q16,MATCH(2,1/('CONTROLE EC'!G16:Q16<>""))),""))} | K16: =IF(TB_INTEGRADA[[#This Row],[STATUS DEMANDA]]="NÃO EMITIDA SAMC","S/ EMISSÃO",_xlfn.XLOOKUP(TB_INTEGRADA[[#This Row],[Nº SS]],'CONTROLE EC'!B:B,'CONTROLE EC'!T:T,"",0,-1)) -> ENTREGUE | L16: =IF(TB_INTEGRADA[[#This Row],[STATUS DEMANDA]]="NÃO EMITIDA SAMC","S/ EMISSÃO",IF(TB_INTEGRADA[[#This Row],[STATUS DEMANDA]]="ON HOLD","ON HOLD",IF(TB_INTEGRADA[[#This Row],[STATUS DEMANDA]]="CANCELADA","CANCELADA",IF(TB_INTEGRADA[[#This Row],[DATA APROV. (EC)]]=0,"FISCALIZ.",IF(TB_INTEGRADA[[#This Row],[DATA APROV. (EC)]]="","PEND. FISCALIZ.",IF(TB_INTEGRADA[[#This Row],[DATA APROV. (EC)]]="N/A","APROVADO",IF(TB_INTEGRADA[[#This Row],[REVISÃO (EC)]]="","",_xlfn.XLOOKUP(TB_INTEGRADA[[#This Row],[Nº SS]],'CONTROLE EC'!B:B,'CONTROLE EC'!V:V,"",0,1)))))))) -> APROVADO | M16: {=IFERROR(_xlfn.IFS(TB_INTEGRADA[[#This Row],[STATUS DEMANDA]]="CANCELADA",0,TB_INTEGRADA[[#This Row],[DATA APROV. (EC)]]="",TODAY()-TB_INTEGRADA[[#This Row],[DATA ENVIO. (EC)]],TB_INTEGRADA[[#This Row],[DATA APROV. (EC)]]>=TB_INTEGRADA[[#This Row],[DATA ENVIO. (EC)]],0,TB_INTEGRADA[[#This Row],[DATA ENVIO. (EC)]]="",0,TB_INTEGRADA[[#This Row],[DATA ENVIO. (EC)]]>TB_INTEGRADA[[#This Row],[DATA APROV. (EC)]],TODAY()-TB_INTEGRADA[[#This Row],[DATA ENVIO. (EC)]]),"")} -> 0 | N16: =IF(TB_INTEGRADA[[#This Row],[STATUS DEMANDA]]="NÃO EMITIDA SAMC","S/ EMISSÃO",IF(TB_INTEGRADA[[#This Row],[STATUS DEMANDA]]="ON HOLD","ON HOLD",IF(F16="CANCELADA","CANCELADA",IF(L16="REPROVADO","EM PLANEJ.",IF(K16<>"ENTREGUE","EM PLANEJ.",IF(H16="","EM PLANEJ.",IF(I16="","FISCALIZ.",IF(M16<0,"EM PLANEJ.",IF(TB_INTEGRADA[[#This Row],[DATA APROV. (EC)]]>=TB_INTEGRADA[[#This Row],[DATA ENVIO. (EC)]],"RETORNO OK","FISCALIZ."))))))))) -> RETORNO OK | O16: =_xlfn.XLOOKUP(TB_INTEGRADA[[#This Row],[Nº SS]],'CONTROLE CRONOG'!B:B,'CONTROLE CRONOG'!R:R,"",0,1) -> REV.04 | P16: =IF(TB_INTEGRADA[[#This Row],[REVISÃO (CR)]]="","",_xlfn.XLOOKUP(TB_INTEGRADA[[#This Row],[Nº SS]],'CONTROLE CRONOG'!B:B,'CONTROLE CRONOG'!S:S,"",0,1)) -> 45923 | Q16: =IF(TB_INTEGRADA[[#This Row],[REVISÃO (CR)]]="","",_xlfn.XLOOKUP(TB_INTEGRADA[[#This Row],[Nº SS]],'CONTROLE CRONOG'!B:B,'CONTROLE CRONOG'!U:U,"",0,1)) -> 45924 | R16: {=IF(TB_INTEGRADA[[#This Row],[DATA ENVIO. (CR)]]=IFERROR(INDEX('CONTROLE CRONOG'!G16:Q16,MATCH(2,1/('CONTROLE CRONOG'!G16:Q16<>""))),""),"",IFERROR(INDEX('CONTROLE CRONOG'!G16:Q16,MATCH(2,1/('CONTROLE CRONOG'!G16:Q16<>""))),""))} | S16: =_xlfn.XLOOKUP(TB_INTEGRADA[[#This Row],[Nº SS]],'CONTROLE CRONOG'!B:B,'CONTROLE CRONOG'!T:T,"",0,-1) -> ENTREGUE | T16: =IF(TB_INTEGRADA[[#This Row],[STATUS DEMANDA]]="ON HOLD","ON HOLD",IF(TB_INTEGRADA[[#This Row],[STATUS DEMANDA]]="CANCELADA","CANCELADA",IF(TB_INTEGRADA[[#This Row],[DATA APROV. (CR)]]=0,"FISCALIZ.",IF(TB_INTEGRADA[[#This Row],[DATA APROV. (CR)]]="N/A","APROVADO",IF(TB_INTEGRADA[[#This Row],[REVISÃO (CR)]]="","",_xlfn.XLOOKUP(TB_INTEGRADA[[#This Row],[Nº SS]],'CONTROLE CRONOG'!B:B,'CONTROLE CRONOG'!V:V,"",0,1)))))) -> APROVADO | V16: 45968 | W16: 45989 | X16: =IFERROR(TB_INTEGRADA[[#This Row],[TÉRM. TD]]-TB_INTEGRADA[[#This Row],[TÉRMINO LB]],0) -> 21 | Y16: 1 | Z16: 1 | AA16: 0 | AB16: =IFERROR(TB_INTEGRADA[[#This Row],[REAL (%)]]-TB_INTEGRADA[[#This Row],[PREV (%)]],0) -> 0 | AF16: =IF(TB_INTEGRADA[[#This Row],[TOMADOR]]="EDIVIT",TB_INTEGRADA[[#This Row],[ORÇ DIG]]*1.38,IF(TB_INTEGRADA[[#This Row],[TOMADOR]]="UTGC",TB_INTEGRADA[[#This Row],[ORÇ DIG]]*1.47,IF(TB_INTEGRADA[[#This Row],[TOMADOR]]="TIMS",TB_INTEGRADA[[#This Row],[ORÇ DIG]]*1.34,IF(TB_INTEGRADA[[#This Row],[TOMADOR]]="UTGSUL",TB_INTEGRADA[[#This Row],[ORÇ DIG]]*1.37,IF(TB_INTEGRADA[[#This Row],[TOMADOR]]="REGAP",TB_INTEGRADA[[#This Row],[ORÇ DIG]]*1.36,IF(TB_INTEGRADA[[#This Row],[TOMADOR]]="UTEIBI",TB_INTEGRADA[[#This Row],[ORÇ DIG]]*1.5,"S/TOMADOR")))))) -> 2259.0519 | AG16: 1536.77 | AH16: =SUMIFS(Tb_HhPLAN[Hh DISC],Tb_HhPLAN[SS],TB_INTEGRADA[[#This Row],[Nº SS]],Tb_HhPLAN[DISCIPLINA],"MEC") -> 897.85507 | AI16: =SUMIFS(Hh_EXE_TOTAL[Hh],Hh_EXE_TOTAL[Nº SS],TB_INTEGRADA[[#This Row],[Nº SS]],Hh_EXE_TOTAL[DISCIPLINA],"MEC") -> 1803.8333 | AJ16: =IF(TB_INTEGRADA[[#This Row],[TOMADOR]]="EDIVIT",TB_INTEGRADA[[#This Row],[ORÇ DIG1]]*1.38,IF(TB_INTEGRADA[[#This Row],[TOMADOR]]="UTGC",TB_INTEGRADA[[#This Row],[ORÇ DIG1]]*1.47,IF(TB_INTEGRADA[[#This Row],[TOMADOR]]="TIMS",TB_INTEGRADA[[#This Row],[ORÇ DIG1]]*1.34,IF(TB_INTEGRADA[[#This Row],[TOMADOR]]="UTGSUL",TB_INTEGRADA[[#This Row],[ORÇ DIG1]]*1.37,IF(TB_INTEGRADA[[#This Row],[TOMADOR]]="REGAP",TB_INTEGRADA[[#This Row],[ORÇ DIG1]]*1.36,IF(TB_INTEGRADA[[#This Row],[TOMADOR]]="UTEIBI",TB_INTEGRADA[[#This Row],[ORÇ DIG1]]*1.5,"S/TOMADOR")))))) -> 0 | AK16: 0 | AL16: =SUMIFS(Tb_HhPLAN[Hh DISC],Tb_HhPLAN[SS],TB_INTEGRADA[[#This Row],[Nº SS]],Tb_HhPLAN[DISCIPLINA],"CIVIL") -> 0 | AM16: =SUMIFS(Hh_EXE_TOTAL[Hh],Hh_EXE_TOTAL[Nº SS],TB_INTEGRADA[[#This Row],[Nº SS]],Hh_EXE_TOTAL[DISCIPLINA],"CIVIL") -> 0 | AN16: =IF(TB_INTEGRADA[[#This Row],[TOMADOR]]="EDIVIT",TB_INTEGRADA[[#This Row],[ORÇ DIG2]]*1.38,IF(TB_INTEGRADA[[#This Row],[TOMADOR]]="UTGC",TB_INTEGRADA[[#This Row],[ORÇ DIG2]]*1.47,IF(TB_INTEGRADA[[#This Row],[TOMADOR]]="TIMS",TB_INTEGRADA[[#This Row],[ORÇ DIG2]]*1.34,IF(TB_INTEGRADA[[#This Row],[TOMADOR]]="UTGSUL",TB_INTEGRADA[[#This Row],[ORÇ DIG2]]*1.37,IF(TB_INTEGRADA[[#This Row],[TOMADOR]]="REGAP",TB_INTEGRADA[[#This Row],[ORÇ DIG2]]*1.36,IF(TB_INTEGRADA[[#This Row],[TOMADOR]]="UTEIBI",TB_INTEGRADA[[#This Row],[ORÇ DIG2]]*1.5,"S/TOMADOR")))))) -> 130.7271 | AO16: 88.93 | AP16: =SUMIFS(Tb_HhPLAN[Hh DISC],Tb_HhPLAN[SS],TB_INTEGRADA[[#This Row],[Nº SS]],Tb_HhPLAN[DISCIPLINA],"ELÉT") -> 70.144928 | AQ16: =SUMIFS(Hh_EXE_TOTAL[Hh],Hh_EXE_TOTAL[Nº SS],TB_INTEGRADA[[#This Row],[Nº SS]],Hh_EXE_TOTAL[DISCIPLINA],"ELÉT") -> 92.166667 | AR16: =IF(TB_INTEGRADA[[#This Row],[TOMADOR]]="EDIVIT",TB_INTEGRADA[[#This Row],[ORÇ DIG3]]*1.38,IF(TB_INTEGRADA[[#This Row],[TOMADOR]]="UTGC",TB_INTEGRADA[[#This Row],[ORÇ DIG3]]*1.47,IF(TB_INTEGRADA[[#This Row],[TOMADOR]]="TIMS",TB_INTEGRADA[[#This Row],[ORÇ DIG3]]*1.34,IF(TB_INTEGRADA[[#This Row],[TOMADOR]]="UTGSUL",TB_INTEGRADA[[#This Row],[ORÇ DIG3]]*1.37,IF(TB_INTEGRADA[[#This Row],[TOMADOR]]="REGAP",TB_INTEGRADA[[#This Row],[ORÇ DIG3]]*1.36,IF(TB_INTEGRADA[[#This Row],[TOMADOR]]="UTEIBI",TB_INTEGRADA[[#This Row],[ORÇ DIG3]]*1.5,"S/TOMADOR")))))) -> 0 | AS16: 0 | AT16: =SUMIFS(Tb_HhPLAN[Hh DISC],Tb_HhPLAN[SS],TB_INTEGRADA[[#This Row],[Nº SS]],Tb_HhPLAN[DISCIPLINA],"PINT") -> 0 | AU16: =SUMIFS(Hh_EXE_TOTAL[Hh],Hh_EXE_TOTAL[Nº SS],TB_INTEGRADA[[#This Row],[Nº SS]],Hh_EXE_TOTAL[DISCIPLINA],"PINT") -> 0 | AV16: =TB_INTEGRADA[[#This Row],[ORÇADO]]+TB_INTEGRADA[[#This Row],[ORÇADO1]]+TB_INTEGRADA[[#This Row],[ORÇADO2]]+TB_INTEGRADA[[#This Row],[ORÇADO3]] -> 2389.779 | AW16: =TB_INTEGRADA[[#This Row],[PLANEJ]]+TB_INTEGRADA[[#This Row],[PLANEJ1]]+TB_INTEGRADA[[#This Row],[PLANEJ2]]+TB_INTEGRADA[[#This Row],[PLANEJ3]] -> 968 | AX16: =TB_INTEGRADA[[#This Row],[REALIZ]]+TB_INTEGRADA[[#This Row],[REALIZ1]]+TB_INTEGRADA[[#This Row],[REALIZ2]]+TB_INTEGRADA[[#This Row],[REALIZ3]] -> 1896 | AY16: =IFERROR(TB_INTEGRADA[[#This Row],[REALIZ4]]/TB_INTEGRADA[[#This Row],[ORÇADO4]],"") -> 0.7933788 | AZ16: =_xlfn.XLOOKUP(TB_INTEGRADA[[#This Row],[Nº SS]],'CONTROLE EC'!B:B,'CONTROLE EC'!W:W,"",0,1) -> 718931.28 | BA16: =_xlfn.XLOOKUP(TB_INTEGRADA[[#This Row],[Nº SS]],'CONTROLE EC'!B:B,'CONTROLE EC'!X:X,"",0,1) -> 718931.28 | BB16: =_xlfn.XLOOKUP(TB_INTEGRADA[[#This Row],[Nº SS]],'CONTROLE EC'!B:B,'CONTROLE EC'!Y:Y,"",0,1) -> 0
A17: =IF(COUNTIFS($B$5:B17,TB_INTEGRADA[[#This Row],[Nº SS]])<>1,"",COUNTIFS($B$5:B17,TB_INTEGRADA[[#This Row],[Nº SS]])) -> 1 | B17: SS-12/2025 | C17: =_xlfn.XLOOKUP(TB_INTEGRADA[[#This Row],[Nº SS]],'CONTROLE EC'!B:B,'CONTROLE EC'!C:C,"",0,1) -> 22-0496-ES - CONSTRUÇÃO DE ÁREA DE ESTOQUE DE MATERIAIS | D17: =_xlfn.XLOOKUP(TB_INTEGRADA[[#This Row],[Nº SS]],'CONTROLE CRONOG'!B:B,'CONTROLE CRONOG'!D:D,"",0,1) -> SERVIÇO | E17: =_xlfn.XLOOKUP(TB_INTEGRADA[[#This Row],[Nº SS]],'CONTROLE EC'!B:B,'CONTROLE EC'!E:E,"",0,1) -> UTGC | F17: =_xlfn.XLOOKUP(TB_INTEGRADA[[#This Row],[Nº SS]],'CONTROLE EC'!B:B,'CONTROLE EC'!F:F,"",0,1) -> EM ANDAMENTO | G17: =_xlfn.XLOOKUP(TB_INTEGRADA[[#This Row],[Nº SS]],'CONTROLE EC'!B:B,'CONTROLE EC'!R:R,"",0,1) -> REV.02 | H17: =IF(TB_INTEGRADA[[#This Row],[REVISÃO (EC)]]="","",_xlfn.XLOOKUP(TB_INTEGRADA[[#This Row],[Nº SS]],'CONTROLE EC'!B:B,'CONTROLE EC'!S:S,"",0,1)) -> 45951 | I17: =IF(TB_INTEGRADA[[#This Row],[REVISÃO (EC)]]="","",_xlfn.XLOOKUP(TB_INTEGRADA[[#This Row],[Nº SS]],'CONTROLE EC'!B:B,'CONTROLE EC'!U:U,"",0,1)) -> 45952 | J17: {=IF(TB_INTEGRADA[[#This Row],[DATA ENVIO. (EC)]]=IFERROR(INDEX('CONTROLE EC'!G17:Q17,MATCH(2,1/('CONTROLE EC'!G17:Q17<>""))),""),"",IFERROR(INDEX('CONTROLE EC'!G17:Q17,MATCH(2,1/('CONTROLE EC'!G17:Q17<>""))),""))} | K17: =IF(TB_INTEGRADA[[#This Row],[STATUS DEMANDA]]="NÃO EMITIDA SAMC","S/ EMISSÃO",_xlfn.XLOOKUP(TB_INTEGRADA[[#This Row],[Nº SS]],'CONTROLE EC'!B:B,'CONTROLE EC'!T:T,"",0,-1)) -> ENTREGUE | L17: =IF(TB_INTEGRADA[[#This Row],[STATUS DEMANDA]]="NÃO EMITIDA SAMC","S/ EMISSÃO",IF(TB_INTEGRADA[[#This Row],[STATUS DEMANDA]]="ON HOLD","ON HOLD",IF(TB_INTEGRADA[[#This Row],[STATUS DEMANDA]]="CANCELADA","CANCELADA",IF(TB_INTEGRADA[[#This Row],[DATA APROV. (EC)]]=0,"FISCALIZ.",IF(TB_INTEGRADA[[#This Row],[DATA APROV. (EC)]]="","PEND. FISCALIZ.",IF(TB_INTEGRADA[[#This Row],[DATA APROV. (EC)]]="N/A","APROVADO",IF(TB_INTEGRADA[[#This Row],[REVISÃO (EC)]]="","",_xlfn.XLOOKUP(TB_INTEGRADA[[#This Row],[Nº SS]],'CONTROLE EC'!B:B,'CONTROLE EC'!V:V,"",0,1)))))))) -> APROVADO | M17: {=IFERROR(_xlfn.IFS(TB_INTEGRADA[[#This Row],[STATUS DEMANDA]]="CANCELADA",0,TB_INTEGRADA[[#This Row],[DATA APROV. (EC)]]="",TODAY()-TB_INTEGRADA[[#This Row],[DATA ENVIO. (EC)]],TB_INTEGRADA[[#This Row],[DATA APROV. (EC)]]>=TB_INTEGRADA[[#This Row],[DATA ENVIO. (EC)]],0,TB_INTEGRADA[[#This Row],[DATA ENVIO. (EC)]]="",0,TB_INTEGRADA[[#This Row],[DATA ENVIO. (EC)]]>TB_INTEGRADA[[#This Row],[DATA APROV. (EC)]],TODAY()-TB_INTEGRADA[[#This Row],[DATA ENVIO. (EC)]]),"")} -> 0 | N17: =IF(TB_INTEGRADA[[#This Row],[STATUS DEMANDA]]="NÃO EMITIDA SAMC","S/ EMISSÃO",IF(TB_INTEGRADA[[#This Row],[STATUS DEMANDA]]="ON HOLD","ON HOLD",IF(F17="CANCELADA","CANCELADA",IF(L17="REPROVADO","EM PLANEJ.",IF(K17<>"ENTREGUE","EM PLANEJ.",IF(H17="","EM PLANEJ.",IF(I17="","FISCALIZ.",IF(M17<0,"EM PLANEJ.",IF(TB_INTEGRADA[[#This Row],[DATA APROV. (EC)]]>=TB_INTEGRADA[[#This Row],[DATA ENVIO. (EC)]],"RETORNO OK","FISCALIZ."))))))))) -> RETORNO OK | O17: =_xlfn.XLOOKUP(TB_INTEGRADA[[#This Row],[Nº SS]],'CONTROLE CRONOG'!B:B,'CONTROLE CRONOG'!R:R,"",0,1) -> REV.01 | P17: =IF(TB_INTEGRADA[[#This Row],[REVISÃO (CR)]]="","",_xlfn.XLOOKUP(TB_INTEGRADA[[#This Row],[Nº SS]],'CONTROLE CRONOG'!B:B,'CONTROLE CRONOG'!S:S,"",0,1)) -> 45937 | Q17: =IF(TB_INTEGRADA[[#This Row],[REVISÃO (CR)]]="","",_xlfn.XLOOKUP(TB_INTEGRADA[[#This Row],[Nº SS]],'CONTROLE CRONOG'!B:B,'CONTROLE CRONOG'!U:U,"",0,1)) -> 45950 | R17: {=IF(TB_INTEGRADA[[#This Row],[DATA ENVIO. (CR)]]=IFERROR(INDEX('CONTROLE CRONOG'!G17:Q17,MATCH(2,1/('CONTROLE CRONOG'!G17:Q17<>""))),""),"",IFERROR(INDEX('CONTROLE CRONOG'!G17:Q17,MATCH(2,1/('CONTROLE CRONOG'!G17:Q17<>""))),""))} | S17: =_xlfn.XLOOKUP(TB_INTEGRADA[[#This Row],[Nº SS]],'CONTROLE CRONOG'!B:B,'CONTROLE CRONOG'!T:T,"",0,-1) -> ENTREGUE | T17: =IF(TB_INTEGRADA[[#This Row],[STATUS DEMANDA]]="ON HOLD","ON HOLD",IF(TB_INTEGRADA[[#This Row],[STATUS DEMANDA]]="CANCELADA","CANCELADA",IF(TB_INTEGRADA[[#This Row],[DATA APROV. (CR)]]=0,"FISCALIZ.",IF(TB_INTEGRADA[[#This Row],[DATA APROV. (CR)]]="N/A","APROVADO",IF(TB_INTEGRADA[[#This Row],[REVISÃO (CR)]]="","",_xlfn.XLOOKUP(TB_INTEGRADA[[#This Row],[Nº SS]],'CONTROLE CRONOG'!B:B,'CONTROLE CRONOG'!V:V,"",0,1)))))) -> APROVADO | V17: 46106 | W17: 46120 | X17: =IFERROR(TB_INTEGRADA[[#This Row],[TÉRM. TD]]-TB_INTEGRADA[[#This Row],[TÉRMINO LB]],0) -> 14 | Y17: 0.9699 | Z17: 0.7237 | AA17: -0.1504 | AB17: =IFERROR(TB_INTEGRADA[[#This Row],[REAL (%)]]-TB_INTEGRADA[[#This Row],[PREV (%)]],0) -> -0.2462 | AC17: 9 | AD17: 12 | AF17: =IF(TB_INTEGRADA[[#This Row],[TOMADOR]]="EDIVIT",TB_INTEGRADA[[#This Row],[ORÇ DIG]]*1.38,IF(TB_INTEGRADA[[#This Row],[TOMADOR]]="UTGC",TB_INTEGRADA[[#This Row],[ORÇ DIG]]*1.47,IF(TB_INTEGRADA[[#This Row],[TOMADOR]]="TIMS",TB_INTEGRADA[[#This Row],[ORÇ DIG]]*1.34,IF(TB_INTEGRADA[[#This Row],[TOMADOR]]="UTGSUL",TB_INTEGRADA[[#This Row],[ORÇ DIG]]*1.37,IF(TB_INTEGRADA[[#This Row],[TOMADOR]]="REGAP",TB_INTEGRADA[[#This Row],[ORÇ DIG]]*1.36,IF(TB_INTEGRADA[[#This Row],[TOMADOR]]="UTEIBI",TB_INTEGRADA[[#This Row],[ORÇ DIG]]*1.5,"S/TOMADOR")))))) -> 576.1812 | AG17: 391.96 | AH17: =SUMIFS(Tb_HhPLAN[Hh DISC],Tb_HhPLAN[SS],TB_INTEGRADA[[#This Row],[Nº SS]],Tb_HhPLAN[DISCIPLINA],"MEC") -> 765.99206 | AI17: =SUMIFS(Hh_EXE_TOTAL[Hh],Hh_EXE_TOTAL[Nº SS],TB_INTEGRADA[[#This Row],[Nº SS]],Hh_EXE_TOTAL[DISCIPLINA],"MEC") -> 736.42105 | AJ17: =IF(TB_INTEGRADA[[#This Row],[TOMADOR]]="EDIVIT",TB_INTEGRADA[[#This Row],[ORÇ DIG1]]*1.38,IF(TB_INTEGRADA[[#This Row],[TOMADOR]]="UTGC",TB_INTEGRADA[[#This Row],[ORÇ DIG1]]*1.47,IF(TB_INTEGRADA[[#This Row],[TOMADOR]]="TIMS",TB_INTEGRADA[[#This Row],[ORÇ DIG1]]*1.34,IF(TB_INTEGRADA[[#This Row],[TOMADOR]]="UTGSUL",TB_INTEGRADA[[#This Row],[ORÇ DIG1]]*1.37,IF(TB_INTEGRADA[[#This Row],[TOMADOR]]="REGAP",TB_INTEGRADA[[#This Row],[ORÇ DIG1]]*1.36,IF(TB_INTEGRADA[[#This Row],[TOMADOR]]="UTEIBI",TB_INTEGRADA[[#This Row],[ORÇ DIG1]]*1.5,"S/TOMADOR")))))) -> 852.159 | AK17: 579.7 | AL17: =SUMIFS(Tb_HhPLAN[Hh DISC],Tb_HhPLAN[SS],TB_INTEGRADA[[#This Row],[Nº SS]],Tb_HhPLAN[DISCIPLINA],"CIVIL") -> 702.81746 | AM17: =SUMIFS(Hh_EXE_TOTAL[Hh],Hh_EXE_TOTAL[Nº SS],TB_INTEGRADA[[#This Row],[Nº SS]],Hh_EXE_TOTAL[DISCIPLINA],"CIVIL") -> 986.52632 | AN17: =IF(TB_INTEGRADA[[#This Row],[TOMADOR]]="EDIVIT",TB_INTEGRADA[[#This Row],[ORÇ DIG2]]*1.38,IF(TB_INTEGRADA[[#This Row],[TOMADOR]]="UTGC",TB_INTEGRADA[[#This Row],[ORÇ DIG2]]*1.47,IF(TB_INTEGRADA[[#This Row],[TOMADOR]]="TIMS",TB_INTEGRADA[[#This Row],[ORÇ DIG2]]*1.34,IF(TB_INTEGRADA[[#This Row],[TOMADOR]]="UTGSUL",TB_INTEGRADA[[#This Row],[ORÇ DIG2]]*1.37,IF(TB_INTEGRADA[[#This Row],[TOMADOR]]="REGAP",TB_INTEGRADA[[#This Row],[ORÇ DIG2]]*1.36,IF(TB_INTEGRADA[[#This Row],[TOMADOR]]="UTEIBI",TB_INTEGRADA[[#This Row],[ORÇ DIG2]]*1.5,"S/TOMADOR")))))) -> 2684.6757 | AO17: 1826.31 | AP17: =SUMIFS(Tb_HhPLAN[Hh DISC],Tb_HhPLAN[SS],TB_INTEGRADA[[#This Row],[Nº SS]],Tb_HhPLAN[DISCIPLINA],"ELÉT") -> 521.19048 | AQ17: =SUMIFS(Hh_EXE_TOTAL[Hh],Hh_EXE_TOTAL[Nº SS],TB_INTEGRADA[[#This Row],[Nº SS]],Hh_EXE_TOTAL[DISCIPLINA],"ELÉT") -> 389.05263 | AR17: =IF(TB_INTEGRADA[[#This Row],[TOMADOR]]="EDIVIT",TB_INTEGRADA[[#This Row],[ORÇ DIG3]]*1.38,IF(TB_INTEGRADA[[#This Row],[TOMADOR]]="UTGC",TB_INTEGRADA[[#This Row],[ORÇ DIG3]]*1.47,IF(TB_INTEGRADA[[#This Row],[TOMADOR]]="TIMS",TB_INTEGRADA[[#This Row],[ORÇ DIG3]]*1.34,IF(TB_INTEGRADA[[#This Row],[TOMADOR]]="UTGSUL",TB_INTEGRADA[[#This Row],[ORÇ DIG3]]*1.37,IF(TB_INTEGRADA[[#This Row],[TOMADOR]]="REGAP",TB_INTEGRADA[[#This Row],[ORÇ DIG3]]*1.36,IF(TB_INTEGRADA[[#This Row],[TOMADOR]]="UTEIBI",TB_INTEGRADA[[#This Row],[ORÇ DIG3]]*1.5,"S/TOMADOR")))))) -> 42.924 | AS17: 29.2 | AT17: =SUMIFS(Tb_HhPLAN[Hh DISC],Tb_HhPLAN[SS],TB_INTEGRADA[[#This Row],[Nº SS]],Tb_HhPLAN[DISCIPLINA],"PINT") -> 0 | AU17: =SUMIFS(Hh_EXE_TOTAL[Hh],Hh_EXE_TOTAL[Nº SS],TB_INTEGRADA[[#This Row],[Nº SS]],Hh_EXE_TOTAL[DISCIPLINA],"PINT") -> 0 | AV17: =TB_INTEGRADA[[#This Row],[ORÇADO]]+TB_INTEGRADA[[#This Row],[ORÇADO1]]+TB_INTEGRADA[[#This Row],[ORÇADO2]]+TB_INTEGRADA[[#This Row],[ORÇADO3]] -> 4155.9399 | AW17: =TB_INTEGRADA[[#This Row],[PLANEJ]]+TB_INTEGRADA[[#This Row],[PLANEJ1]]+TB_INTEGRADA[[#This Row],[PLANEJ2]]+TB_INTEGRADA[[#This Row],[PLANEJ3]] -> 1990 | AX17: =TB_INTEGRADA[[#This Row],[REALIZ]]+TB_INTEGRADA[[#This Row],[REALIZ1]]+TB_INTEGRADA[[#This Row],[REALIZ2]]+TB_INTEGRADA[[#This Row],[REALIZ3]] -> 2112 | AY17: =IFERROR(TB_INTEGRADA[[#This Row],[REALIZ4]]/TB_INTEGRADA[[#This Row],[ORÇADO4]],"") -> 0.50818829 | AZ17: =_xlfn.XLOOKUP(TB_INTEGRADA[[#This Row],[Nº SS]],'CONTROLE EC'!B:B,'CONTROLE EC'!W:W,"",0,1) -> 1144868.6 | BA17: =_xlfn.XLOOKUP(TB_INTEGRADA[[#This Row],[Nº SS]],'CONTROLE EC'!B:B,'CONTROLE EC'!X:X,"",0,1) -> 457946.07 | BB17: =_xlfn.XLOOKUP(TB_INTEGRADA[[#This Row],[Nº SS]],'CONTROLE EC'!B:B,'CONTROLE EC'!Y:Y,"",0,1) -> 686922.51
A18: =IF(COUNTIFS($B$5:B18,TB_INTEGRADA[[#This Row],[Nº SS]])<>1,"",COUNTIFS($B$5:B18,TB_INTEGRADA[[#This Row],[Nº SS]])) -> 1 | B18: SS-14/2025 | C18: =_xlfn.XLOOKUP(TB_INTEGRADA[[#This Row],[Nº SS]],'CONTROLE EC'!B:B,'CONTROLE EC'!C:C,"",0,1) -> 23-0496-ES - ADEQUAÇÃO DOS SANITÁRIOS COLETIVOS - TORRES LESTE E OESTE | D18: =_xlfn.XLOOKUP(TB_INTEGRADA[[#This Row],[Nº SS]],'CONTROLE CRONOG'!B:B,'CONTROLE CRONOG'!D:D,"",0,1) -> SERVIÇO | E18: =_xlfn.XLOOKUP(TB_INTEGRADA[[#This Row],[Nº SS]],'CONTROLE EC'!B:B,'CONTROLE EC'!E:E,"",0,1) -> EDIVIT | F18: =_xlfn.XLOOKUP(TB_INTEGRADA[[#This Row],[Nº SS]],'CONTROLE EC'!B:B,'CONTROLE EC'!F:F,"",0,1) -> ON HOLD | G18: =_xlfn.XLOOKUP(TB_INTEGRADA[[#This Row],[Nº SS]],'CONTROLE EC'!B:B,'CONTROLE EC'!R:R,"",0,1) -> REV.03 | H18: =IF(TB_INTEGRADA[[#This Row],[REVISÃO (EC)]]="","",_xlfn.XLOOKUP(TB_INTEGRADA[[#This Row],[Nº SS]],'CONTROLE EC'!B:B,'CONTROLE EC'!S:S,"",0,1)) -> 45986 | I18: =IF(TB_INTEGRADA[[#This Row],[REVISÃO (EC)]]="","",_xlfn.XLOOKUP(TB_INTEGRADA[[#This Row],[Nº SS]],'CONTROLE EC'!B:B,'CONTROLE EC'!U:U,"",0,1)) -> 45980 | J18: {=IF(TB_INTEGRADA[[#This Row],[DATA ENVIO. (EC)]]=IFERROR(INDEX('CONTROLE EC'!G18:Q18,MATCH(2,1/('CONTROLE EC'!G18:Q18<>""))),""),"",IFERROR(INDEX('CONTROLE EC'!G18:Q18,MATCH(2,1/('CONTROLE EC'!G18:Q18<>""))),""))} | K18: =IF(TB_INTEGRADA[[#This Row],[STATUS DEMANDA]]="NÃO EMITIDA SAMC","S/ EMISSÃO",_xlfn.XLOOKUP(TB_INTEGRADA[[#This Row],[Nº SS]],'CONTROLE EC'!B:B,'CONTROLE EC'!T:T,"",0,-1)) -> ENTREGUE | L18: =IF(TB_INTEGRADA[[#This Row],[STATUS DEMANDA]]="NÃO EMITIDA SAMC","S/ EMISSÃO",IF(TB_INTEGRADA[[#This Row],[STATUS DEMANDA]]="ON HOLD","ON HOLD",IF(TB_INTEGRADA[[#This Row],[STATUS DEMANDA]]="CANCELADA","CANCELADA",IF(TB_INTEGRADA[[#This Row],[DATA APROV. (EC)]]=0,"FISCALIZ.",IF(TB_INTEGRADA[[#This Row],[DATA APROV. (EC)]]="","PEND. FISCALIZ.",IF(TB_INTEGRADA[[#This Row],[DATA APROV. (EC)]]="N/A","APROVADO",IF(TB_INTEGRADA[[#This Row],[REVISÃO (EC)]]="","",_xlfn.XLOOKUP(TB_INTEGRADA[[#This Row],[Nº SS]],'CONTROLE EC'!B:B,'CONTROLE EC'!V:V,"",0,1)))))))) -> ON HOLD | M18: {=IFERROR(_xlfn.IFS(TB_INTEGRADA[[#This Row],[STATUS DEMANDA]]="CANCELADA",0,TB_INTEGRADA[[#This Row],[DATA APROV. (EC)]]="",TODAY()-TB_INTEGRADA[[#This Row],[DATA ENVIO. (EC)]],TB_INTEGRADA[[#This Row],[DATA APROV. (EC)]]>=TB_INTEGRADA[[#This Row],[DATA ENVIO. (EC)]],0,TB_INTEGRADA[[#This Row],[DATA ENVIO. (EC)]]="",0,TB_INTEGRADA[[#This Row],[DATA ENVIO. (EC)]]>TB_INTEGRADA[[#This Row],[DATA APROV. (EC)]],TODAY()-TB_INTEGRADA[[#This Row],[DATA ENVIO. (EC)]]),"")} -> 122 | N18: =IF(TB_INTEGRADA[[#This Row],[STATUS DEMANDA]]="NÃO EMITIDA SAMC","S/ EMISSÃO",IF(TB_INTEGRADA[[#This Row],[STATUS DEMANDA]]="ON HOLD","ON HOLD",IF(F18="CANCELADA","CANCELADA",IF(L18="REPROVADO","EM PLANEJ.",IF(K18<>"ENTREGUE","EM PLANEJ.",IF(H18="","EM PLANEJ.",IF(I18="","FISCALIZ.",IF(M18<0,"EM PLANEJ.",IF(TB_INTEGRADA[[#This Row],[DATA APROV. (EC)]]>=TB_INTEGRADA[[#This Row],[DATA ENVIO. (EC)]],"RETORNO OK","FISCALIZ."))))))))) -> ON HOLD | O18: =_xlfn.XLOOKUP(TB_INTEGRADA[[#This Row],[Nº SS]],'CONTROLE CRONOG'!B:B,'CONTROLE CRONOG'!R:R,"",0,1) -> REV.02 | P18: =IF(TB_INTEGRADA[[#This Row],[REVISÃO (CR)]]="","",_xlfn.XLOOKUP(TB_INTEGRADA[[#This Row],[Nº SS]],'CONTROLE CRONOG'!B:B,'CONTROLE CRONOG'!S:S,"",0,1)) -> 45986 | Q18: =IF(TB_INTEGRADA[[#This Row],[REVISÃO (CR)]]="","",_xlfn.XLOOKUP(TB_INTEGRADA[[#This Row],[Nº SS]],'CONTROLE CRONOG'!B:B,'CONTROLE CRONOG'!U:U,"",0,1)) -> 45944 | R18: {=IF(TB_INTEGRADA[[#This Row],[DATA ENVIO. (CR)]]=IFERROR(INDEX('CONTROLE CRONOG'!G18:Q18,MATCH(2,1/('CONTROLE CRONOG'!G18:Q18<>""))),""),"",IFERROR(INDEX('CONTROLE CRONOG'!G18:Q18,MATCH(2,1/('CONTROLE CRONOG'!G18:Q18<>""))),""))} | S18: =_xlfn.XLOOKUP(TB_INTEGRADA[[#This Row],[Nº SS]],'CONTROLE CRONOG'!B:B,'CONTROLE CRONOG'!T:T,"",0,-1) -> ENTREGUE | T18: =IF(TB_INTEGRADA[[#This Row],[STATUS DEMANDA]]="ON HOLD","ON HOLD",IF(TB_INTEGRADA[[#This Row],[STATUS DEMANDA]]="CANCELADA","CANCELADA",IF(TB_INTEGRADA[[#This Row],[DATA APROV. (CR)]]=0,"FISCALIZ.",IF(TB_INTEGRADA[[#This Row],[DATA APROV. (CR)]]="N/A","APROVADO",IF(TB_INTEGRADA[[#This Row],[REVISÃO (CR)]]="","",_xlfn.XLOOKUP(TB_INTEGRADA[[#This Row],[Nº SS]],'CONTROLE CRONOG'!B:B,'CONTROLE CRONOG'!V:V,"",0,1)))))) -> ON HOLD | X18: =IFERROR(TB_INTEGRADA[[#This Row],[TÉRM. TD]]-TB_INTEGRADA[[#This Row],[TÉRMINO LB]],0) -> 0 | AA18: 0 | AB18: =IFERROR(TB_INTEGRADA[[#This Row],[REAL (%)]]-TB_INTEGRADA[[#This Row],[PREV (%)]],0) -> 0 | AF18: =IF(TB_INTEGRADA[[#This Row],[TOMADOR]]="EDIVIT",TB_INTEGRADA[[#This Row],[ORÇ DIG]]*1.38,IF(TB_INTEGRADA[[#This Row],[TOMADOR]]="UTGC",TB_INTEGRADA[[#This Row],[ORÇ DIG]]*1.47,IF(TB_INTEGRADA[[#This Row],[TOMADOR]]="TIMS",TB_INTEGRADA[[#This Row],[ORÇ DIG]]*1.34,IF(TB_INTEGRADA[[#This Row],[TOMADOR]]="UTGSUL",TB_INTEGRADA[[#This Row],[ORÇ DIG]]*1.37,IF(TB_INTEGRADA[[#This Row],[TOMADOR]]="REGAP",TB_INTEGRADA[[#This Row],[ORÇ DIG]]*1.36,IF(TB_INTEGRADA[[#This Row],[TOMADOR]]="UTEIBI",TB_INTEGRADA[[#This Row],[ORÇ DIG]]*1.5,"S/TOMADOR")))))) -> 0 | AH18: =SUMIFS(Tb_HhPLAN[Hh DISC],Tb_HhPLAN[SS],TB_INTEGRADA[[#This Row],[Nº SS]],Tb_HhPLAN[DISCIPLINA],"MEC") -> 0 | AI18: =SUMIFS(Hh_EXE_TOTAL[Hh],Hh_EXE_TOTAL[Nº SS],TB_INTEGRADA[[#This Row],[Nº SS]],Hh_EXE_TOTAL[DISCIPLINA],"MEC") -> 0 | AJ18: =IF(TB_INTEGRADA[[#This Row],[TOMADOR]]="EDIVIT",TB_INTEGRADA[[#This Row],[ORÇ DIG1]]*1.38,IF(TB_INTEGRADA[[#This Row],[TOMADOR]]="UTGC",TB_INTEGRADA[[#This Row],[ORÇ DIG1]]*1.47,IF(TB_INTEGRADA[[#This Row],[TOMADOR]]="TIMS",TB_INTEGRADA[[#This Row],[ORÇ DIG1]]*1.34,IF(TB_INTEGRADA[[#This Row],[TOMADOR]]="UTGSUL",TB_INTEGRADA[[#This Row],[ORÇ DIG1]]*1.37,IF(TB_INTEGRADA[[#This Row],[TOMADOR]]="REGAP",TB_INTEGRADA[[#This Row],[ORÇ DIG1]]*1.36,IF(TB_INTEGRADA[[#This Row],[TOMADOR]]="UTEIBI",TB_INTEGRADA[[#This Row],[ORÇ DIG1]]*1.5,"S/TOMADOR")))))) -> 0 | AL18: =SUMIFS(Tb_HhPLAN[Hh DISC],Tb_HhPLAN[SS],TB_INTEGRADA[[#This Row],[Nº SS]],Tb_HhPLAN[DISCIPLINA],"CIVIL") -> 9462.8451 | AM18: =SUMIFS(Hh_EXE_TOTAL[Hh],Hh_EXE_TOTAL[Nº SS],TB_INTEGRADA[[#This Row],[Nº SS]],Hh_EXE_TOTAL[DISCIPLINA],"CIVIL") -> 0 | AN18: =IF(TB_INTEGRADA[[#This Row],[TOMADOR]]="EDIVIT",TB_INTEGRADA[[#This Row],[ORÇ DIG2]]*1.38,IF(TB_INTEGRADA[[#This Row],[TOMADOR]]="UTGC",TB_INTEGRADA[[#This Row],[ORÇ DIG2]]*1.47,IF(TB_INTEGRADA[[#This Row],[TOMADOR]]="TIMS",TB_INTEGRADA[[#This Row],[ORÇ DIG2]]*1.34,IF(TB_INTEGRADA[[#This Row],[TOMADOR]]="UTGSUL",TB_INTEGRADA[[#This Row],[ORÇ DIG2]]*1.37,IF(TB_INTEGRADA[[#This Row],[TOMADOR]]="REGAP",TB_INTEGRADA[[#This Row],[ORÇ DIG2]]*1.36,IF(TB_INTEGRADA[[#This Row],[TOMADOR]]="UTEIBI",TB_INTEGRADA[[#This Row],[ORÇ DIG2]]*1.5,"S/TOMADOR")))))) -> 0 | AP18: =SUMIFS(Tb_HhPLAN[Hh DISC],Tb_HhPLAN[SS],TB_INTEGRADA[[#This Row],[Nº SS]],Tb_HhPLAN[DISCIPLINA],"ELÉT") -> 110.55488 | AQ18: =SUMIFS(Hh_EXE_TOTAL[Hh],Hh_EXE_TOTAL[Nº SS],TB_INTEGRADA[[#This Row],[Nº SS]],Hh_EXE_TOTAL[DISCIPLINA],"ELÉT") -> 0 | AR18: =IF(TB_INTEGRADA[[#This Row],[TOMADOR]]="EDIVIT",TB_INTEGRADA[[#This Row],[ORÇ DIG3]]*1.38,IF(TB_INTEGRADA[[#This Row],[TOMADOR]]="UTGC",TB_INTEGRADA[[#This Row],[ORÇ DIG3]]*1.47,IF(TB_INTEGRADA[[#This Row],[TOMADOR]]="TIMS",TB_INTEGRADA[[#This Row],[ORÇ DIG3]]*1.34,IF(TB_INTEGRADA[[#This Row],[TOMADOR]]="UTGSUL",TB_INTEGRADA[[#This Row],[ORÇ DIG3]]*1.37,IF(TB_INTEGRADA[[#This Row],[TOMADOR]]="REGAP",TB_INTEGRADA[[#This Row],[ORÇ DIG3]]*1.36,IF(TB_INTEGRADA[[#This Row],[TOMADOR]]="UTEIBI",TB_INTEGRADA[[#This Row],[ORÇ DIG3]]*1.5,"S/TOMADOR")))))) -> 0 | AT18: =SUMIFS(Tb_HhPLAN[Hh DISC],Tb_HhPLAN[SS],TB_INTEGRADA[[#This Row],[Nº SS]],Tb_HhPLAN[DISCIPLINA],"PINT") -> 0 | AU18: =SUMIFS(Hh_EXE_TOTAL[Hh],Hh_EXE_TOTAL[Nº SS],TB_INTEGRADA[[#This Row],[Nº SS]],Hh_EXE_TOTAL[DISCIPLINA],"PINT") -> 0 | AV18: =TB_INTEGRADA[[#This Row],[ORÇADO]]+TB_INTEGRADA[[#This Row],[ORÇADO1]]+TB_INTEGRADA[[#This Row],[ORÇADO2]]+TB_INTEGRADA[[#This Row],[ORÇADO3]] -> 0 | AW18: =TB_INTEGRADA[[#This Row],[PLANEJ]]+TB_INTEGRADA[[#This Row],[PLANEJ1]]+TB_INTEGRADA[[#This Row],[PLANEJ2]]+TB_INTEGRADA[[#This Row],[PLANEJ3]] -> 9573.4 | AX18: =TB_INTEGRADA[[#This Row],[REALIZ]]+TB_INTEGRADA[[#This Row],[REALIZ1]]+TB_INTEGRADA[[#This Row],[REALIZ2]]+TB_INTEGRADA[[#This Row],[REALIZ3]] -> 0 | AY18: =IFERROR(TB_INTEGRADA[[#This Row],[REALIZ4]]/TB_INTEGRADA[[#This Row],[ORÇADO4]],"") | AZ18: =_xlfn.XLOOKUP(TB_INTEGRADA[[#This Row],[Nº SS]],'CONTROLE EC'!B:B,'CONTROLE EC'!W:W,"",0,1) -> 0 | BA18: =_xlfn.XLOOKUP(TB_INTEGRADA[[#This Row],[Nº SS]],'CONTROLE EC'!B:B,'CONTROLE EC'!X:X,"",0,1) -> 0 | BB18: =_xlfn.XLOOKUP(TB_INTEGRADA[[#This Row],[Nº SS]],'CONTROLE EC'!B:B,'CONTROLE EC'!Y:Y,"",0,1) -> 0
A19: =IF(COUNTIFS($B$5:B19,TB_INTEGRADA[[#This Row],[Nº SS]])<>1,"",COUNTIFS($B$5:B19,TB_INTEGRADA[[#This Row],[Nº SS]])) -> 1 | B19: SS-15/2025 | C19: =_xlfn.XLOOKUP(TB_INTEGRADA[[#This Row],[Nº SS]],'CONTROLE EC'!B:B,'CONTROLE EC'!C:C,"",0,1) -> 23-0052-ES - MANUTENÇÃO DAS TORRES DE RESFRIAMENTO | D19: =_xlfn.XLOOKUP(TB_INTEGRADA[[#This Row],[Nº SS]],'CONTROLE CRONOG'!B:B,'CONTROLE CRONOG'!D:D,"",0,1) -> SERVIÇO | E19: =_xlfn.XLOOKUP(TB_INTEGRADA[[#This Row],[Nº SS]],'CONTROLE EC'!B:B,'CONTROLE EC'!E:E,"",0,1) -> EDIVIT | F19: =_xlfn.XLOOKUP(TB_INTEGRADA[[#This Row],[Nº SS]],'CONTROLE EC'!B:B,'CONTROLE EC'!F:F,"",0,1) -> EM ANDAMENTO | G19: =_xlfn.XLOOKUP(TB_INTEGRADA[[#This Row],[Nº SS]],'CONTROLE EC'!B:B,'CONTROLE EC'!R:R,"",0,1) -> REV.02 | H19: =IF(TB_INTEGRADA[[#This Row],[REVISÃO (EC)]]="","",_xlfn.XLOOKUP(TB_INTEGRADA[[#This Row],[Nº SS]],'CONTROLE EC'!B:B,'CONTROLE EC'!S:S,"",0,1)) -> 45951 | I19: =IF(TB_INTEGRADA[[#This Row],[REVISÃO (EC)]]="","",_xlfn.XLOOKUP(TB_INTEGRADA[[#This Row],[Nº SS]],'CONTROLE EC'!B:B,'CONTROLE EC'!U:U,"",0,1)) -> 45951 | J19: {=IF(TB_INTEGRADA[[#This Row],[DATA ENVIO. (EC)]]=IFERROR(INDEX('CONTROLE EC'!G19:Q19,MATCH(2,1/('CONTROLE EC'!G19:Q19<>""))),""),"",IFERROR(INDEX('CONTROLE EC'!G19:Q19,MATCH(2,1/('CONTROLE EC'!G19:Q19<>""))),""))} | K19: =IF(TB_INTEGRADA[[#This Row],[STATUS DEMANDA]]="NÃO EMITIDA SAMC","S/ EMISSÃO",_xlfn.XLOOKUP(TB_INTEGRADA[[#This Row],[Nº SS]],'CONTROLE EC'!B:B,'CONTROLE EC'!T:T,"",0,-1)) -> ENTREGUE | L19: =IF(TB_INTEGRADA[[#This Row],[STATUS DEMANDA]]="NÃO EMITIDA SAMC","S/ EMISSÃO",IF(TB_INTEGRADA[[#This Row],[STATUS DEMANDA]]="ON HOLD","ON HOLD",IF(TB_INTEGRADA[[#This Row],[STATUS DEMANDA]]="CANCELADA","CANCELADA",IF(TB_INTEGRADA[[#This Row],[DATA APROV. (EC)]]=0,"FISCALIZ.",IF(TB_INTEGRADA[[#This Row],[DATA APROV. (EC)]]="","PEND. FISCALIZ.",IF(TB_INTEGRADA[[#This Row],[DATA APROV. (EC)]]="N/A","APROVADO",IF(TB_INTEGRADA[[#This Row],[REVISÃO (EC)]]="","",_xlfn.XLOOKUP(TB_INTEGRADA[[#This Row],[Nº SS]],'CONTROLE EC'!B:B,'CONTROLE EC'!V:V,"",0,1)))))))) -> APROVADO | M19: {=IFERROR(_xlfn.IFS(TB_INTEGRADA[[#This Row],[STATUS DEMANDA]]="CANCELADA",0,TB_INTEGRADA[[#This Row],[DATA APROV. (EC)]]="",TODAY()-TB_INTEGRADA[[#This Row],[DATA ENVIO. (EC)]],TB_INTEGRADA[[#This Row],[DATA APROV. (EC)]]>=TB_INTEGRADA[[#This Row],[DATA ENVIO. (EC)]],0,TB_INTEGRADA[[#This Row],[DATA ENVIO. (EC)]]="",0,TB_INTEGRADA[[#This Row],[DATA ENVIO. (EC)]]>TB_INTEGRADA[[#This Row],[DATA APROV. (EC)]],TODAY()-TB_INTEGRADA[[#This Row],[DATA ENVIO. (EC)]]),"")} -> 0 | N19: =IF(TB_INTEGRADA[[#This Row],[STATUS DEMANDA]]="NÃO EMITIDA SAMC","S/ EMISSÃO",IF(TB_INTEGRADA[[#This Row],[STATUS DEMANDA]]="ON HOLD","ON HOLD",IF(F19="CANCELADA","CANCELADA",IF(L19="REPROVADO","EM PLANEJ.",IF(K19<>"ENTREGUE","EM PLANEJ.",IF(H19="","EM PLANEJ.",IF(I19="","FISCALIZ.",IF(M19<0,"EM PLANEJ.",IF(TB_INTEGRADA[[#This Row],[DATA APROV. (EC)]]>=TB_INTEGRADA[[#This Row],[DATA ENVIO. (EC)]],"RETORNO OK","FISCALIZ."))))))))) -> RETORNO OK | O19: =_xlfn.XLOOKUP(TB_INTEGRADA[[#This Row],[Nº SS]],'CONTROLE CRONOG'!B:B,'CONTROLE CRONOG'!R:R,"",0,1) -> REV.02 | P19: =IF(TB_INTEGRADA[[#This Row],[REVISÃO (CR)]]="","",_xlfn.XLOOKUP(TB_INTEGRADA[[#This Row],[Nº SS]],'CONTROLE CRONOG'!B:B,'CONTROLE CRONOG'!S:S,"",0,1)) -> 45950 | Q19: =IF(TB_INTEGRADA[[#This Row],[REVISÃO (CR)]]="","",_xlfn.XLOOKUP(TB_INTEGRADA[[#This Row],[Nº SS]],'CONTROLE CRONOG'!B:B,'CONTROLE CRONOG'!U:U,"",0,1)) -> 45951 | R19: {=IF(TB_INTEGRADA[[#This Row],[DATA ENVIO. (CR)]]=IFERROR(INDEX('CONTROLE CRONOG'!G19:Q19,MATCH(2,1/('CONTROLE CRONOG'!G19:Q19<>""))),""),"",IFERROR(INDEX('CONTROLE CRONOG'!G19:Q19,MATCH(2,1/('CONTROLE CRONOG'!G19:Q19<>""))),""))} | S19: =_xlfn.XLOOKUP(TB_INTEGRADA[[#This Row],[Nº SS]],'CONTROLE CRONOG'!B:B,'CONTROLE CRONOG'!T:T,"",0,-1) -> ENTREGUE | T19: =IF(TB_INTEGRADA[[#This Row],[STATUS DEMANDA]]="ON HOLD","ON HOLD",IF(TB_INTEGRADA[[#This Row],[STATUS DEMANDA]]="CANCELADA","CANCELADA",IF(TB_INTEGRADA[[#This Row],[DATA APROV. (CR)]]=0,"FISCALIZ.",IF(TB_INTEGRADA[[#This Row],[DATA APROV. (CR)]]="N/A","APROVADO",IF(TB_INTEGRADA[[#This Row],[REVISÃO (CR)]]="","",_xlfn.XLOOKUP(TB_INTEGRADA[[#This Row],[Nº SS]],'CONTROLE CRONOG'!B:B,'CONTROLE CRONOG'!V:V,"",0,1)))))) -> APROVADO | V19: 46251 | W19: 46238 | X19: =IFERROR(TB_INTEGRADA[[#This Row],[TÉRM. TD]]-TB_INTEGRADA[[#This Row],[TÉRMINO LB]],0) -> -13 | Y19: 0.456 | Z19: 0.5504 | AA19: 0.0995 | AB19: =IFERROR(TB_INTEGRADA[[#This Row],[REAL (%)]]-TB_INTEGRADA[[#This Row],[PREV (%)]],0) -> 0.0944 | AC19: 0 | AD19: 7 | AF19: =IF(TB_INTEGRADA[[#This Row],[TOMADOR]]="EDIVIT",TB_INTEGRADA[[#This Row],[ORÇ DIG]]*1.38,IF(TB_INTEGRADA[[#This Row],[TOMADOR]]="UTGC",TB_INTEGRADA[[#This Row],[ORÇ DIG]]*1.47,IF(TB_INTEGRADA[[#This Row],[TOMADOR]]="TIMS",TB_INTEGRADA[[#This Row],[ORÇ DIG]]*1.34,IF(TB_INTEGRADA[[#This Row],[TOMADOR]]="UTGSUL",TB_INTEGRADA[[#This Row],[ORÇ DIG]]*1.37,IF(TB_INTEGRADA[[#This Row],[TOMADOR]]="REGAP",TB_INTEGRADA[[#This Row],[ORÇ DIG]]*1.36,IF(TB_INTEGRADA[[#This Row],[TOMADOR]]="UTEIBI",TB_INTEGRADA[[#This Row],[ORÇ DIG]]*1.5,"S/TOMADOR")))))) -> 2163.012 | AG19: 1567.4 | AH19: =SUMIFS(Tb_HhPLAN[Hh DISC],Tb_HhPLAN[SS],TB_INTEGRADA[[#This Row],[Nº SS]],Tb_HhPLAN[DISCIPLINA],"MEC") -> 985.20635 | AI19: =SUMIFS(Hh_EXE_TOTAL[Hh],Hh_EXE_TOTAL[Nº SS],TB_INTEGRADA[[#This Row],[Nº SS]],Hh_EXE_TOTAL[DISCIPLINA],"MEC") -> 2030.3448 | AJ19: =IF(TB_INTEGRADA[[#This Row],[TOMADOR]]="EDIVIT",TB_INTEGRADA[[#This Row],[ORÇ DIG1]]*1.38,IF(TB_INTEGRADA[[#This Row],[TOMADOR]]="UTGC",TB_INTEGRADA[[#This Row],[ORÇ DIG1]]*1.47,IF(TB_INTEGRADA[[#This Row],[TOMADOR]]="TIMS",TB_INTEGRADA[[#This Row],[ORÇ DIG1]]*1.34,IF(TB_INTEGRADA[[#This Row],[TOMADOR]]="UTGSUL",TB_INTEGRADA[[#This Row],[ORÇ DIG1]]*1.37,IF(TB_INTEGRADA[[#This Row],[TOMADOR]]="REGAP",TB_INTEGRADA[[#This Row],[ORÇ DIG1]]*1.36,IF(TB_INTEGRADA[[#This Row],[TOMADOR]]="UTEIBI",TB_INTEGRADA[[#This Row],[ORÇ DIG1]]*1.5,"S/TOMADOR")))))) -> 0 | AK19: 0 | AL19: =SUMIFS(Tb_HhPLAN[Hh DISC],Tb_HhPLAN[SS],TB_INTEGRADA[[#This Row],[Nº SS]],Tb_HhPLAN[DISCIPLINA],"CIVIL") -> 0 | AM19: =SUMIFS(Hh_EXE_TOTAL[Hh],Hh_EXE_TOTAL[Nº SS],TB_INTEGRADA[[#This Row],[Nº SS]],Hh_EXE_TOTAL[DISCIPLINA],"CIVIL") -> 0 | AN19: =IF(TB_INTEGRADA[[#This Row],[TOMADOR]]="EDIVIT",TB_INTEGRADA[[#This Row],[ORÇ DIG2]]*1.38,IF(TB_INTEGRADA[[#This Row],[TOMADOR]]="UTGC",TB_INTEGRADA[[#This Row],[ORÇ DIG2]]*1.47,IF(TB_INTEGRADA[[#This Row],[TOMADOR]]="TIMS",TB_INTEGRADA[[#This Row],[ORÇ DIG2]]*1.34,IF(TB_INTEGRADA[[#This Row],[TOMADOR]]="UTGSUL",TB_INTEGRADA[[#This Row],[ORÇ DIG2]]*1.37,IF(TB_INTEGRADA[[#This Row],[TOMADOR]]="REGAP",TB_INTEGRADA[[#This Row],[ORÇ DIG2]]*1.36,IF(TB_INTEGRADA[[#This Row],[TOMADOR]]="UTEIBI",TB_INTEGRADA[[#This Row],[ORÇ DIG2]]*1.5,"S/TOMADOR")))))) -> 2163.84 | AO19: 1568 | AP19: =SUMIFS(Tb_HhPLAN[Hh DISC],Tb_HhPLAN[SS],TB_INTEGRADA[[#This Row],[Nº SS]],Tb_HhPLAN[DISCIPLINA],"ELÉT") -> 66.793651 | AQ19: =SUMIFS(Hh_EXE_TOTAL[Hh],Hh_EXE_TOTAL[Nº SS],TB_INTEGRADA[[#This Row],[Nº SS]],Hh_EXE_TOTAL[DISCIPLINA],"ELÉT") -> 17.655172 | AR19: =IF(TB_INTEGRADA[[#This Row],[TOMADOR]]="EDIVIT",TB_INTEGRADA[[#This Row],[ORÇ DIG3]]*1.38,IF(TB_INTEGRADA[[#This Row],[TOMADOR]]="UTGC",TB_INTEGRADA[[#This Row],[ORÇ DIG3]]*1.47,IF(TB_INTEGRADA[[#This Row],[TOMADOR]]="TIMS",TB_INTEGRADA[[#This Row],[ORÇ DIG3]]*1.34,IF(TB_INTEGRADA[[#This Row],[TOMADOR]]="UTGSUL",TB_INTEGRADA[[#This Row],[ORÇ DIG3]]*1.37,IF(TB_INTEGRADA[[#This Row],[TOMADOR]]="REGAP",TB_INTEGRADA[[#This Row],[ORÇ DIG3]]*1.36,IF(TB_INTEGRADA[[#This Row],[TOMADOR]]="UTEIBI",TB_INTEGRADA[[#This Row],[ORÇ DIG3]]*1.5,"S/TOMADOR")))))) -> 841.7448 | AS19: 609.96 | AT19: =SUMIFS(Tb_HhPLAN[Hh DISC],Tb_HhPLAN[SS],TB_INTEGRADA[[#This Row],[Nº SS]],Tb_HhPLAN[DISCIPLINA],"PINT") -> 0 | AU19: =SUMIFS(Hh_EXE_TOTAL[Hh],Hh_EXE_TOTAL[Nº SS],TB_INTEGRADA[[#This Row],[Nº SS]],Hh_EXE_TOTAL[DISCIPLINA],"PINT") -> 0 | AV19: =TB_INTEGRADA[[#This Row],[ORÇADO]]+TB_INTEGRADA[[#This Row],[ORÇADO1]]+TB_INTEGRADA[[#This Row],[ORÇADO2]]+TB_INTEGRADA[[#This Row],[ORÇADO3]] -> 5168.5968 | AW19: =TB_INTEGRADA[[#This Row],[PLANEJ]]+TB_INTEGRADA[[#This Row],[PLANEJ1]]+TB_INTEGRADA[[#This Row],[PLANEJ2]]+TB_INTEGRADA[[#This Row],[PLANEJ3]] -> 1052 | AX19: =TB_INTEGRADA[[#This Row],[REALIZ]]+TB_INTEGRADA[[#This Row],[REALIZ1]]+TB_INTEGRADA[[#This Row],[REALIZ2]]+TB_INTEGRADA[[#This Row],[REALIZ3]] -> 2048 | AY19: =IFERROR(TB_INTEGRADA[[#This Row],[REALIZ4]]/TB_INTEGRADA[[#This Row],[ORÇADO4]],"") -> 0.39623907 | AZ19: =_xlfn.XLOOKUP(TB_INTEGRADA[[#This Row],[Nº SS]],'CONTROLE EC'!B:B,'CONTROLE EC'!W:W,"",0,1) -> 1662818.3 | BA19: =_xlfn.XLOOKUP(TB_INTEGRADA[[#This Row],[Nº SS]],'CONTROLE EC'!B:B,'CONTROLE EC'!X:X,"",0,1) -> 1197230 | BB19: =_xlfn.XLOOKUP(TB_INTEGRADA[[#This Row],[Nº SS]],'CONTROLE EC'!B:B,'CONTROLE EC'!Y:Y,"",0,1) -> 465588.29
A20: =IF(COUNTIFS($B$5:B20,TB_INTEGRADA[[#This Row],[Nº SS]])<>1,"",COUNTIFS($B$5:B20,TB_INTEGRADA[[#This Row],[Nº SS]])) -> 1 | B20: SS-16/2025 | C20: =_xlfn.XLOOKUP(TB_INTEGRADA[[#This Row],[Nº SS]],'CONTROLE EC'!B:B,'CONTROLE EC'!C:C,"",0,1) -> 23-0052-ES - SUBSTITUIÇÃO DOS ISOLAMENTOS ACÚSTICOS NA CENTRAL DE UTILIDADES | D20: =_xlfn.XLOOKUP(TB_INTEGRADA[[#This Row],[Nº SS]],'CONTROLE CRONOG'!B:B,'CONTROLE CRONOG'!D:D,"",0,1) -> SERVIÇO | E20: =_xlfn.XLOOKUP(TB_INTEGRADA[[#This Row],[Nº SS]],'CONTROLE EC'!B:B,'CONTROLE EC'!E:E,"",0,1) -> EDIVIT | F20: =_xlfn.XLOOKUP(TB_INTEGRADA[[#This Row],[Nº SS]],'CONTROLE EC'!B:B,'CONTROLE EC'!F:F,"",0,1) -> CONCLUÍDA | G20: =_xlfn.XLOOKUP(TB_INTEGRADA[[#This Row],[Nº SS]],'CONTROLE EC'!B:B,'CONTROLE EC'!R:R,"",0,1) -> REV.01 | H20: =IF(TB_INTEGRADA[[#This Row],[REVISÃO (EC)]]="","",_xlfn.XLOOKUP(TB_INTEGRADA[[#This Row],[Nº SS]],'CONTROLE EC'!B:B,'CONTROLE EC'!S:S,"",0,1)) -> 45946 | I20: =IF(TB_INTEGRADA[[#This Row],[REVISÃO (EC)]]="","",_xlfn.XLOOKUP(TB_INTEGRADA[[#This Row],[Nº SS]],'CONTROLE EC'!B:B,'CONTROLE EC'!U:U,"",0,1)) -> 45947 | J20: {=IF(TB_INTEGRADA[[#This Row],[DATA ENVIO. (EC)]]=IFERROR(INDEX('CONTROLE EC'!G20:Q20,MATCH(2,1/('CONTROLE EC'!G20:Q20<>""))),""),"",IFERROR(INDEX('CONTROLE EC'!G20:Q20,MATCH(2,1/('CONTROLE EC'!G20:Q20<>""))),""))} | K20: =IF(TB_INTEGRADA[[#This Row],[STATUS DEMANDA]]="NÃO EMITIDA SAMC","S/ EMISSÃO",_xlfn.XLOOKUP(TB_INTEGRADA[[#This Row],[Nº SS]],'CONTROLE EC'!B:B,'CONTROLE EC'!T:T,"",0,-1)) -> ENTREGUE | L20: =IF(TB_INTEGRADA[[#This Row],[STATUS DEMANDA]]="NÃO EMITIDA SAMC","S/ EMISSÃO",IF(TB_INTEGRADA[[#This Row],[STATUS DEMANDA]]="ON HOLD","ON HOLD",IF(TB_INTEGRADA[[#This Row],[STATUS DEMANDA]]="CANCELADA","CANCELADA",IF(TB_INTEGRADA[[#This Row],[DATA APROV. (EC)]]=0,"FISCALIZ.",IF(TB_INTEGRADA[[#This Row],[DATA APROV. (EC)]]="","PEND. FISCALIZ.",IF(TB_INTEGRADA[[#This Row],[DATA APROV. (EC)]]="N/A","APROVADO",IF(TB_INTEGRADA[[#This Row],[REVISÃO (EC)]]="","",_xlfn.XLOOKUP(TB_INTEGRADA[[#This Row],[Nº SS]],'CONTROLE EC'!B:B,'CONTROLE EC'!V:V,"",0,1)))))))) -> APROVADO | M20: {=IFERROR(_xlfn.IFS(TB_INTEGRADA[[#This Row],[STATUS DEMANDA]]="CANCELADA",0,TB_INTEGRADA[[#This Row],[DATA APROV. (EC)]]="",TODAY()-TB_INTEGRADA[[#This Row],[DATA ENVIO. (EC)]],TB_INTEGRADA[[#This Row],[DATA APROV. (EC)]]>=TB_INTEGRADA[[#This Row],[DATA ENVIO. (EC)]],0,TB_INTEGRADA[[#This Row],[DATA ENVIO. (EC)]]="",0,TB_INTEGRADA[[#This Row],[DATA ENVIO. (EC)]]>TB_INTEGRADA[[#This Row],[DATA APROV. (EC)]],TODAY()-TB_INTEGRADA[[#This Row],[DATA ENVIO. (EC)]]),"")} -> 0 | N20: =IF(TB_INTEGRADA[[#This Row],[STATUS DEMANDA]]="NÃO EMITIDA SAMC","S/ EMISSÃO",IF(TB_INTEGRADA[[#This Row],[STATUS DEMANDA]]="ON HOLD","ON HOLD",IF(F20="CANCELADA","CANCELADA",IF(L20="REPROVADO","EM PLANEJ.",IF(K20<>"ENTREGUE","EM PLANEJ.",IF(H20="","EM PLANEJ.",IF(I20="","FISCALIZ.",IF(M20<0,"EM PLANEJ.",IF(TB_INTEGRADA[[#This Row],[DATA APROV. (EC)]]>=TB_INTEGRADA[[#This Row],[DATA ENVIO. (EC)]],"RETORNO OK","FISCALIZ."))))))))) -> RETORNO OK | O20: =_xlfn.XLOOKUP(TB_INTEGRADA[[#This Row],[Nº SS]],'CONTROLE CRONOG'!B:B,'CONTROLE CRONOG'!R:R,"",0,1) -> REV.00 | P20: =IF(TB_INTEGRADA[[#This Row],[REVISÃO (CR)]]="","",_xlfn.XLOOKUP(TB_INTEGRADA[[#This Row],[Nº SS]],'CONTROLE CRONOG'!B:B,'CONTROLE CRONOG'!S:S,"",0,1)) -> 45938 | Q20: =IF(TB_INTEGRADA[[#This Row],[REVISÃO (CR)]]="","",_xlfn.XLOOKUP(TB_INTEGRADA[[#This Row],[Nº SS]],'CONTROLE CRONOG'!B:B,'CONTROLE CRONOG'!U:U,"",0,1)) -> 45943 | R20: {=IF(TB_INTEGRADA[[#This Row],[DATA ENVIO. (CR)]]=IFERROR(INDEX('CONTROLE CRONOG'!G20:Q20,MATCH(2,1/('CONTROLE CRONOG'!G20:Q20<>""))),""),"",IFERROR(INDEX('CONTROLE CRONOG'!G20:Q20,MATCH(2,1/('CONTROLE CRONOG'!G20:Q20<>""))),""))} | S20: =_xlfn.XLOOKUP(TB_INTEGRADA[[#This Row],[Nº SS]],'CONTROLE CRONOG'!B:B,'CONTROLE CRONOG'!T:T,"",0,-1) -> ENTREGUE | T20: =IF(TB_INTEGRADA[[#This Row],[STATUS DEMANDA]]="ON HOLD","ON HOLD",IF(TB_INTEGRADA[[#This Row],[STATUS DEMANDA]]="CANCELADA","CANCELADA",IF(TB_INTEGRADA[[#This Row],[DATA APROV. (CR)]]=0,"FISCALIZ.",IF(TB_INTEGRADA[[#This Row],[DATA APROV. (CR)]]="N/A","APROVADO",IF(TB_INTEGRADA[[#This Row],[REVISÃO (CR)]]="","",_xlfn.XLOOKUP(TB_INTEGRADA[[#This Row],[Nº SS]],'CONTROLE CRONOG'!B:B,'CONTROLE CRONOG'!V:V,"",0,1)))))) -> APROVADO | V20: 46010 | W20: 46046 | X20: =IFERROR(TB_INTEGRADA[[#This Row],[TÉRM. TD]]-TB_INTEGRADA[[#This Row],[TÉRMINO LB]],0) -> 36 | Y20: 1 | Z20: 1 | AA20: 0 | AB20: =IFERROR(TB_INTEGRADA[[#This Row],[REAL (%)]]-TB_INTEGRADA[[#This Row],[PREV (%)]],0) -> 0 | AC20: 0 | AD20: 0 | AF20: =IF(TB_INTEGRADA[[#This Row],[TOMADOR]]="EDIVIT",TB_INTEGRADA[[#This Row],[ORÇ DIG]]*1.38,IF(TB_INTEGRADA[[#This Row],[TOMADOR]]="UTGC",TB_INTEGRADA[[#This Row],[ORÇ DIG]]*1.47,IF(TB_INTEGRADA[[#This Row],[TOMADOR]]="TIMS",TB_INTEGRADA[[#This Row],[ORÇ DIG]]*1.34,IF(TB_INTEGRADA[[#This Row],[TOMADOR]]="UTGSUL",TB_INTEGRADA[[#This Row],[ORÇ DIG]]*1.37,IF(TB_INTEGRADA[[#This Row],[TOMADOR]]="REGAP",TB_INTEGRADA[[#This Row],[ORÇ DIG]]*1.36,IF(TB_INTEGRADA[[#This Row],[TOMADOR]]="UTEIBI",TB_INTEGRADA[[#This Row],[ORÇ DIG]]*1.5,"S/TOMADOR")))))) -> 1813.113 | AG20: 1313.85 | AH20: =SUMIFS(Tb_HhPLAN[Hh DISC],Tb_HhPLAN[SS],TB_INTEGRADA[[#This Row],[Nº SS]],Tb_HhPLAN[DISCIPLINA],"MEC") -> 476 | AI20: =SUMIFS(Hh_EXE_TOTAL[Hh],Hh_EXE_TOTAL[Nº SS],TB_INTEGRADA[[#This Row],[Nº SS]],Hh_EXE_TOTAL[DISCIPLINA],"MEC") -> 1208 | AJ20: =IF(TB_INTEGRADA[[#This Row],[TOMADOR]]="EDIVIT",TB_INTEGRADA[[#This Row],[ORÇ DIG1]]*1.38,IF(TB_INTEGRADA[[#This Row],[TOMADOR]]="UTGC",TB_INTEGRADA[[#This Row],[ORÇ DIG1]]*1.47,IF(TB_INTEGRADA[[#This Row],[TOMADOR]]="TIMS",TB_INTEGRADA[[#This Row],[ORÇ DIG1]]*1.34,IF(TB_INTEGRADA[[#This Row],[TOMADOR]]="UTGSUL",TB_INTEGRADA[[#This Row],[ORÇ DIG1]]*1.37,IF(TB_INTEGRADA[[#This Row],[TOMADOR]]="REGAP",TB_INTEGRADA[[#This Row],[ORÇ DIG1]]*1.36,IF(TB_INTEGRADA[[#This Row],[TOMADOR]]="UTEIBI",TB_INTEGRADA[[#This Row],[ORÇ DIG1]]*1.5,"S/TOMADOR")))))) -> 0 | AL20: =SUMIFS(Tb_HhPLAN[Hh DISC],Tb_HhPLAN[SS],TB_INTEGRADA[[#This Row],[Nº SS]],Tb_HhPLAN[DISCIPLINA],"CIVIL") -> 0 | AM20: =SUMIFS(Hh_EXE_TOTAL[Hh],Hh_EXE_TOTAL[Nº SS],TB_INTEGRADA[[#This Row],[Nº SS]],Hh_EXE_TOTAL[DISCIPLINA],"CIVIL") -> 0 | AN20: =IF(TB_INTEGRADA[[#This Row],[TOMADOR]]="EDIVIT",TB_INTEGRADA[[#This Row],[ORÇ DIG2]]*1.38,IF(TB_INTEGRADA[[#This Row],[TOMADOR]]="UTGC",TB_INTEGRADA[[#This Row],[ORÇ DIG2]]*1.47,IF(TB_INTEGRADA[[#This Row],[TOMADOR]]="TIMS",TB_INTEGRADA[[#This Row],[ORÇ DIG2]]*1.34,IF(TB_INTEGRADA[[#This Row],[TOMADOR]]="UTGSUL",TB_INTEGRADA[[#This Row],[ORÇ DIG2]]*1.37,IF(TB_INTEGRADA[[#This Row],[TOMADOR]]="REGAP",TB_INTEGRADA[[#This Row],[ORÇ DIG2]]*1.36,IF(TB_INTEGRADA[[#This Row],[TOMADOR]]="UTEIBI",TB_INTEGRADA[[#This Row],[ORÇ DIG2]]*1.5,"S/TOMADOR")))))) -> 0 | AP20: =SUMIFS(Tb_HhPLAN[Hh DISC],Tb_HhPLAN[SS],TB_INTEGRADA[[#This Row],[Nº SS]],Tb_HhPLAN[DISCIPLINA],"ELÉT") -> 0 | AQ20: =SUMIFS(Hh_EXE_TOTAL[Hh],Hh_EXE_TOTAL[Nº SS],TB_INTEGRADA[[#This Row],[Nº SS]],Hh_EXE_TOTAL[DISCIPLINA],"ELÉT") -> 0 | AR20: =IF(TB_INTEGRADA[[#This Row],[TOMADOR]]="EDIVIT",TB_INTEGRADA[[#This Row],[ORÇ DIG3]]*1.38,IF(TB_INTEGRADA[[#This Row],[TOMADOR]]="UTGC",TB_INTEGRADA[[#This Row],[ORÇ DIG3]]*1.47,IF(TB_INTEGRADA[[#This Row],[TOMADOR]]="TIMS",TB_INTEGRADA[[#This Row],[ORÇ DIG3]]*1.34,IF(TB_INTEGRADA[[#This Row],[TOMADOR]]="UTGSUL",TB_INTEGRADA[[#This Row],[ORÇ DIG3]]*1.37,IF(TB_INTEGRADA[[#This Row],[TOMADOR]]="REGAP",TB_INTEGRADA[[#This Row],[ORÇ DIG3]]*1.36,IF(TB_INTEGRADA[[#This Row],[TOMADOR]]="UTEIBI",TB_INTEGRADA[[#This Row],[ORÇ DIG3]]*1.5,"S/TOMADOR")))))) -> 0 | AT20: =SUMIFS(Tb_HhPLAN[Hh DISC],Tb_HhPLAN[SS],TB_INTEGRADA[[#This Row],[Nº SS]],Tb_HhPLAN[DISCIPLINA],"PINT") -> 0 | AU20: =SUMIFS(Hh_EXE_TOTAL[Hh],Hh_EXE_TOTAL[Nº SS],TB_INTEGRADA[[#This Row],[Nº SS]],Hh_EXE_TOTAL[DISCIPLINA],"PINT") -> 0 | AV20: =TB_INTEGRADA[[#This Row],[ORÇADO]]+TB_INTEGRADA[[#This Row],[ORÇADO1]]+TB_INTEGRADA[[#This Row],[ORÇADO2]]+TB_INTEGRADA[[#This Row],[ORÇADO3]] -> 1813.113 | AW20: =TB_INTEGRADA[[#This Row],[PLANEJ]]+TB_INTEGRADA[[#This Row],[PLANEJ1]]+TB_INTEGRADA[[#This Row],[PLANEJ2]]+TB_INTEGRADA[[#This Row],[PLANEJ3]] -> 476 | AX20: =TB_INTEGRADA[[#This Row],[REALIZ]]+TB_INTEGRADA[[#This Row],[REALIZ1]]+TB_INTEGRADA[[#This Row],[REALIZ2]]+TB_INTEGRADA[[#This Row],[REALIZ3]] -> 1208 | AY20: =IFERROR(TB_INTEGRADA[[#This Row],[REALIZ4]]/TB_INTEGRADA[[#This Row],[ORÇADO4]],"") -> 0.66625743 | AZ20: =_xlfn.XLOOKUP(TB_INTEGRADA[[#This Row],[Nº SS]],'CONTROLE EC'!B:B,'CONTROLE EC'!W:W,"",0,1) -> 228497.33 | BA20: =_xlfn.XLOOKUP(TB_INTEGRADA[[#This Row],[Nº SS]],'CONTROLE EC'!B:B,'CONTROLE EC'!X:X,"",0,1) -> 228497.33 | BB20: =_xlfn.XLOOKUP(TB_INTEGRADA[[#This Row],[Nº SS]],'CONTROLE EC'!B:B,'CONTROLE EC'!Y:Y,"",0,1) -> 0
A21: =IF(COUNTIFS($B$5:B21,TB_INTEGRADA[[#This Row],[Nº SS]])<>1,"",COUNTIFS($B$5:B21,TB_INTEGRADA[[#This Row],[Nº SS]])) -> 1 | B21: SS-17/2025 | C21: =_xlfn.XLOOKUP(TB_INTEGRADA[[#This Row],[Nº SS]],'CONTROLE EC'!B:B,'CONTROLE EC'!C:C,"",0,1) -> 23-0291-ES - ADEQUAÇÃO DA LUMINOSIDADE EXTERNA DO EDIVIT | D21: =_xlfn.XLOOKUP(TB_INTEGRADA[[#This Row],[Nº SS]],'CONTROLE CRONOG'!B:B,'CONTROLE CRONOG'!D:D,"",0,1) -> SERVIÇO | E21: =_xlfn.XLOOKUP(TB_INTEGRADA[[#This Row],[Nº SS]],'CONTROLE EC'!B:B,'CONTROLE EC'!E:E,"",0,1) -> EDIVIT | F21: =_xlfn.XLOOKUP(TB_INTEGRADA[[#This Row],[Nº SS]],'CONTROLE EC'!B:B,'CONTROLE EC'!F:F,"",0,1) -> EM ANDAMENTO | G21: =_xlfn.XLOOKUP(TB_INTEGRADA[[#This Row],[Nº SS]],'CONTROLE EC'!B:B,'CONTROLE EC'!R:R,"",0,1) -> REV.01 | H21: =IF(TB_INTEGRADA[[#This Row],[REVISÃO (EC)]]="","",_xlfn.XLOOKUP(TB_INTEGRADA[[#This Row],[Nº SS]],'CONTROLE EC'!B:B,'CONTROLE EC'!S:S,"",0,1)) -> 45973 | I21: =IF(TB_INTEGRADA[[#This Row],[REVISÃO (EC)]]="","",_xlfn.XLOOKUP(TB_INTEGRADA[[#This Row],[Nº SS]],'CONTROLE EC'!B:B,'CONTROLE EC'!U:U,"",0,1)) -> 45973 | J21: {=IF(TB_INTEGRADA[[#This Row],[DATA ENVIO. (EC)]]=IFERROR(INDEX('CONTROLE EC'!G21:Q21,MATCH(2,1/('CONTROLE EC'!G21:Q21<>""))),""),"",IFERROR(INDEX('CONTROLE EC'!G21:Q21,MATCH(2,1/('CONTROLE EC'!G21:Q21<>""))),""))} | K21: =IF(TB_INTEGRADA[[#This Row],[STATUS DEMANDA]]="NÃO EMITIDA SAMC","S/ EMISSÃO",_xlfn.XLOOKUP(TB_INTEGRADA[[#This Row],[Nº SS]],'CONTROLE EC'!B:B,'CONTROLE EC'!T:T,"",0,-1)) -> ENTREGUE | L21: =IF(TB_INTEGRADA[[#This Row],[STATUS DEMANDA]]="NÃO EMITIDA SAMC","S/ EMISSÃO",IF(TB_INTEGRADA[[#This Row],[STATUS DEMANDA]]="ON HOLD","ON HOLD",IF(TB_INTEGRADA[[#This Row],[STATUS DEMANDA]]="CANCELADA","CANCELADA",IF(TB_INTEGRADA[[#This Row],[DATA APROV. (EC)]]=0,"FISCALIZ.",IF(TB_INTEGRADA[[#This Row],[DATA APROV. (EC)]]="","PEND. FISCALIZ.",IF(TB_INTEGRADA[[#This Row],[DATA APROV. (EC)]]="N/A","APROVADO",IF(TB_INTEGRADA[[#This Row],[REVISÃO (EC)]]="","",_xlfn.XLOOKUP(TB_INTEGRADA[[#This Row],[Nº SS]],'CONTROLE EC'!B:B,'CONTROLE EC'!V:V,"",0,1)))))))) -> APROVADO | M21: {=IFERROR(_xlfn.IFS(TB_INTEGRADA[[#This Row],[STATUS DEMANDA]]="CANCELADA",0,TB_INTEGRADA[[#This Row],[DATA APROV. (EC)]]="",TODAY()-TB_INTEGRADA[[#This Row],[DATA ENVIO. (EC)]],TB_INTEGRADA[[#This Row],[DATA APROV. (EC)]]>=TB_INTEGRADA[[#This Row],[DATA ENVIO. (EC)]],0,TB_INTEGRADA[[#This Row],[DATA ENVIO. (EC)]]="",0,TB_INTEGRADA[[#This Row],[DATA ENVIO. (EC)]]>TB_INTEGRADA[[#This Row],[DATA APROV. (EC)]],TODAY()-TB_INTEGRADA[[#This Row],[DATA ENVIO. (EC)]]),"")} -> 0 | N21: =IF(TB_INTEGRADA[[#This Row],[STATUS DEMANDA]]="NÃO EMITIDA SAMC","S/ EMISSÃO",IF(TB_INTEGRADA[[#This Row],[STATUS DEMANDA]]="ON HOLD","ON HOLD",IF(F21="CANCELADA","CANCELADA",IF(L21="REPROVADO","EM PLANEJ.",IF(K21<>"ENTREGUE","EM PLANEJ.",IF(H21="","EM PLANEJ.",IF(I21="","FISCALIZ.",IF(M21<0,"EM PLANEJ.",IF(TB_INTEGRADA[[#This Row],[DATA APROV. (EC)]]>=TB_INTEGRADA[[#This Row],[DATA ENVIO. (EC)]],"RETORNO OK","FISCALIZ."))))))))) -> RETORNO OK | O21: =_xlfn.XLOOKUP(TB_INTEGRADA[[#This Row],[Nº SS]],'CONTROLE CRONOG'!B:B,'CONTROLE CRONOG'!R:R,"",0,1) -> REV.01 | P21: =IF(TB_INTEGRADA[[#This Row],[REVISÃO (CR)]]="","",_xlfn.XLOOKUP(TB_INTEGRADA[[#This Row],[Nº SS]],'CONTROLE CRONOG'!B:B,'CONTROLE CRONOG'!S:S,"",0,1)) -> 45973 | Q21: =IF(TB_INTEGRADA[[#This Row],[REVISÃO (CR)]]="","",_xlfn.XLOOKUP(TB_INTEGRADA[[#This Row],[Nº SS]],'CONTROLE CRONOG'!B:B,'CONTROLE CRONOG'!U:U,"",0,1)) -> 45973 | R21: {=IF(TB_INTEGRADA[[#This Row],[DATA ENVIO. (CR)]]=IFERROR(INDEX('CONTROLE CRONOG'!G21:Q21,MATCH(2,1/('CONTROLE CRONOG'!G21:Q21<>""))),""),"",IFERROR(INDEX('CONTROLE CRONOG'!G21:Q21,MATCH(2,1/('CONTROLE CRONOG'!G21:Q21<>""))),""))} | S21: =_xlfn.XLOOKUP(TB_INTEGRADA[[#This Row],[Nº SS]],'CONTROLE CRONOG'!B:B,'CONTROLE CRONOG'!T:T,"",0,-1) -> ENTREGUE | T21: =IF(TB_INTEGRADA[[#This Row],[STATUS DEMANDA]]="ON HOLD","ON HOLD",IF(TB_INTEGRADA[[#This Row],[STATUS DEMANDA]]="CANCELADA","CANCELADA",IF(TB_INTEGRADA[[#This Row],[DATA APROV. (CR)]]=0,"FISCALIZ.",IF(TB_INTEGRADA[[#This Row],[DATA APROV. (CR)]]="N/A","APROVADO",IF(TB_INTEGRADA[[#This Row],[REVISÃO (CR)]]="","",_xlfn.XLOOKUP(TB_INTEGRADA[[#This Row],[Nº SS]],'CONTROLE CRONOG'!B:B,'CONTROLE CRONOG'!V:V,"",0,1)))))) -> APROVADO | V21: 46170 | W21: 46192 | X21: =IFERROR(TB_INTEGRADA[[#This Row],[TÉRM. TD]]-TB_INTEGRADA[[#This Row],[TÉRMINO LB]],0) -> 22 | Y21: 0.6296 | Z21: 0.4495 | AA21: -0.1148 | AB21: =IFERROR(TB_INTEGRADA[[#This Row],[REAL (%)]]-TB_INTEGRADA[[#This Row],[PREV (%)]],0) -> -0.1801 | AC21: 4 | AD21: 4 | AF21: =IF(TB_INTEGRADA[[#This Row],[TOMADOR]]="EDIVIT",TB_INTEGRADA[[#This Row],[ORÇ DIG]]*1.38,IF(TB_INTEGRADA[[#This Row],[TOMADOR]]="UTGC",TB_INTEGRADA[[#This Row],[ORÇ DIG]]*1.47,IF(TB_INTEGRADA[[#This Row],[TOMADOR]]="TIMS",TB_INTEGRADA[[#This Row],[ORÇ DIG]]*1.34,IF(TB_INTEGRADA[[#This Row],[TOMADOR]]="UTGSUL",TB_INTEGRADA[[#This Row],[ORÇ DIG]]*1.37,IF(TB_INTEGRADA[[#This Row],[TOMADOR]]="REGAP",TB_INTEGRADA[[#This Row],[ORÇ DIG]]*1.36,IF(TB_INTEGRADA[[#This Row],[TOMADOR]]="UTEIBI",TB_INTEGRADA[[#This Row],[ORÇ DIG]]*1.5,"S/TOMADOR")))))) -> 0 | AH21: =SUMIFS(Tb_HhPLAN[Hh DISC],Tb_HhPLAN[SS],TB_INTEGRADA[[#This Row],[Nº SS]],Tb_HhPLAN[DISCIPLINA],"MEC") -> 63.466982 | AI21: =SUMIFS(Hh_EXE_TOTAL[Hh],Hh_EXE_TOTAL[Nº SS],TB_INTEGRADA[[#This Row],[Nº SS]],Hh_EXE_TOTAL[DISCIPLINA],"MEC") -> 0 | AJ21: =IF(TB_INTEGRADA[[#This Row],[TOMADOR]]="EDIVIT",TB_INTEGRADA[[#This Row],[ORÇ DIG1]]*1.38,IF(TB_INTEGRADA[[#This Row],[TOMADOR]]="UTGC",TB_INTEGRADA[[#This Row],[ORÇ DIG1]]*1.47,IF(TB_INTEGRADA[[#This Row],[TOMADOR]]="TIMS",TB_INTEGRADA[[#This Row],[ORÇ DIG1]]*1.34,IF(TB_INTEGRADA[[#This Row],[TOMADOR]]="UTGSUL",TB_INTEGRADA[[#This Row],[ORÇ DIG1]]*1.37,IF(TB_INTEGRADA[[#This Row],[TOMADOR]]="REGAP",TB_INTEGRADA[[#This Row],[ORÇ DIG1]]*1.36,IF(TB_INTEGRADA[[#This Row],[TOMADOR]]="UTEIBI",TB_INTEGRADA[[#This Row],[ORÇ DIG1]]*1.5,"S/TOMADOR")))))) -> 0 | AL21: =SUMIFS(Tb_HhPLAN[Hh DISC],Tb_HhPLAN[SS],TB_INTEGRADA[[#This Row],[Nº SS]],Tb_HhPLAN[DISCIPLINA],"CIVIL") -> 0 | AM21: =SUMIFS(Hh_EXE_TOTAL[Hh],Hh_EXE_TOTAL[Nº SS],TB_INTEGRADA[[#This Row],[Nº SS]],Hh_EXE_TOTAL[DISCIPLINA],"CIVIL") -> 0 | AN21: =IF(TB_INTEGRADA[[#This Row],[TOMADOR]]="EDIVIT",TB_INTEGRADA[[#This Row],[ORÇ DIG2]]*1.38,IF(TB_INTEGRADA[[#This Row],[TOMADOR]]="UTGC",TB_INTEGRADA[[#This Row],[ORÇ DIG2]]*1.47,IF(TB_INTEGRADA[[#This Row],[TOMADOR]]="TIMS",TB_INTEGRADA[[#This Row],[ORÇ DIG2]]*1.34,IF(TB_INTEGRADA[[#This Row],[TOMADOR]]="UTGSUL",TB_INTEGRADA[[#This Row],[ORÇ DIG2]]*1.37,IF(TB_INTEGRADA[[#This Row],[TOMADOR]]="REGAP",TB_INTEGRADA[[#This Row],[ORÇ DIG2]]*1.36,IF(TB_INTEGRADA[[#This Row],[TOMADOR]]="UTEIBI",TB_INTEGRADA[[#This Row],[ORÇ DIG2]]*1.5,"S/TOMADOR")))))) -> 4295.2776 | AO21: 3112.52 | AP21: =SUMIFS(Tb_HhPLAN[Hh DISC],Tb_HhPLAN[SS],TB_INTEGRADA[[#This Row],[Nº SS]],Tb_HhPLAN[DISCIPLINA],"ELÉT") -> 1813.093 | AQ21: =SUMIFS(Hh_EXE_TOTAL[Hh],Hh_EXE_TOTAL[Nº SS],TB_INTEGRADA[[#This Row],[Nº SS]],Hh_EXE_TOTAL[DISCIPLINA],"ELÉT") -> 1952 | AR21: =IF(TB_INTEGRADA[[#This Row],[TOMADOR]]="EDIVIT",TB_INTEGRADA[[#This Row],[ORÇ DIG3]]*1.38,IF(TB_INTEGRADA[[#This Row],[TOMADOR]]="UTGC",TB_INTEGRADA[[#This Row],[ORÇ DIG3]]*1.47,IF(TB_INTEGRADA[[#This Row],[TOMADOR]]="TIMS",TB_INTEGRADA[[#This Row],[ORÇ DIG3]]*1.34,IF(TB_INTEGRADA[[#This Row],[TOMADOR]]="UTGSUL",TB_INTEGRADA[[#This Row],[ORÇ DIG3]]*1.37,IF(TB_INTEGRADA[[#This Row],[TOMADOR]]="REGAP",TB_INTEGRADA[[#This Row],[ORÇ DIG3]]*1.36,IF(TB_INTEGRADA[[#This Row],[TOMADOR]]="UTEIBI",TB_INTEGRADA[[#This Row],[ORÇ DIG3]]*1.5,"S/TOMADOR")))))) -> 0 | AT21: =SUMIFS(Tb_HhPLAN[Hh DISC],Tb_HhPLAN[SS],TB_INTEGRADA[[#This Row],[Nº SS]],Tb_HhPLAN[DISCIPLINA],"PINT") -> 0 | AU21: =SUMIFS(Hh_EXE_TOTAL[Hh],Hh_EXE_TOTAL[Nº SS],TB_INTEGRADA[[#This Row],[Nº SS]],Hh_EXE_TOTAL[DISCIPLINA],"PINT") -> 0 | AV21: =TB_INTEGRADA[[#This Row],[ORÇADO]]+TB_INTEGRADA[[#This Row],[ORÇADO1]]+TB_INTEGRADA[[#This Row],[ORÇADO2]]+TB_INTEGRADA[[#This Row],[ORÇADO3]] -> 4295.2776 | AW21: =TB_INTEGRADA[[#This Row],[PLANEJ]]+TB_INTEGRADA[[#This Row],[PLANEJ1]]+TB_INTEGRADA[[#This Row],[PLANEJ2]]+TB_INTEGRADA[[#This Row],[PLANEJ3]] -> 1876.56 | AX21: =TB_INTEGRADA[[#This Row],[REALIZ]]+TB_INTEGRADA[[#This Row],[REALIZ1]]+TB_INTEGRADA[[#This Row],[REALIZ2]]+TB_INTEGRADA[[#This Row],[REALIZ3]] -> 1952 | AY21: =IFERROR(TB_INTEGRADA[[#This Row],[REALIZ4]]/TB_INTEGRADA[[#This Row],[ORÇADO4]],"") -> 0.45445258 | AZ21: =_xlfn.XLOOKUP(TB_INTEGRADA[[#This Row],[Nº SS]],'CONTROLE EC'!B:B,'CONTROLE EC'!W:W,"",0,1) -> 1233914.5 | BA21: =_xlfn.XLOOKUP(TB_INTEGRADA[[#This Row],[Nº SS]],'CONTROLE EC'!B:B,'CONTROLE EC'!X:X,"",0,1) -> 715670.12 | BB21: =_xlfn.XLOOKUP(TB_INTEGRADA[[#This Row],[Nº SS]],'CONTROLE EC'!B:B,'CONTROLE EC'!Y:Y,"",0,1) -> 518244.4
A22: =IF(COUNTIFS($B$5:B22,TB_INTEGRADA[[#This Row],[Nº SS]])<>1,"",COUNTIFS($B$5:B22,TB_INTEGRADA[[#This Row],[Nº SS]])) -> 1 | B22: SS-18/2025 | C22: =_xlfn.XLOOKUP(TB_INTEGRADA[[#This Row],[Nº SS]],'CONTROLE EC'!B:B,'CONTROLE EC'!C:C,"",0,1) -> 24-1110-ES - ADEQUAÇÃO DA SALA DE MONITORAMENTO CISC | D22: =_xlfn.XLOOKUP(TB_INTEGRADA[[#This Row],[Nº SS]],'CONTROLE CRONOG'!B:B,'CONTROLE CRONOG'!D:D,"",0,1) -> SERVIÇO | E22: =_xlfn.XLOOKUP(TB_INTEGRADA[[#This Row],[Nº SS]],'CONTROLE EC'!B:B,'CONTROLE EC'!E:E,"",0,1) -> UTGC | F22: =_xlfn.XLOOKUP(TB_INTEGRADA[[#This Row],[Nº SS]],'CONTROLE EC'!B:B,'CONTROLE EC'!F:F,"",0,1) -> CONCLUÍDA | G22: =_xlfn.XLOOKUP(TB_INTEGRADA[[#This Row],[Nº SS]],'CONTROLE EC'!B:B,'CONTROLE EC'!R:R,"",0,1) -> REV.02 | H22: =IF(TB_INTEGRADA[[#This Row],[REVISÃO (EC)]]="","",_xlfn.XLOOKUP(TB_INTEGRADA[[#This Row],[Nº SS]],'CONTROLE EC'!B:B,'CONTROLE EC'!S:S,"",0,1)) -> 45975 | I22: =IF(TB_INTEGRADA[[#This Row],[REVISÃO (EC)]]="","",_xlfn.XLOOKUP(TB_INTEGRADA[[#This Row],[Nº SS]],'CONTROLE EC'!B:B,'CONTROLE EC'!U:U,"",0,1)) -> 45975 | J22: {=IF(TB_INTEGRADA[[#This Row],[DATA ENVIO. (EC)]]=IFERROR(INDEX('CONTROLE EC'!G22:Q22,MATCH(2,1/('CONTROLE EC'!G22:Q22<>""))),""),"",IFERROR(INDEX('CONTROLE EC'!G22:Q22,MATCH(2,1/('CONTROLE EC'!G22:Q22<>""))),""))} | K22: =IF(TB_INTEGRADA[[#This Row],[STATUS DEMANDA]]="NÃO EMITIDA SAMC","S/ EMISSÃO",_xlfn.XLOOKUP(TB_INTEGRADA[[#This Row],[Nº SS]],'CONTROLE EC'!B:B,'CONTROLE EC'!T:T,"",0,-1)) -> ENTREGUE | L22: =IF(TB_INTEGRADA[[#This Row],[STATUS DEMANDA]]="NÃO EMITIDA SAMC","S/ EMISSÃO",IF(TB_INTEGRADA[[#This Row],[STATUS DEMANDA]]="ON HOLD","ON HOLD",IF(TB_INTEGRADA[[#This Row],[STATUS DEMANDA]]="CANCELADA","CANCELADA",IF(TB_INTEGRADA[[#This Row],[DATA APROV. (EC)]]=0,"FISCALIZ.",IF(TB_INTEGRADA[[#This Row],[DATA APROV. (EC)]]="","PEND. FISCALIZ.",IF(TB_INTEGRADA[[#This Row],[DATA APROV. (EC)]]="N/A","APROVADO",IF(TB_INTEGRADA[[#This Row],[REVISÃO (EC)]]="","",_xlfn.XLOOKUP(TB_INTEGRADA[[#This Row],[Nº SS]],'CONTROLE EC'!B:B,'CONTROLE EC'!V:V,"",0,1)))))))) -> APROVADO | M22: {=IFERROR(_xlfn.IFS(TB_INTEGRADA[[#This Row],[STATUS DEMANDA]]="CANCELADA",0,TB_INTEGRADA[[#This Row],[DATA APROV. (EC)]]="",TODAY()-TB_INTEGRADA[[#This Row],[DATA ENVIO. (EC)]],TB_INTEGRADA[[#This Row],[DATA APROV. (EC)]]>=TB_INTEGRADA[[#This Row],[DATA ENVIO. (EC)]],0,TB_INTEGRADA[[#This Row],[DATA ENVIO. (EC)]]="",0,TB_INTEGRADA[[#This Row],[DATA ENVIO. (EC)]]>TB_INTEGRADA[[#This Row],[DATA APROV. (EC)]],TODAY()-TB_INTEGRADA[[#This Row],[DATA ENVIO. (EC)]]),"")} -> 0 | N22: =IF(TB_INTEGRADA[[#This Row],[STATUS DEMANDA]]="NÃO EMITIDA SAMC","S/ EMISSÃO",IF(TB_INTEGRADA[[#This Row],[STATUS DEMANDA]]="ON HOLD","ON HOLD",IF(F22="CANCELADA","CANCELADA",IF(L22="REPROVADO","EM PLANEJ.",IF(K22<>"ENTREGUE","EM PLANEJ.",IF(H22="","EM PLANEJ.",IF(I22="","FISCALIZ.",IF(M22<0,"EM PLANEJ.",IF(TB_INTEGRADA[[#This Row],[DATA APROV. (EC)]]>=TB_INTEGRADA[[#This Row],[DATA ENVIO. (EC)]],"RETORNO OK","FISCALIZ."))))))))) -> RETORNO OK | O22: =_xlfn.XLOOKUP(TB_INTEGRADA[[#This Row],[Nº SS]],'CONTROLE CRONOG'!B:B,'CONTROLE CRONOG'!R:R,"",0,1) -> REV.03 | P22: =IF(TB_INTEGRADA[[#This Row],[REVISÃO (CR)]]="","",_xlfn.XLOOKUP(TB_INTEGRADA[[#This Row],[Nº SS]],'CONTROLE CRONOG'!B:B,'CONTROLE CRONOG'!S:S,"",0,1)) -> 45979 | Q22: =IF(TB_INTEGRADA[[#This Row],[REVISÃO (CR)]]="","",_xlfn.XLOOKUP(TB_INTEGRADA[[#This Row],[Nº SS]],'CONTROLE CRONOG'!B:B,'CONTROLE CRONOG'!U:U,"",0,1)) -> 45980 | R22: {=IF(TB_INTEGRADA[[#This Row],[DATA ENVIO. (CR)]]=IFERROR(INDEX('CONTROLE CRONOG'!G22:Q22,MATCH(2,1/('CONTROLE CRONOG'!G22:Q22<>""))),""),"",IFERROR(INDEX('CONTROLE CRONOG'!G22:Q22,MATCH(2,1/('CONTROLE CRONOG'!G22:Q22<>""))),""))} | S22: =_xlfn.XLOOKUP(TB_INTEGRADA[[#This Row],[Nº SS]],'CONTROLE CRONOG'!B:B,'CONTROLE CRONOG'!T:T,"",0,-1) -> ENTREGUE | T22: =IF(TB_INTEGRADA[[#This Row],[STATUS DEMANDA]]="ON HOLD","ON HOLD",IF(TB_INTEGRADA[[#This Row],[STATUS DEMANDA]]="CANCELADA","CANCELADA",IF(TB_INTEGRADA[[#This Row],[DATA APROV. (CR)]]=0,"FISCALIZ.",IF(TB_INTEGRADA[[#This Row],[DATA APROV. (CR)]]="N/A","APROVADO",IF(TB_INTEGRADA[[#This Row],[REVISÃO (CR)]]="","",_xlfn.XLOOKUP(TB_INTEGRADA[[#This Row],[Nº SS]],'CONTROLE CRONOG'!B:B,'CONTROLE CRONOG'!V:V,"",0,1)))))) -> APROVADO | V22: 46077 | W22: 46083 | X22: =IFERROR(TB_INTEGRADA[[#This Row],[TÉRM. TD]]-TB_INTEGRADA[[#This Row],[TÉRMINO LB]],0) -> 6 | Y22: 1 | Z22: 0.9995 | AA22: -0.0005 | AB22: =IFERROR(TB_INTEGRADA[[#This Row],[REAL (%)]]-TB_INTEGRADA[[#This Row],[PREV (%)]],0) -> -0.0005 | AC22: 0 | AF22: =IF(TB_INTEGRADA[[#This Row],[TOMADOR]]="EDIVIT",TB_INTEGRADA[[#This Row],[ORÇ DIG]]*1.38,IF(TB_INTEGRADA[[#This Row],[TOMADOR]]="UTGC",TB_INTEGRADA[[#This Row],[ORÇ DIG]]*1.47,IF(TB_INTEGRADA[[#This Row],[TOMADOR]]="TIMS",TB_INTEGRADA[[#This Row],[ORÇ DIG]]*1.34,IF(TB_INTEGRADA[[#This Row],[TOMADOR]]="UTGSUL",TB_INTEGRADA[[#This Row],[ORÇ DIG]]*1.37,IF(TB_INTEGRADA[[#This Row],[TOMADOR]]="REGAP",TB_INTEGRADA[[#This Row],[ORÇ DIG]]*1.36,IF(TB_INTEGRADA[[#This Row],[TOMADOR]]="UTEIBI",TB_INTEGRADA[[#This Row],[ORÇ DIG]]*1.5,"S/TOMADOR")))))) -> 0 | AH22: =SUMIFS(Tb_HhPLAN[Hh DISC],Tb_HhPLAN[SS],TB_INTEGRADA[[#This Row],[Nº SS]],Tb_HhPLAN[DISCIPLINA],"MEC") -> 0 | AI22: =SUMIFS(Hh_EXE_TOTAL[Hh],Hh_EXE_TOTAL[Nº SS],TB_INTEGRADA[[#This Row],[Nº SS]],Hh_EXE_TOTAL[DISCIPLINA],"MEC") -> 0 | AJ22: =IF(TB_INTEGRADA[[#This Row],[TOMADOR]]="EDIVIT",TB_INTEGRADA[[#This Row],[ORÇ DIG1]]*1.38,IF(TB_INTEGRADA[[#This Row],[TOMADOR]]="UTGC",TB_INTEGRADA[[#This Row],[ORÇ DIG1]]*1.47,IF(TB_INTEGRADA[[#This Row],[TOMADOR]]="TIMS",TB_INTEGRADA[[#This Row],[ORÇ DIG1]]*1.34,IF(TB_INTEGRADA[[#This Row],[TOMADOR]]="UTGSUL",TB_INTEGRADA[[#This Row],[ORÇ DIG1]]*1.37,IF(TB_INTEGRADA[[#This Row],[TOMADOR]]="REGAP",TB_INTEGRADA[[#This Row],[ORÇ DIG1]]*1.36,IF(TB_INTEGRADA[[#This Row],[TOMADOR]]="UTEIBI",TB_INTEGRADA[[#This Row],[ORÇ DIG1]]*1.5,"S/TOMADOR")))))) -> 859.4355 | AK22: 584.65 | AL22: =SUMIFS(Tb_HhPLAN[Hh DISC],Tb_HhPLAN[SS],TB_INTEGRADA[[#This Row],[Nº SS]],Tb_HhPLAN[DISCIPLINA],"CIVIL") -> 560.44898 | AM22: =SUMIFS(Hh_EXE_TOTAL[Hh],Hh_EXE_TOTAL[Nº SS],TB_INTEGRADA[[#This Row],[Nº SS]],Hh_EXE_TOTAL[DISCIPLINA],"CIVIL") -> 588.52174 | AN22: =IF(TB_INTEGRADA[[#This Row],[TOMADOR]]="EDIVIT",TB_INTEGRADA[[#This Row],[ORÇ DIG2]]*1.38,IF(TB_INTEGRADA[[#This Row],[TOMADOR]]="UTGC",TB_INTEGRADA[[#This Row],[ORÇ DIG2]]*1.47,IF(TB_INTEGRADA[[#This Row],[TOMADOR]]="TIMS",TB_INTEGRADA[[#This Row],[ORÇ DIG2]]*1.34,IF(TB_INTEGRADA[[#This Row],[TOMADOR]]="UTGSUL",TB_INTEGRADA[[#This Row],[ORÇ DIG2]]*1.37,IF(TB_INTEGRADA[[#This Row],[TOMADOR]]="REGAP",TB_INTEGRADA[[#This Row],[ORÇ DIG2]]*1.36,IF(TB_INTEGRADA[[#This Row],[TOMADOR]]="UTEIBI",TB_INTEGRADA[[#This Row],[ORÇ DIG2]]*1.5,"S/TOMADOR")))))) -> 460.9185 | AO22: 313.55 | AP22: =SUMIFS(Tb_HhPLAN[Hh DISC],Tb_HhPLAN[SS],TB_INTEGRADA[[#This Row],[Nº SS]],Tb_HhPLAN[DISCIPLINA],"ELÉT") -> 170.57143 | AQ22: =SUMIFS(Hh_EXE_TOTAL[Hh],Hh_EXE_TOTAL[Nº SS],TB_INTEGRADA[[#This Row],[Nº SS]],Hh_EXE_TOTAL[DISCIPLINA],"ELÉT") -> 150.26087 | AR22: =IF(TB_INTEGRADA[[#This Row],[TOMADOR]]="EDIVIT",TB_INTEGRADA[[#This Row],[ORÇ DIG3]]*1.38,IF(TB_INTEGRADA[[#This Row],[TOMADOR]]="UTGC",TB_INTEGRADA[[#This Row],[ORÇ DIG3]]*1.47,IF(TB_INTEGRADA[[#This Row],[TOMADOR]]="TIMS",TB_INTEGRADA[[#This Row],[ORÇ DIG3]]*1.34,IF(TB_INTEGRADA[[#This Row],[TOMADOR]]="UTGSUL",TB_INTEGRADA[[#This Row],[ORÇ DIG3]]*1.37,IF(TB_INTEGRADA[[#This Row],[TOMADOR]]="REGAP",TB_INTEGRADA[[#This Row],[ORÇ DIG3]]*1.36,IF(TB_INTEGRADA[[#This Row],[TOMADOR]]="UTEIBI",TB_INTEGRADA[[#This Row],[ORÇ DIG3]]*1.5,"S/TOMADOR")))))) -> 285.7827 | AS22: 194.41 | AT22: =SUMIFS(Tb_HhPLAN[Hh DISC],Tb_HhPLAN[SS],TB_INTEGRADA[[#This Row],[Nº SS]],Tb_HhPLAN[DISCIPLINA],"PINT") -> 64.979592 | AU22: =SUMIFS(Hh_EXE_TOTAL[Hh],Hh_EXE_TOTAL[Nº SS],TB_INTEGRADA[[#This Row],[Nº SS]],Hh_EXE_TOTAL[DISCIPLINA],"PINT") -> 413.21739 | AV22: =TB_INTEGRADA[[#This Row],[ORÇADO]]+TB_INTEGRADA[[#This Row],[ORÇADO1]]+TB_INTEGRADA[[#This Row],[ORÇADO2]]+TB_INTEGRADA[[#This Row],[ORÇADO3]] -> 1606.1367 | AW22: =TB_INTEGRADA[[#This Row],[PLANEJ]]+TB_INTEGRADA[[#This Row],[PLANEJ1]]+TB_INTEGRADA[[#This Row],[PLANEJ2]]+TB_INTEGRADA[[#This Row],[PLANEJ3]] -> 796 | AX22: =TB_INTEGRADA[[#This Row],[REALIZ]]+TB_INTEGRADA[[#This Row],[REALIZ1]]+TB_INTEGRADA[[#This Row],[REALIZ2]]+TB_INTEGRADA[[#This Row],[REALIZ3]] -> 1152 | AY22: =IFERROR(TB_INTEGRADA[[#This Row],[REALIZ4]]/TB_INTEGRADA[[#This Row],[ORÇADO4]],"") -> 0.71724904 | AZ22: =_xlfn.XLOOKUP(TB_INTEGRADA[[#This Row],[Nº SS]],'CONTROLE EC'!B:B,'CONTROLE EC'!W:W,"",0,1) -> 196612.97 | BA22: =_xlfn.XLOOKUP(TB_INTEGRADA[[#This Row],[Nº SS]],'CONTROLE EC'!B:B,'CONTROLE EC'!X:X,"",0,1) -> 196612.97 | BB22: =_xlfn.XLOOKUP(TB_INTEGRADA[[#This Row],[Nº SS]],'CONTROLE EC'!B:B,'CONTROLE EC'!Y:Y,"",0,1) -> 0
A23: =IF(COUNTIFS($B$5:B23,TB_INTEGRADA[[#This Row],[Nº SS]])<>1,"",COUNTIFS($B$5:B23,TB_INTEGRADA[[#This Row],[Nº SS]])) -> 1 | B23: SS-19/2025 | C23: =_xlfn.XLOOKUP(TB_INTEGRADA[[#This Row],[Nº SS]],'CONTROLE EC'!B:B,'CONTROLE EC'!C:C,"",0,1) -> 23-0316-ES - SINALIZAÇÃO DAS ESCADAS | D23: =_xlfn.XLOOKUP(TB_INTEGRADA[[#This Row],[Nº SS]],'CONTROLE CRONOG'!B:B,'CONTROLE CRONOG'!D:D,"",0,1) -> SERVIÇO | E23: =_xlfn.XLOOKUP(TB_INTEGRADA[[#This Row],[Nº SS]],'CONTROLE EC'!B:B,'CONTROLE EC'!E:E,"",0,1) -> EDIVIT | F23: =_xlfn.XLOOKUP(TB_INTEGRADA[[#This Row],[Nº SS]],'CONTROLE EC'!B:B,'CONTROLE EC'!F:F,"",0,1) -> CONCLUÍDA | G23: =_xlfn.XLOOKUP(TB_INTEGRADA[[#This Row],[Nº SS]],'CONTROLE EC'!B:B,'CONTROLE EC'!R:R,"",0,1) -> REV.01 | H23: =IF(TB_INTEGRADA[[#This Row],[REVISÃO (EC)]]="","",_xlfn.XLOOKUP(TB_INTEGRADA[[#This Row],[Nº SS]],'CONTROLE EC'!B:B,'CONTROLE EC'!S:S,"",0,1)) -> 45960 | I23: =IF(TB_INTEGRADA[[#This Row],[REVISÃO (EC)]]="","",_xlfn.XLOOKUP(TB_INTEGRADA[[#This Row],[Nº SS]],'CONTROLE EC'!B:B,'CONTROLE EC'!U:U,"",0,1)) -> 45960 | J23: {=IF(TB_INTEGRADA[[#This Row],[DATA ENVIO. (EC)]]=IFERROR(INDEX('CONTROLE EC'!G23:Q23,MATCH(2,1/('CONTROLE EC'!G23:Q23<>""))),""),"",IFERROR(INDEX('CONTROLE EC'!G23:Q23,MATCH(2,1/('CONTROLE EC'!G23:Q23<>""))),""))} | K23: =IF(TB_INTEGRADA[[#This Row],[STATUS DEMANDA]]="NÃO EMITIDA SAMC","S/ EMISSÃO",_xlfn.XLOOKUP(TB_INTEGRADA[[#This Row],[Nº SS]],'CONTROLE EC'!B:B,'CONTROLE EC'!T:T,"",0,-1)) -> ENTREGUE | L23: =IF(TB_INTEGRADA[[#This Row],[STATUS DEMANDA]]="NÃO EMITIDA SAMC","S/ EMISSÃO",IF(TB_INTEGRADA[[#This Row],[STATUS DEMANDA]]="ON HOLD","ON HOLD",IF(TB_INTEGRADA[[#This Row],[STATUS DEMANDA]]="CANCELADA","CANCELADA",IF(TB_INTEGRADA[[#This Row],[DATA APROV. (EC)]]=0,"FISCALIZ.",IF(TB_INTEGRADA[[#This Row],[DATA APROV. (EC)]]="","PEND. FISCALIZ.",IF(TB_INTEGRADA[[#This Row],[DATA APROV. (EC)]]="N/A","APROVADO",IF(TB_INTEGRADA[[#This Row],[REVISÃO (EC)]]="","",_xlfn.XLOOKUP(TB_INTEGRADA[[#This Row],[Nº SS]],'CONTROLE EC'!B:B,'CONTROLE EC'!V:V,"",0,1)))))))) -> APROVADO | M23: {=IFERROR(_xlfn.IFS(TB_INTEGRADA[[#This Row],[STATUS DEMANDA]]="CANCELADA",0,TB_INTEGRADA[[#This Row],[DATA APROV. (EC)]]="",TODAY()-TB_INTEGRADA[[#This Row],[DATA ENVIO. (EC)]],TB_INTEGRADA[[#This Row],[DATA APROV. (EC)]]>=TB_INTEGRADA[[#This Row],[DATA ENVIO. (EC)]],0,TB_INTEGRADA[[#This Row],[DATA ENVIO. (EC)]]="",0,TB_INTEGRADA[[#This Row],[DATA ENVIO. (EC)]]>TB_INTEGRADA[[#This Row],[DATA APROV. (EC)]],TODAY()-TB_INTEGRADA[[#This Row],[DATA ENVIO. (EC)]]),"")} -> 0 | N23: =IF(TB_INTEGRADA[[#This Row],[STATUS DEMANDA]]="NÃO EMITIDA SAMC","S/ EMISSÃO",IF(TB_INTEGRADA[[#This Row],[STATUS DEMANDA]]="ON HOLD","ON HOLD",IF(F23="CANCELADA","CANCELADA",IF(L23="REPROVADO","EM PLANEJ.",IF(K23<>"ENTREGUE","EM PLANEJ.",IF(H23="","EM PLANEJ.",IF(I23="","FISCALIZ.",IF(M23<0,"EM PLANEJ.",IF(TB_INTEGRADA[[#This Row],[DATA APROV. (EC)]]>=TB_INTEGRADA[[#This Row],[DATA ENVIO. (EC)]],"RETORNO OK","FISCALIZ."))))))))) -> RETORNO OK | O23: =_xlfn.XLOOKUP(TB_INTEGRADA[[#This Row],[Nº SS]],'CONTROLE CRONOG'!B:B,'CONTROLE CRONOG'!R:R,"",0,1) -> REV.01 | P23: =IF(TB_INTEGRADA[[#This Row],[REVISÃO (CR)]]="","",_xlfn.XLOOKUP(TB_INTEGRADA[[#This Row],[Nº SS]],'CONTROLE CRONOG'!B:B,'CONTROLE CRONOG'!S:S,"",0,1)) -> 45959 | Q23: =IF(TB_INTEGRADA[[#This Row],[REVISÃO (CR)]]="","",_xlfn.XLOOKUP(TB_INTEGRADA[[#This Row],[Nº SS]],'CONTROLE CRONOG'!B:B,'CONTROLE CRONOG'!U:U,"",0,1)) -> 45959 | R23: {=IF(TB_INTEGRADA[[#This Row],[DATA ENVIO. (CR)]]=IFERROR(INDEX('CONTROLE CRONOG'!G23:Q23,MATCH(2,1/('CONTROLE CRONOG'!G23:Q23<>""))),""),"",IFERROR(INDEX('CONTROLE CRONOG'!G23:Q23,MATCH(2,1/('CONTROLE CRONOG'!G23:Q23<>""))),""))} | S23: =_xlfn.XLOOKUP(TB_INTEGRADA[[#This Row],[Nº SS]],'CONTROLE CRONOG'!B:B,'CONTROLE CRONOG'!T:T,"",0,-1) -> ENTREGUE | T23: =IF(TB_INTEGRADA[[#This Row],[STATUS DEMANDA]]="ON HOLD","ON HOLD",IF(TB_INTEGRADA[[#This Row],[STATUS DEMANDA]]="CANCELADA","CANCELADA",IF(TB_INTEGRADA[[#This Row],[DATA APROV. (CR)]]=0,"FISCALIZ.",IF(TB_INTEGRADA[[#This Row],[DATA APROV. (CR)]]="N/A","APROVADO",IF(TB_INTEGRADA[[#This Row],[REVISÃO (CR)]]="","",_xlfn.XLOOKUP(TB_INTEGRADA[[#This Row],[Nº SS]],'CONTROLE CRONOG'!B:B,'CONTROLE CRONOG'!V:V,"",0,1)))))) -> APROVADO | V23: 45993 | W23: 46003 | X23: =IFERROR(TB_INTEGRADA[[#This Row],[TÉRM. TD]]-TB_INTEGRADA[[#This Row],[TÉRMINO LB]],0) -> 10 | Y23: 1 | Z23: 1 | AA23: 0 | AB23: =IFERROR(TB_INTEGRADA[[#This Row],[REAL (%)]]-TB_INTEGRADA[[#This Row],[PREV (%)]],0) -> 0 | AC23: 0 | AD23: 0 | AF23: =IF(TB_INTEGRADA[[#This Row],[TOMADOR]]="EDIVIT",TB_INTEGRADA[[#This Row],[ORÇ DIG]]*1.38,IF(TB_INTEGRADA[[#This Row],[TOMADOR]]="UTGC",TB_INTEGRADA[[#This Row],[ORÇ DIG]]*1.47,IF(TB_INTEGRADA[[#This Row],[TOMADOR]]="TIMS",TB_INTEGRADA[[#This Row],[ORÇ DIG]]*1.34,IF(TB_INTEGRADA[[#This Row],[TOMADOR]]="UTGSUL",TB_INTEGRADA[[#This Row],[ORÇ DIG]]*1.37,IF(TB_INTEGRADA[[#This Row],[TOMADOR]]="REGAP",TB_INTEGRADA[[#This Row],[ORÇ DIG]]*1.36,IF(TB_INTEGRADA[[#This Row],[TOMADOR]]="UTEIBI",TB_INTEGRADA[[#This Row],[ORÇ DIG]]*1.5,"S/TOMADOR")))))) -> 0 | AH23: =SUMIFS(Tb_HhPLAN[Hh DISC],Tb_HhPLAN[SS],TB_INTEGRADA[[#This Row],[Nº SS]],Tb_HhPLAN[DISCIPLINA],"MEC") -> 0 | AI23: =SUMIFS(Hh_EXE_TOTAL[Hh],Hh_EXE_TOTAL[Nº SS],TB_INTEGRADA[[#This Row],[Nº SS]],Hh_EXE_TOTAL[DISCIPLINA],"MEC") -> 0 | AJ23: =IF(TB_INTEGRADA[[#This Row],[TOMADOR]]="EDIVIT",TB_INTEGRADA[[#This Row],[ORÇ DIG1]]*1.38,IF(TB_INTEGRADA[[#This Row],[TOMADOR]]="UTGC",TB_INTEGRADA[[#This Row],[ORÇ DIG1]]*1.47,IF(TB_INTEGRADA[[#This Row],[TOMADOR]]="TIMS",TB_INTEGRADA[[#This Row],[ORÇ DIG1]]*1.34,IF(TB_INTEGRADA[[#This Row],[TOMADOR]]="UTGSUL",TB_INTEGRADA[[#This Row],[ORÇ DIG1]]*1.37,IF(TB_INTEGRADA[[#This Row],[TOMADOR]]="REGAP",TB_INTEGRADA[[#This Row],[ORÇ DIG1]]*1.36,IF(TB_INTEGRADA[[#This Row],[TOMADOR]]="UTEIBI",TB_INTEGRADA[[#This Row],[ORÇ DIG1]]*1.5,"S/TOMADOR")))))) -> 773.4486 | AK23: 560.47 | AL23: =SUMIFS(Tb_HhPLAN[Hh DISC],Tb_HhPLAN[SS],TB_INTEGRADA[[#This Row],[Nº SS]],Tb_HhPLAN[DISCIPLINA],"CIVIL") -> 716 | AM23: =SUMIFS(Hh_EXE_TOTAL[Hh],Hh_EXE_TOTAL[Nº SS],TB_INTEGRADA[[#This Row],[Nº SS]],Hh_EXE_TOTAL[DISCIPLINA],"CIVIL") -> 848 | AN23: =IF(TB_INTEGRADA[[#This Row],[TOMADOR]]="EDIVIT",TB_INTEGRADA[[#This Row],[ORÇ DIG2]]*1.38,IF(TB_INTEGRADA[[#This Row],[TOMADOR]]="UTGC",TB_INTEGRADA[[#This Row],[ORÇ DIG2]]*1.47,IF(TB_INTEGRADA[[#This Row],[TOMADOR]]="TIMS",TB_INTEGRADA[[#This Row],[ORÇ DIG2]]*1.34,IF(TB_INTEGRADA[[#This Row],[TOMADOR]]="UTGSUL",TB_INTEGRADA[[#This Row],[ORÇ DIG2]]*1.37,IF(TB_INTEGRADA[[#This Row],[TOMADOR]]="REGAP",TB_INTEGRADA[[#This Row],[ORÇ DIG2]]*1.36,IF(TB_INTEGRADA[[#This Row],[TOMADOR]]="UTEIBI",TB_INTEGRADA[[#This Row],[ORÇ DIG2]]*1.5,"S/TOMADOR")))))) -> 0 | AP23: =SUMIFS(Tb_HhPLAN[Hh DISC],Tb_HhPLAN[SS],TB_INTEGRADA[[#This Row],[Nº SS]],Tb_HhPLAN[DISCIPLINA],"ELÉT") -> 0 | AQ23: =SUMIFS(Hh_EXE_TOTAL[Hh],Hh_EXE_TOTAL[Nº SS],TB_INTEGRADA[[#This Row],[Nº SS]],Hh_EXE_TOTAL[DISCIPLINA],"ELÉT") -> 0 | AR23: =IF(TB_INTEGRADA[[#This Row],[TOMADOR]]="EDIVIT",TB_INTEGRADA[[#This Row],[ORÇ DIG3]]*1.38,IF(TB_INTEGRADA[[#This Row],[TOMADOR]]="UTGC",TB_INTEGRADA[[#This Row],[ORÇ DIG3]]*1.47,IF(TB_INTEGRADA[[#This Row],[TOMADOR]]="TIMS",TB_INTEGRADA[[#This Row],[ORÇ DIG3]]*1.34,IF(TB_INTEGRADA[[#This Row],[TOMADOR]]="UTGSUL",TB_INTEGRADA[[#This Row],[ORÇ DIG3]]*1.37,IF(TB_INTEGRADA[[#This Row],[TOMADOR]]="REGAP",TB_INTEGRADA[[#This Row],[ORÇ DIG3]]*1.36,IF(TB_INTEGRADA[[#This Row],[TOMADOR]]="UTEIBI",TB_INTEGRADA[[#This Row],[ORÇ DIG3]]*1.5,"S/TOMADOR")))))) -> 0 | AT23: =SUMIFS(Tb_HhPLAN[Hh DISC],Tb_HhPLAN[SS],TB_INTEGRADA[[#This Row],[Nº SS]],Tb_HhPLAN[DISCIPLINA],"PINT") -> 0 | AU23: =SUMIFS(Hh_EXE_TOTAL[Hh],Hh_EXE_TOTAL[Nº SS],TB_INTEGRADA[[#This Row],[Nº SS]],Hh_EXE_TOTAL[DISCIPLINA],"PINT") -> 0 | AV23: =TB_INTEGRADA[[#This Row],[ORÇADO]]+TB_INTEGRADA[[#This Row],[ORÇADO1]]+TB_INTEGRADA[[#This Row],[ORÇADO2]]+TB_INTEGRADA[[#This Row],[ORÇADO3]] -> 773.4486 | AW23: =TB_INTEGRADA[[#This Row],[PLANEJ]]+TB_INTEGRADA[[#This Row],[PLANEJ1]]+TB_INTEGRADA[[#This Row],[PLANEJ2]]+TB_INTEGRADA[[#This Row],[PLANEJ3]] -> 716 | AX23: =TB_INTEGRADA[[#This Row],[REALIZ]]+TB_INTEGRADA[[#This Row],[REALIZ1]]+TB_INTEGRADA[[#This Row],[REALIZ2]]+TB_INTEGRADA[[#This Row],[REALIZ3]] -> 848 | AY23: =IFERROR(TB_INTEGRADA[[#This Row],[REALIZ4]]/TB_INTEGRADA[[#This Row],[ORÇADO4]],"") -> 1.0963883 | AZ23: =_xlfn.XLOOKUP(TB_INTEGRADA[[#This Row],[Nº SS]],'CONTROLE EC'!B:B,'CONTROLE EC'!W:W,"",0,1) -> 90327.897 | BA23: =_xlfn.XLOOKUP(TB_INTEGRADA[[#This Row],[Nº SS]],'CONTROLE EC'!B:B,'CONTROLE EC'!X:X,"",0,1) -> 90327.897 | BB23: =_xlfn.XLOOKUP(TB_INTEGRADA[[#This Row],[Nº SS]],'CONTROLE EC'!B:B,'CONTROLE EC'!Y:Y,"",0,1) -> 0
A24: =IF(COUNTIFS($B$5:B24,TB_INTEGRADA[[#This Row],[Nº SS]])<>1,"",COUNTIFS($B$5:B24,TB_INTEGRADA[[#This Row],[Nº SS]])) -> 1 | B24: SS-20/2025 | C24: =_xlfn.XLOOKUP(TB_INTEGRADA[[#This Row],[Nº SS]],'CONTROLE EC'!B:B,'CONTROLE EC'!C:C,"",0,1) -> 25-0147-ES - DISPONIBILIZAÇÃO DE CONTAINER ESCRITÓRIO | D24: =_xlfn.XLOOKUP(TB_INTEGRADA[[#This Row],[Nº SS]],'CONTROLE CRONOG'!B:B,'CONTROLE CRONOG'!D:D,"",0,1) -> SERVIÇO | E24: =_xlfn.XLOOKUP(TB_INTEGRADA[[#This Row],[Nº SS]],'CONTROLE EC'!B:B,'CONTROLE EC'!E:E,"",0,1) -> UTGC | F24: =_xlfn.XLOOKUP(TB_INTEGRADA[[#This Row],[Nº SS]],'CONTROLE EC'!B:B,'CONTROLE EC'!F:F,"",0,1) -> CONCLUÍDA | G24: =_xlfn.XLOOKUP(TB_INTEGRADA[[#This Row],[Nº SS]],'CONTROLE EC'!B:B,'CONTROLE EC'!R:R,"",0,1) -> REV.00 | H24: =IF(TB_INTEGRADA[[#This Row],[REVISÃO (EC)]]="","",_xlfn.XLOOKUP(TB_INTEGRADA[[#This Row],[Nº SS]],'CONTROLE EC'!B:B,'CONTROLE EC'!S:S,"",0,1)) -> 45957 | I24: =IF(TB_INTEGRADA[[#This Row],[REVISÃO (EC)]]="","",_xlfn.XLOOKUP(TB_INTEGRADA[[#This Row],[Nº SS]],'CONTROLE EC'!B:B,'CONTROLE EC'!U:U,"",0,1)) -> 45959 | J24: {=IF(TB_INTEGRADA[[#This Row],[DATA ENVIO. (EC)]]=IFERROR(INDEX('CONTROLE EC'!G24:Q24,MATCH(2,1/('CONTROLE EC'!G24:Q24<>""))),""),"",IFERROR(INDEX('CONTROLE EC'!G24:Q24,MATCH(2,1/('CONTROLE EC'!G24:Q24<>""))),""))} | K24: =IF(TB_INTEGRADA[[#This Row],[STATUS DEMANDA]]="NÃO EMITIDA SAMC","S/ EMISSÃO",_xlfn.XLOOKUP(TB_INTEGRADA[[#This Row],[Nº SS]],'CONTROLE EC'!B:B,'CONTROLE EC'!T:T,"",0,-1)) -> ENTREGUE | L24: =IF(TB_INTEGRADA[[#This Row],[STATUS DEMANDA]]="NÃO EMITIDA SAMC","S/ EMISSÃO",IF(TB_INTEGRADA[[#This Row],[STATUS DEMANDA]]="ON HOLD","ON HOLD",IF(TB_INTEGRADA[[#This Row],[STATUS DEMANDA]]="CANCELADA","CANCELADA",IF(TB_INTEGRADA[[#This Row],[DATA APROV. (EC)]]=0,"FISCALIZ.",IF(TB_INTEGRADA[[#This Row],[DATA APROV. (EC)]]="","PEND. FISCALIZ.",IF(TB_INTEGRADA[[#This Row],[DATA APROV. (EC)]]="N/A","APROVADO",IF(TB_INTEGRADA[[#This Row],[REVISÃO (EC)]]="","",_xlfn.XLOOKUP(TB_INTEGRADA[[#This Row],[Nº SS]],'CONTROLE EC'!B:B,'CONTROLE EC'!V:V,"",0,1)))))))) -> APROVADO | M24: {=IFERROR(_xlfn.IFS(TB_INTEGRADA[[#This Row],[STATUS DEMANDA]]="CANCELADA",0,TB_INTEGRADA[[#This Row],[DATA APROV. (EC)]]="",TODAY()-TB_INTEGRADA[[#This Row],[DATA ENVIO. (EC)]],TB_INTEGRADA[[#This Row],[DATA APROV. (EC)]]>=TB_INTEGRADA[[#This Row],[DATA ENVIO. (EC)]],0,TB_INTEGRADA[[#This Row],[DATA ENVIO. (EC)]]="",0,TB_INTEGRADA[[#This Row],[DATA ENVIO. (EC)]]>TB_INTEGRADA[[#This Row],[DATA APROV. (EC)]],TODAY()-TB_INTEGRADA[[#This Row],[DATA ENVIO. (EC)]]),"")} -> 0 | N24: =IF(TB_INTEGRADA[[#This Row],[STATUS DEMANDA]]="NÃO EMITIDA SAMC","S/ EMISSÃO",IF(TB_INTEGRADA[[#This Row],[STATUS DEMANDA]]="ON HOLD","ON HOLD",IF(F24="CANCELADA","CANCELADA",IF(L24="REPROVADO","EM PLANEJ.",IF(K24<>"ENTREGUE","EM PLANEJ.",IF(H24="","EM PLANEJ.",IF(I24="","FISCALIZ.",IF(M24<0,"EM PLANEJ.",IF(TB_INTEGRADA[[#This Row],[DATA APROV. (EC)]]>=TB_INTEGRADA[[#This Row],[DATA ENVIO. (EC)]],"RETORNO OK","FISCALIZ."))))))))) -> RETORNO OK | O24: =_xlfn.XLOOKUP(TB_INTEGRADA[[#This Row],[Nº SS]],'CONTROLE CRONOG'!B:B,'CONTROLE CRONOG'!R:R,"",0,1) -> REV.00 | P24: =IF(TB_INTEGRADA[[#This Row],[REVISÃO (CR)]]="","",_xlfn.XLOOKUP(TB_INTEGRADA[[#This Row],[Nº SS]],'CONTROLE CRONOG'!B:B,'CONTROLE CRONOG'!S:S,"",0,1)) -> N/A | Q24: =IF(TB_INTEGRADA[[#This Row],[REVISÃO (CR)]]="","",_xlfn.XLOOKUP(TB_INTEGRADA[[#This Row],[Nº SS]],'CONTROLE CRONOG'!B:B,'CONTROLE CRONOG'!U:U,"",0,1)) -> N/A | R24: {=IF(TB_INTEGRADA[[#This Row],[DATA ENVIO. (CR)]]=IFERROR(INDEX('CONTROLE CRONOG'!G24:Q24,MATCH(2,1/('CONTROLE CRONOG'!G24:Q24<>""))),""),"",IFERROR(INDEX('CONTROLE CRONOG'!G24:Q24,MATCH(2,1/('CONTROLE CRONOG'!G24:Q24<>""))),""))} | S24: =_xlfn.XLOOKUP(TB_INTEGRADA[[#This Row],[Nº SS]],'CONTROLE CRONOG'!B:B,'CONTROLE CRONOG'!T:T,"",0,-1) -> ENTREGUE | T24: =IF(TB_INTEGRADA[[#This Row],[STATUS DEMANDA]]="ON HOLD","ON HOLD",IF(TB_INTEGRADA[[#This Row],[STATUS DEMANDA]]="CANCELADA","CANCELADA",IF(TB_INTEGRADA[[#This Row],[DATA APROV. (CR)]]=0,"FISCALIZ.",IF(TB_INTEGRADA[[#This Row],[DATA APROV. (CR)]]="N/A","APROVADO",IF(TB_INTEGRADA[[#This Row],[REVISÃO (CR)]]="","",_xlfn.XLOOKUP(TB_INTEGRADA[[#This Row],[Nº SS]],'CONTROLE CRONOG'!B:B,'CONTROLE CRONOG'!V:V,"",0,1)))))) -> APROVADO | V24: 46052 | W24: 46052 | X24: =IFERROR(TB_INTEGRADA[[#This Row],[TÉRM. TD]]-TB_INTEGRADA[[#This Row],[TÉRMINO LB]],0) -> 0 | Y24: 1 | Z24: 1 | AA24: 0 | AB24: =IFERROR(TB_INTEGRADA[[#This Row],[REAL (%)]]-TB_INTEGRADA[[#This Row],[PREV (%)]],0) -> 0 | AC24: 0 | AD24: 0 | AF24: =IF(TB_INTEGRADA[[#This Row],[TOMADOR]]="EDIVIT",TB_INTEGRADA[[#This Row],[ORÇ DIG]]*1.38,IF(TB_INTEGRADA[[#This Row],[TOMADOR]]="UTGC",TB_INTEGRADA[[#This Row],[ORÇ DIG]]*1.47,IF(TB_INTEGRADA[[#This Row],[TOMADOR]]="TIMS",TB_INTEGRADA[[#This Row],[ORÇ DIG]]*1.34,IF(TB_INTEGRADA[[#This Row],[TOMADOR]]="UTGSUL",TB_INTEGRADA[[#This Row],[ORÇ DIG]]*1.37,IF(TB_INTEGRADA[[#This Row],[TOMADOR]]="REGAP",TB_INTEGRADA[[#This Row],[ORÇ DIG]]*1.36,IF(TB_INTEGRADA[[#This Row],[TOMADOR]]="UTEIBI",TB_INTEGRADA[[#This Row],[ORÇ DIG]]*1.5,"S/TOMADOR")))))) -> 0 | AH24: =SUMIFS(Tb_HhPLAN[Hh DISC],Tb_HhPLAN[SS],TB_INTEGRADA[[#This Row],[Nº SS]],Tb_HhPLAN[DISCIPLINA],"MEC") -> 0 | AI24: =SUMIFS(Hh_EXE_TOTAL[Hh],Hh_EXE_TOTAL[Nº SS],TB_INTEGRADA[[#This Row],[Nº SS]],Hh_EXE_TOTAL[DISCIPLINA],"MEC") -> 0 | AJ24: =IF(TB_INTEGRADA[[#This Row],[TOMADOR]]="EDIVIT",TB_INTEGRADA[[#This Row],[ORÇ DIG1]]*1.38,IF(TB_INTEGRADA[[#This Row],[TOMADOR]]="UTGC",TB_INTEGRADA[[#This Row],[ORÇ DIG1]]*1.47,IF(TB_INTEGRADA[[#This Row],[TOMADOR]]="TIMS",TB_INTEGRADA[[#This Row],[ORÇ DIG1]]*1.34,IF(TB_INTEGRADA[[#This Row],[TOMADOR]]="UTGSUL",TB_INTEGRADA[[#This Row],[ORÇ DIG1]]*1.37,IF(TB_INTEGRADA[[#This Row],[TOMADOR]]="REGAP",TB_INTEGRADA[[#This Row],[ORÇ DIG1]]*1.36,IF(TB_INTEGRADA[[#This Row],[TOMADOR]]="UTEIBI",TB_INTEGRADA[[#This Row],[ORÇ DIG1]]*1.5,"S/TOMADOR")))))) -> 0 | AL24: =SUMIFS(Tb_HhPLAN[Hh DISC],Tb_HhPLAN[SS],TB_INTEGRADA[[#This Row],[Nº SS]],Tb_HhPLAN[DISCIPLINA],"CIVIL") -> 0 | AM24: =SUMIFS(Hh_EXE_TOTAL[Hh],Hh_EXE_TOTAL[Nº SS],TB_INTEGRADA[[#This Row],[Nº SS]],Hh_EXE_TOTAL[DISCIPLINA],"CIVIL") -> 0 | AN24: =IF(TB_INTEGRADA[[#This Row],[TOMADOR]]="EDIVIT",TB_INTEGRADA[[#This Row],[ORÇ DIG2]]*1.38,IF(TB_INTEGRADA[[#This Row],[TOMADOR]]="UTGC",TB_INTEGRADA[[#This Row],[ORÇ DIG2]]*1.47,IF(TB_INTEGRADA[[#This Row],[TOMADOR]]="TIMS",TB_INTEGRADA[[#This Row],[ORÇ DIG2]]*1.34,IF(TB_INTEGRADA[[#This Row],[TOMADOR]]="UTGSUL",TB_INTEGRADA[[#This Row],[ORÇ DIG2]]*1.37,IF(TB_INTEGRADA[[#This Row],[TOMADOR]]="REGAP",TB_INTEGRADA[[#This Row],[ORÇ DIG2]]*1.36,IF(TB_INTEGRADA[[#This Row],[TOMADOR]]="UTEIBI",TB_INTEGRADA[[#This Row],[ORÇ DIG2]]*1.5,"S/TOMADOR")))))) -> 0 | AP24: =SUMIFS(Tb_HhPLAN[Hh DISC],Tb_HhPLAN[SS],TB_INTEGRADA[[#This Row],[Nº SS]],Tb_HhPLAN[DISCIPLINA],"ELÉT") -> 0 | AQ24: =SUMIFS(Hh_EXE_TOTAL[Hh],Hh_EXE_TOTAL[Nº SS],TB_INTEGRADA[[#This Row],[Nº SS]],Hh_EXE_TOTAL[DISCIPLINA],"ELÉT") -> 0 | AR24: =IF(TB_INTEGRADA[[#This Row],[TOMADOR]]="EDIVIT",TB_INTEGRADA[[#This Row],[ORÇ DIG3]]*1.38,IF(TB_INTEGRADA[[#This Row],[TOMADOR]]="UTGC",TB_INTEGRADA[[#This Row],[ORÇ DIG3]]*1.47,IF(TB_INTEGRADA[[#This Row],[TOMADOR]]="TIMS",TB_INTEGRADA[[#This Row],[ORÇ DIG3]]*1.34,IF(TB_INTEGRADA[[#This Row],[TOMADOR]]="UTGSUL",TB_INTEGRADA[[#This Row],[ORÇ DIG3]]*1.37,IF(TB_INTEGRADA[[#This Row],[TOMADOR]]="REGAP",TB_INTEGRADA[[#This Row],[ORÇ DIG3]]*1.36,IF(TB_INTEGRADA[[#This Row],[TOMADOR]]="UTEIBI",TB_INTEGRADA[[#This Row],[ORÇ DIG3]]*1.5,"S/TOMADOR")))))) -> 0 | AT24: =SUMIFS(Tb_HhPLAN[Hh DISC],Tb_HhPLAN[SS],TB_INTEGRADA[[#This Row],[Nº SS]],Tb_HhPLAN[DISCIPLINA],"PINT") -> 0 | AU24: =SUMIFS(Hh_EXE_TOTAL[Hh],Hh_EXE_TOTAL[Nº SS],TB_INTEGRADA[[#This Row],[Nº SS]],Hh_EXE_TOTAL[DISCIPLINA],"PINT") -> 0 | AV24: =TB_INTEGRADA[[#This Row],[ORÇADO]]+TB_INTEGRADA[[#This Row],[ORÇADO1]]+TB_INTEGRADA[[#This Row],[ORÇADO2]]+TB_INTEGRADA[[#This Row],[ORÇADO3]] -> 0 | AW24: =TB_INTEGRADA[[#This Row],[PLANEJ]]+TB_INTEGRADA[[#This Row],[PLANEJ1]]+TB_INTEGRADA[[#This Row],[PLANEJ2]]+TB_INTEGRADA[[#This Row],[PLANEJ3]] -> 0 | AX24: =TB_INTEGRADA[[#This Row],[REALIZ]]+TB_INTEGRADA[[#This Row],[REALIZ1]]+TB_INTEGRADA[[#This Row],[REALIZ2]]+TB_INTEGRADA[[#This Row],[REALIZ3]] -> 0 | AY24: =IFERROR(TB_INTEGRADA[[#This Row],[REALIZ4]]/TB_INTEGRADA[[#This Row],[ORÇADO4]],"") | AZ24: =_xlfn.XLOOKUP(TB_INTEGRADA[[#This Row],[Nº SS]],'CONTROLE EC'!B:B,'CONTROLE EC'!W:W,"",0,1) -> 9890.636 | BA24: =_xlfn.XLOOKUP(TB_INTEGRADA[[#This Row],[Nº SS]],'CONTROLE EC'!B:B,'CONTROLE EC'!X:X,"",0,1) -> 9890.636 | BB24: =_xlfn.XLOOKUP(TB_INTEGRADA[[#This Row],[Nº SS]],'CONTROLE EC'!B:B,'CONTROLE EC'!Y:Y,"",0,1) -> 0
A25: =IF(COUNTIFS($B$5:B25,TB_INTEGRADA[[#This Row],[Nº SS]])<>1,"",COUNTIFS($B$5:B25,TB_INTEGRADA[[#This Row],[Nº SS]])) -> 1 | B25: SS-21/2025 | C25: =_xlfn.XLOOKUP(TB_INTEGRADA[[#This Row],[Nº SS]],'CONTROLE EC'!B:B,'CONTROLE EC'!C:C,"",0,1) -> 23-0838-ES - ADEQUAÇÃO DA ILUMINAÇÃO VIÁRIA | D25: =_xlfn.XLOOKUP(TB_INTEGRADA[[#This Row],[Nº SS]],'CONTROLE CRONOG'!B:B,'CONTROLE CRONOG'!D:D,"",0,1) -> SERVIÇO | E25: =_xlfn.XLOOKUP(TB_INTEGRADA[[#This Row],[Nº SS]],'CONTROLE EC'!B:B,'CONTROLE EC'!E:E,"",0,1) -> UTGC | F25: =_xlfn.XLOOKUP(TB_INTEGRADA[[#This Row],[Nº SS]],'CONTROLE EC'!B:B,'CONTROLE EC'!F:F,"",0,1) -> CANCELADA | G25: =_xlfn.XLOOKUP(TB_INTEGRADA[[#This Row],[Nº SS]],'CONTROLE EC'!B:B,'CONTROLE EC'!R:R,"",0,1) -> REV.00 | H25: =IF(TB_INTEGRADA[[#This Row],[REVISÃO (EC)]]="","",_xlfn.XLOOKUP(TB_INTEGRADA[[#This Row],[Nº SS]],'CONTROLE EC'!B:B,'CONTROLE EC'!S:S,"",0,1)) -> 45986 | I25: =IF(TB_INTEGRADA[[#This Row],[REVISÃO (EC)]]="","",_xlfn.XLOOKUP(TB_INTEGRADA[[#This Row],[Nº SS]],'CONTROLE EC'!B:B,'CONTROLE EC'!U:U,"",0,1)) -> 0 | J25: {=IF(TB_INTEGRADA[[#This Row],[DATA ENVIO. (EC)]]=IFERROR(INDEX('CONTROLE EC'!G25:Q25,MATCH(2,1/('CONTROLE EC'!G25:Q25<>""))),""),"",IFERROR(INDEX('CONTROLE EC'!G25:Q25,MATCH(2,1/('CONTROLE EC'!G25:Q25<>""))),""))} | K25: =IF(TB_INTEGRADA[[#This Row],[STATUS DEMANDA]]="NÃO EMITIDA SAMC","S/ EMISSÃO",_xlfn.XLOOKUP(TB_INTEGRADA[[#This Row],[Nº SS]],'CONTROLE EC'!B:B,'CONTROLE EC'!T:T,"",0,-1)) -> CANCELADA | L25: =IF(TB_INTEGRADA[[#This Row],[STATUS DEMANDA]]="NÃO EMITIDA SAMC","S/ EMISSÃO",IF(TB_INTEGRADA[[#This Row],[STATUS DEMANDA]]="ON HOLD","ON HOLD",IF(TB_INTEGRADA[[#This Row],[STATUS DEMANDA]]="CANCELADA","CANCELADA",IF(TB_INTEGRADA[[#This Row],[DATA APROV. (EC)]]=0,"FISCALIZ.",IF(TB_INTEGRADA[[#This Row],[DATA APROV. (EC)]]="","PEND. FISCALIZ.",IF(TB_INTEGRADA[[#This Row],[DATA APROV. (EC)]]="N/A","APROVADO",IF(TB_INTEGRADA[[#This Row],[REVISÃO (EC)]]="","",_xlfn.XLOOKUP(TB_INTEGRADA[[#This Row],[Nº SS]],'CONTROLE EC'!B:B,'CONTROLE EC'!V:V,"",0,1)))))))) -> CANCELADA | M25: {=IFERROR(_xlfn.IFS(TB_INTEGRADA[[#This Row],[STATUS DEMANDA]]="CANCELADA",0,TB_INTEGRADA[[#This Row],[DATA APROV. (EC)]]="",TODAY()-TB_INTEGRADA[[#This Row],[DATA ENVIO. (EC)]],TB_INTEGRADA[[#This Row],[DATA APROV. (EC)]]>=TB_INTEGRADA[[#This Row],[DATA ENVIO. (EC)]],0,TB_INTEGRADA[[#This Row],[DATA ENVIO. (EC)]]="",0,TB_INTEGRADA[[#This Row],[DATA ENVIO. (EC)]]>TB_INTEGRADA[[#This Row],[DATA APROV. (EC)]],TODAY()-TB_INTEGRADA[[#This Row],[DATA ENVIO. (EC)]]),"")} -> 0 | N25: =IF(TB_INTEGRADA[[#This Row],[STATUS DEMANDA]]="NÃO EMITIDA SAMC","S/ EMISSÃO",IF(TB_INTEGRADA[[#This Row],[STATUS DEMANDA]]="ON HOLD","ON HOLD",IF(F25="CANCELADA","CANCELADA",IF(L25="REPROVADO","EM PLANEJ.",IF(K25<>"ENTREGUE","EM PLANEJ.",IF(H25="","EM PLANEJ.",IF(I25="","FISCALIZ.",IF(M25<0,"EM PLANEJ.",IF(TB_INTEGRADA[[#This Row],[DATA APROV. (EC)]]>=TB_INTEGRADA[[#This Row],[DATA ENVIO. (EC)]],"RETORNO OK","FISCALIZ."))))))))) -> CANCELADA | O25: =_xlfn.XLOOKUP(TB_INTEGRADA[[#This Row],[Nº SS]],'CONTROLE CRONOG'!B:B,'CONTROLE CRONOG'!R:R,"",0,1) -> REV.00 | P25: =IF(TB_INTEGRADA[[#This Row],[REVISÃO (CR)]]="","",_xlfn.XLOOKUP(TB_INTEGRADA[[#This Row],[Nº SS]],'CONTROLE CRONOG'!B:B,'CONTROLE CRONOG'!S:S,"",0,1)) -> 45986 | Q25: =IF(TB_INTEGRADA[[#This Row],[REVISÃO (CR)]]="","",_xlfn.XLOOKUP(TB_INTEGRADA[[#This Row],[Nº SS]],'CONTROLE CRONOG'!B:B,'CONTROLE CRONOG'!U:U,"",0,1)) -> 0 | R25: {=IF(TB_INTEGRADA[[#This Row],[DATA ENVIO. (CR)]]=IFERROR(INDEX('CONTROLE CRONOG'!G25:Q25,MATCH(2,1/('CONTROLE CRONOG'!G25:Q25<>""))),""),"",IFERROR(INDEX('CONTROLE CRONOG'!G25:Q25,MATCH(2,1/('CONTROLE CRONOG'!G25:Q25<>""))),""))} | S25: =_xlfn.XLOOKUP(TB_INTEGRADA[[#This Row],[Nº SS]],'CONTROLE CRONOG'!B:B,'CONTROLE CRONOG'!T:T,"",0,-1) -> CANCELADA | T25: =IF(TB_INTEGRADA[[#This Row],[STATUS DEMANDA]]="ON HOLD","ON HOLD",IF(TB_INTEGRADA[[#This Row],[STATUS DEMANDA]]="CANCELADA","CANCELADA",IF(TB_INTEGRADA[[#This Row],[DATA APROV. (CR)]]=0,"FISCALIZ.",IF(TB_INTEGRADA[[#This Row],[DATA APROV. (CR)]]="N/A","APROVADO",IF(TB_INTEGRADA[[#This Row],[REVISÃO (CR)]]="","",_xlfn.XLOOKUP(TB_INTEGRADA[[#This Row],[Nº SS]],'CONTROLE CRONOG'!B:B,'CONTROLE CRONOG'!V:V,"",0,1)))))) -> CANCELADA | X25: =IFERROR(TB_INTEGRADA[[#This Row],[TÉRM. TD]]-TB_INTEGRADA[[#This Row],[TÉRMINO LB]],0) -> 0 | AA25: 0 | AB25: =IFERROR(TB_INTEGRADA[[#This Row],[REAL (%)]]-TB_INTEGRADA[[#This Row],[PREV (%)]],0) -> 0 | AF25: =IF(TB_INTEGRADA[[#This Row],[TOMADOR]]="EDIVIT",TB_INTEGRADA[[#This Row],[ORÇ DIG]]*1.38,IF(TB_INTEGRADA[[#This Row],[TOMADOR]]="UTGC",TB_INTEGRADA[[#This Row],[ORÇ DIG]]*1.47,IF(TB_INTEGRADA[[#This Row],[TOMADOR]]="TIMS",TB_INTEGRADA[[#This Row],[ORÇ DIG]]*1.34,IF(TB_INTEGRADA[[#This Row],[TOMADOR]]="UTGSUL",TB_INTEGRADA[[#This Row],[ORÇ DIG]]*1.37,IF(TB_INTEGRADA[[#This Row],[TOMADOR]]="REGAP",TB_INTEGRADA[[#This Row],[ORÇ DIG]]*1.36,IF(TB_INTEGRADA[[#This Row],[TOMADOR]]="UTEIBI",TB_INTEGRADA[[#This Row],[ORÇ DIG]]*1.5,"S/TOMADOR")))))) -> 0 | AH25: =SUMIFS(Tb_HhPLAN[Hh DISC],Tb_HhPLAN[SS],TB_INTEGRADA[[#This Row],[Nº SS]],Tb_HhPLAN[DISCIPLINA],"MEC") -> 0 | AI25: =SUMIFS(Hh_EXE_TOTAL[Hh],Hh_EXE_TOTAL[Nº SS],TB_INTEGRADA[[#This Row],[Nº SS]],Hh_EXE_TOTAL[DISCIPLINA],"MEC") -> 0 | AJ25: =IF(TB_INTEGRADA[[#This Row],[TOMADOR]]="EDIVIT",TB_INTEGRADA[[#This Row],[ORÇ DIG1]]*1.38,IF(TB_INTEGRADA[[#This Row],[TOMADOR]]="UTGC",TB_INTEGRADA[[#This Row],[ORÇ DIG1]]*1.47,IF(TB_INTEGRADA[[#This Row],[TOMADOR]]="TIMS",TB_INTEGRADA[[#This Row],[ORÇ DIG1]]*1.34,IF(TB_INTEGRADA[[#This Row],[TOMADOR]]="UTGSUL",TB_INTEGRADA[[#This Row],[ORÇ DIG1]]*1.37,IF(TB_INTEGRADA[[#This Row],[TOMADOR]]="REGAP",TB_INTEGRADA[[#This Row],[ORÇ DIG1]]*1.36,IF(TB_INTEGRADA[[#This Row],[TOMADOR]]="UTEIBI",TB_INTEGRADA[[#This Row],[ORÇ DIG1]]*1.5,"S/TOMADOR")))))) -> 0 | AL25: =SUMIFS(Tb_HhPLAN[Hh DISC],Tb_HhPLAN[SS],TB_INTEGRADA[[#This Row],[Nº SS]],Tb_HhPLAN[DISCIPLINA],"CIVIL") -> 0 | AM25: =SUMIFS(Hh_EXE_TOTAL[Hh],Hh_EXE_TOTAL[Nº SS],TB_INTEGRADA[[#This Row],[Nº SS]],Hh_EXE_TOTAL[DISCIPLINA],"CIVIL") -> 0 | AN25: =IF(TB_INTEGRADA[[#This Row],[TOMADOR]]="EDIVIT",TB_INTEGRADA[[#This Row],[ORÇ DIG2]]*1.38,IF(TB_INTEGRADA[[#This Row],[TOMADOR]]="UTGC",TB_INTEGRADA[[#This Row],[ORÇ DIG2]]*1.47,IF(TB_INTEGRADA[[#This Row],[TOMADOR]]="TIMS",TB_INTEGRADA[[#This Row],[ORÇ DIG2]]*1.34,IF(TB_INTEGRADA[[#This Row],[TOMADOR]]="UTGSUL",TB_INTEGRADA[[#This Row],[ORÇ DIG2]]*1.37,IF(TB_INTEGRADA[[#This Row],[TOMADOR]]="REGAP",TB_INTEGRADA[[#This Row],[ORÇ DIG2]]*1.36,IF(TB_INTEGRADA[[#This Row],[TOMADOR]]="UTEIBI",TB_INTEGRADA[[#This Row],[ORÇ DIG2]]*1.5,"S/TOMADOR")))))) -> 0 | AP25: =SUMIFS(Tb_HhPLAN[Hh DISC],Tb_HhPLAN[SS],TB_INTEGRADA[[#This Row],[Nº SS]],Tb_HhPLAN[DISCIPLINA],"ELÉT") -> 0 | AQ25: =SUMIFS(Hh_EXE_TOTAL[Hh],Hh_EXE_TOTAL[Nº SS],TB_INTEGRADA[[#This Row],[Nº SS]],Hh_EXE_TOTAL[DISCIPLINA],"ELÉT") -> 0 | AR25: =IF(TB_INTEGRADA[[#This Row],[TOMADOR]]="EDIVIT",TB_INTEGRADA[[#This Row],[ORÇ DIG3]]*1.38,IF(TB_INTEGRADA[[#This Row],[TOMADOR]]="UTGC",TB_INTEGRADA[[#This Row],[ORÇ DIG3]]*1.47,IF(TB_INTEGRADA[[#This Row],[TOMADOR]]="TIMS",TB_INTEGRADA[[#This Row],[ORÇ DIG3]]*1.34,IF(TB_INTEGRADA[[#This Row],[TOMADOR]]="UTGSUL",TB_INTEGRADA[[#This Row],[ORÇ DIG3]]*1.37,IF(TB_INTEGRADA[[#This Row],[TOMADOR]]="REGAP",TB_INTEGRADA[[#This Row],[ORÇ DIG3]]*1.36,IF(TB_INTEGRADA[[#This Row],[TOMADOR]]="UTEIBI",TB_INTEGRADA[[#This Row],[ORÇ DIG3]]*1.5,"S/TOMADOR")))))) -> 0 | AT25: =SUMIFS(Tb_HhPLAN[Hh DISC],Tb_HhPLAN[SS],TB_INTEGRADA[[#This Row],[Nº SS]],Tb_HhPLAN[DISCIPLINA],"PINT") -> 0 | AU25: =SUMIFS(Hh_EXE_TOTAL[Hh],Hh_EXE_TOTAL[Nº SS],TB_INTEGRADA[[#This Row],[Nº SS]],Hh_EXE_TOTAL[DISCIPLINA],"PINT") -> 0 | AV25: =TB_INTEGRADA[[#This Row],[ORÇADO]]+TB_INTEGRADA[[#This Row],[ORÇADO1]]+TB_INTEGRADA[[#This Row],[ORÇADO2]]+TB_INTEGRADA[[#This Row],[ORÇADO3]] -> 0 | AW25: =TB_INTEGRADA[[#This Row],[PLANEJ]]+TB_INTEGRADA[[#This Row],[PLANEJ1]]+TB_INTEGRADA[[#This Row],[PLANEJ2]]+TB_INTEGRADA[[#This Row],[PLANEJ3]] -> 0 | AX25: =TB_INTEGRADA[[#This Row],[REALIZ]]+TB_INTEGRADA[[#This Row],[REALIZ1]]+TB_INTEGRADA[[#This Row],[REALIZ2]]+TB_INTEGRADA[[#This Row],[REALIZ3]] -> 0 | AY25: =IFERROR(TB_INTEGRADA[[#This Row],[REALIZ4]]/TB_INTEGRADA[[#This Row],[ORÇADO4]],"") | AZ25: =_xlfn.XLOOKUP(TB_INTEGRADA[[#This Row],[Nº SS]],'CONTROLE EC'!B:B,'CONTROLE EC'!W:W,"",0,1) -> 0 | BA25: =_xlfn.XLOOKUP(TB_INTEGRADA[[#This Row],[Nº SS]],'CONTROLE EC'!B:B,'CONTROLE EC'!X:X,"",0,1) -> 0 | BB25: =_xlfn.XLOOKUP(TB_INTEGRADA[[#This Row],[Nº SS]],'CONTROLE EC'!B:B,'CONTROLE EC'!Y:Y,"",0,1) -> 0
A26: =IF(COUNTIFS($B$5:B26,TB_INTEGRADA[[#This Row],[Nº SS]])<>1,"",COUNTIFS($B$5:B26,TB_INTEGRADA[[#This Row],[Nº SS]])) -> 1 | B26: SS-22/2025 | C26: =_xlfn.XLOOKUP(TB_INTEGRADA[[#This Row],[Nº SS]],'CONTROLE EC'!B:B,'CONTROLE EC'!C:C,"",0,1) -> 24-1106-ES - ADEQUAÇÃO DA SALA DE MONITORAMENTO N1 CISC | D26: =_xlfn.XLOOKUP(TB_INTEGRADA[[#This Row],[Nº SS]],'CONTROLE CRONOG'!B:B,'CONTROLE CRONOG'!D:D,"",0,1) -> SERVIÇO | E26: =_xlfn.XLOOKUP(TB_INTEGRADA[[#This Row],[Nº SS]],'CONTROLE EC'!B:B,'CONTROLE EC'!E:E,"",0,1) -> UTGSUL | F26: =_xlfn.XLOOKUP(TB_INTEGRADA[[#This Row],[Nº SS]],'CONTROLE EC'!B:B,'CONTROLE EC'!F:F,"",0,1) -> CONCLUÍDA | G26: =_xlfn.XLOOKUP(TB_INTEGRADA[[#This Row],[Nº SS]],'CONTROLE EC'!B:B,'CONTROLE EC'!R:R,"",0,1) -> REV.00 | H26: =IF(TB_INTEGRADA[[#This Row],[REVISÃO (EC)]]="","",_xlfn.XLOOKUP(TB_INTEGRADA[[#This Row],[Nº SS]],'CONTROLE EC'!B:B,'CONTROLE EC'!S:S,"",0,1)) -> 45973 | I26: =IF(TB_INTEGRADA[[#This Row],[REVISÃO (EC)]]="","",_xlfn.XLOOKUP(TB_INTEGRADA[[#This Row],[Nº SS]],'CONTROLE EC'!B:B,'CONTROLE EC'!U:U,"",0,1)) -> 45975 | J26: {=IF(TB_INTEGRADA[[#This Row],[DATA ENVIO. (EC)]]=IFERROR(INDEX('CONTROLE EC'!G26:Q26,MATCH(2,1/('CONTROLE EC'!G26:Q26<>""))),""),"",IFERROR(INDEX('CONTROLE EC'!G26:Q26,MATCH(2,1/('CONTROLE EC'!G26:Q26<>""))),""))} | K26: =IF(TB_INTEGRADA[[#This Row],[STATUS DEMANDA]]="NÃO EMITIDA SAMC","S/ EMISSÃO",_xlfn.XLOOKUP(TB_INTEGRADA[[#This Row],[Nº SS]],'CONTROLE EC'!B:B,'CONTROLE EC'!T:T,"",0,-1)) -> ENTREGUE | L26: =IF(TB_INTEGRADA[[#This Row],[STATUS DEMANDA]]="NÃO EMITIDA SAMC","S/ EMISSÃO",IF(TB_INTEGRADA[[#This Row],[STATUS DEMANDA]]="ON HOLD","ON HOLD",IF(TB_INTEGRADA[[#This Row],[STATUS DEMANDA]]="CANCELADA","CANCELADA",IF(TB_INTEGRADA[[#This Row],[DATA APROV. (EC)]]=0,"FISCALIZ.",IF(TB_INTEGRADA[[#This Row],[DATA APROV. (EC)]]="","PEND. FISCALIZ.",IF(TB_INTEGRADA[[#This Row],[DATA APROV. (EC)]]="N/A","APROVADO",IF(TB_INTEGRADA[[#This Row],[REVISÃO (EC)]]="","",_xlfn.XLOOKUP(TB_INTEGRADA[[#This Row],[Nº SS]],'CONTROLE EC'!B:B,'CONTROLE EC'!V:V,"",0,1)))))))) -> APROVADO | M26: {=IFERROR(_xlfn.IFS(TB_INTEGRADA[[#This Row],[STATUS DEMANDA]]="CANCELADA",0,TB_INTEGRADA[[#This Row],[DATA APROV. (EC)]]="",TODAY()-TB_INTEGRADA[[#This Row],[DATA ENVIO. (EC)]],TB_INTEGRADA[[#This Row],[DATA APROV. (EC)]]>=TB_INTEGRADA[[#This Row],[DATA ENVIO. (EC)]],0,TB_INTEGRADA[[#This Row],[DATA ENVIO. (EC)]]="",0,TB_INTEGRADA[[#This Row],[DATA ENVIO. (EC)]]>TB_INTEGRADA[[#This Row],[DATA APROV. (EC)]],TODAY()-TB_INTEGRADA[[#This Row],[DATA ENVIO. (EC)]]),"")} -> 0 | N26: =IF(TB_INTEGRADA[[#This Row],[STATUS DEMANDA]]="NÃO EMITIDA SAMC","S/ EMISSÃO",IF(TB_INTEGRADA[[#This Row],[STATUS DEMANDA]]="ON HOLD","ON HOLD",IF(F26="CANCELADA","CANCELADA",IF(L26="REPROVADO","EM PLANEJ.",IF(K26<>"ENTREGUE","EM PLANEJ.",IF(H26="","EM PLANEJ.",IF(I26="","FISCALIZ.",IF(M26<0,"EM PLANEJ.",IF(TB_INTEGRADA[[#This Row],[DATA APROV. (EC)]]>=TB_INTEGRADA[[#This Row],[DATA ENVIO. (EC)]],"RETORNO OK","FISCALIZ."))))))))) -> RETORNO OK | O26: =_xlfn.XLOOKUP(TB_INTEGRADA[[#This Row],[Nº SS]],'CONTROLE CRONOG'!B:B,'CONTROLE CRONOG'!R:R,"",0,1) -> REV.01 | P26: =IF(TB_INTEGRADA[[#This Row],[REVISÃO (CR)]]="","",_xlfn.XLOOKUP(TB_INTEGRADA[[#This Row],[Nº SS]],'CONTROLE CRONOG'!B:B,'CONTROLE CRONOG'!S:S,"",0,1)) -> 46000 | Q26: =IF(TB_INTEGRADA[[#This Row],[REVISÃO (CR)]]="","",_xlfn.XLOOKUP(TB_INTEGRADA[[#This Row],[Nº SS]],'CONTROLE CRONOG'!B:B,'CONTROLE CRONOG'!U:U,"",0,1)) -> 46000 | R26: {=IF(TB_INTEGRADA[[#This Row],[DATA ENVIO. (CR)]]=IFERROR(INDEX('CONTROLE CRONOG'!G26:Q26,MATCH(2,1/('CONTROLE CRONOG'!G26:Q26<>""))),""),"",IFERROR(INDEX('CONTROLE CRONOG'!G26:Q26,MATCH(2,1/('CONTROLE CRONOG'!G26:Q26<>""))),""))} | S26: =_xlfn.XLOOKUP(TB_INTEGRADA[[#This Row],[Nº SS]],'CONTROLE CRONOG'!B:B,'CONTROLE CRONOG'!T:T,"",0,-1) -> ENTREGUE | T26: =IF(TB_INTEGRADA[[#This Row],[STATUS DEMANDA]]="ON HOLD","ON HOLD",IF(TB_INTEGRADA[[#This Row],[STATUS DEMANDA]]="CANCELADA","CANCELADA",IF(TB_INTEGRADA[[#This Row],[DATA APROV. (CR)]]=0,"FISCALIZ.",IF(TB_INTEGRADA[[#This Row],[DATA APROV. (CR)]]="N/A","APROVADO",IF(TB_INTEGRADA[[#This Row],[REVISÃO (CR)]]="","",_xlfn.XLOOKUP(TB_INTEGRADA[[#This Row],[Nº SS]],'CONTROLE CRONOG'!B:B,'CONTROLE CRONOG'!V:V,"",0,1)))))) -> APROVADO | V26: 46037 | W26: 46045 | X26: =IFERROR(TB_INTEGRADA[[#This Row],[TÉRM. TD]]-TB_INTEGRADA[[#This Row],[TÉRMINO LB]],0) -> 8 | Y26: 1 | Z26: 1 | AA26: 0 | AB26: =IFERROR(TB_INTEGRADA[[#This Row],[REAL (%)]]-TB_INTEGRADA[[#This Row],[PREV (%)]],0) -> 0 | AC26: 0 | AD26: 0 | AF26: =IF(TB_INTEGRADA[[#This Row],[TOMADOR]]="EDIVIT",TB_INTEGRADA[[#This Row],[ORÇ DIG]]*1.38,IF(TB_INTEGRADA[[#This Row],[TOMADOR]]="UTGC",TB_INTEGRADA[[#This Row],[ORÇ DIG]]*1.47,IF(TB_INTEGRADA[[#This Row],[TOMADOR]]="TIMS",TB_INTEGRADA[[#This Row],[ORÇ DIG]]*1.34,IF(TB_INTEGRADA[[#This Row],[TOMADOR]]="UTGSUL",TB_INTEGRADA[[#This Row],[ORÇ DIG]]*1.37,IF(TB_INTEGRADA[[#This Row],[TOMADOR]]="REGAP",TB_INTEGRADA[[#This Row],[ORÇ DIG]]*1.36,IF(TB_INTEGRADA[[#This Row],[TOMADOR]]="UTEIBI",TB_INTEGRADA[[#This Row],[ORÇ DIG]]*1.5,"S/TOMADOR")))))) -> 0 | AH26: =SUMIFS(Tb_HhPLAN[Hh DISC],Tb_HhPLAN[SS],TB_INTEGRADA[[#This Row],[Nº SS]],Tb_HhPLAN[DISCIPLINA],"MEC") -> 0 | AI26: =SUMIFS(Hh_EXE_TOTAL[Hh],Hh_EXE_TOTAL[Nº SS],TB_INTEGRADA[[#This Row],[Nº SS]],Hh_EXE_TOTAL[DISCIPLINA],"MEC") -> 0 | AJ26: =IF(TB_INTEGRADA[[#This Row],[TOMADOR]]="EDIVIT",TB_INTEGRADA[[#This Row],[ORÇ DIG1]]*1.38,IF(TB_INTEGRADA[[#This Row],[TOMADOR]]="UTGC",TB_INTEGRADA[[#This Row],[ORÇ DIG1]]*1.47,IF(TB_INTEGRADA[[#This Row],[TOMADOR]]="TIMS",TB_INTEGRADA[[#This Row],[ORÇ DIG1]]*1.34,IF(TB_INTEGRADA[[#This Row],[TOMADOR]]="UTGSUL",TB_INTEGRADA[[#This Row],[ORÇ DIG1]]*1.37,IF(TB_INTEGRADA[[#This Row],[TOMADOR]]="REGAP",TB_INTEGRADA[[#This Row],[ORÇ DIG1]]*1.36,IF(TB_INTEGRADA[[#This Row],[TOMADOR]]="UTEIBI",TB_INTEGRADA[[#This Row],[ORÇ DIG1]]*1.5,"S/TOMADOR")))))) -> 117.2583 | AK26: 85.59 | AL26: =SUMIFS(Tb_HhPLAN[Hh DISC],Tb_HhPLAN[SS],TB_INTEGRADA[[#This Row],[Nº SS]],Tb_HhPLAN[DISCIPLINA],"CIVIL") -> 108.79295 | AM26: =SUMIFS(Hh_EXE_TOTAL[Hh],Hh_EXE_TOTAL[Nº SS],TB_INTEGRADA[[#This Row],[Nº SS]],Hh_EXE_TOTAL[DISCIPLINA],"CIVIL") -> 816 | AN26: =IF(TB_INTEGRADA[[#This Row],[TOMADOR]]="EDIVIT",TB_INTEGRADA[[#This Row],[ORÇ DIG2]]*1.38,IF(TB_INTEGRADA[[#This Row],[TOMADOR]]="UTGC",TB_INTEGRADA[[#This Row],[ORÇ DIG2]]*1.47,IF(TB_INTEGRADA[[#This Row],[TOMADOR]]="TIMS",TB_INTEGRADA[[#This Row],[ORÇ DIG2]]*1.34,IF(TB_INTEGRADA[[#This Row],[TOMADOR]]="UTGSUL",TB_INTEGRADA[[#This Row],[ORÇ DIG2]]*1.37,IF(TB_INTEGRADA[[#This Row],[TOMADOR]]="REGAP",TB_INTEGRADA[[#This Row],[ORÇ DIG2]]*1.36,IF(TB_INTEGRADA[[#This Row],[TOMADOR]]="UTEIBI",TB_INTEGRADA[[#This Row],[ORÇ DIG2]]*1.5,"S/TOMADOR")))))) -> 242.1749 | AO26: 176.77 | AP26: =SUMIFS(Tb_HhPLAN[Hh DISC],Tb_HhPLAN[SS],TB_INTEGRADA[[#This Row],[Nº SS]],Tb_HhPLAN[DISCIPLINA],"ELÉT") -> 87.207048 | AQ26: =SUMIFS(Hh_EXE_TOTAL[Hh],Hh_EXE_TOTAL[Nº SS],TB_INTEGRADA[[#This Row],[Nº SS]],Hh_EXE_TOTAL[DISCIPLINA],"ELÉT") -> 96 | AR26: =IF(TB_INTEGRADA[[#This Row],[TOMADOR]]="EDIVIT",TB_INTEGRADA[[#This Row],[ORÇ DIG3]]*1.38,IF(TB_INTEGRADA[[#This Row],[TOMADOR]]="UTGC",TB_INTEGRADA[[#This Row],[ORÇ DIG3]]*1.47,IF(TB_INTEGRADA[[#This Row],[TOMADOR]]="TIMS",TB_INTEGRADA[[#This Row],[ORÇ DIG3]]*1.34,IF(TB_INTEGRADA[[#This Row],[TOMADOR]]="UTGSUL",TB_INTEGRADA[[#This Row],[ORÇ DIG3]]*1.37,IF(TB_INTEGRADA[[#This Row],[TOMADOR]]="REGAP",TB_INTEGRADA[[#This Row],[ORÇ DIG3]]*1.36,IF(TB_INTEGRADA[[#This Row],[TOMADOR]]="UTEIBI",TB_INTEGRADA[[#This Row],[ORÇ DIG3]]*1.5,"S/TOMADOR")))))) -> 137.7535 | AS26: 100.55 | AT26: =SUMIFS(Tb_HhPLAN[Hh DISC],Tb_HhPLAN[SS],TB_INTEGRADA[[#This Row],[Nº SS]],Tb_HhPLAN[DISCIPLINA],"PINT") -> 0 | AU26: =SUMIFS(Hh_EXE_TOTAL[Hh],Hh_EXE_TOTAL[Nº SS],TB_INTEGRADA[[#This Row],[Nº SS]],Hh_EXE_TOTAL[DISCIPLINA],"PINT") -> 0 | AV26: =TB_INTEGRADA[[#This Row],[ORÇADO]]+TB_INTEGRADA[[#This Row],[ORÇADO1]]+TB_INTEGRADA[[#This Row],[ORÇADO2]]+TB_INTEGRADA[[#This Row],[ORÇADO3]] -> 497.1867 | AW26: =TB_INTEGRADA[[#This Row],[PLANEJ]]+TB_INTEGRADA[[#This Row],[PLANEJ1]]+TB_INTEGRADA[[#This Row],[PLANEJ2]]+TB_INTEGRADA[[#This Row],[PLANEJ3]] -> 196 | AX26: =TB_INTEGRADA[[#This Row],[REALIZ]]+TB_INTEGRADA[[#This Row],[REALIZ1]]+TB_INTEGRADA[[#This Row],[REALIZ2]]+TB_INTEGRADA[[#This Row],[REALIZ3]] -> 912 | AY26: =IFERROR(TB_INTEGRADA[[#This Row],[REALIZ4]]/TB_INTEGRADA[[#This Row],[ORÇADO4]],"") -> 1.834321 | AZ26: =_xlfn.XLOOKUP(TB_INTEGRADA[[#This Row],[Nº SS]],'CONTROLE EC'!B:B,'CONTROLE EC'!W:W,"",0,1) -> 117731.58 | BA26: =_xlfn.XLOOKUP(TB_INTEGRADA[[#This Row],[Nº SS]],'CONTROLE EC'!B:B,'CONTROLE EC'!X:X,"",0,1) -> 117731.58 | BB26: =_xlfn.XLOOKUP(TB_INTEGRADA[[#This Row],[Nº SS]],'CONTROLE EC'!B:B,'CONTROLE EC'!Y:Y,"",0,1) -> 0
A27: =IF(COUNTIFS($B$5:B27,TB_INTEGRADA[[#This Row],[Nº SS]])<>1,"",COUNTIFS($B$5:B27,TB_INTEGRADA[[#This Row],[Nº SS]])) -> 1 | B27: SS-23/2025 | C27: =_xlfn.XLOOKUP(TB_INTEGRADA[[#This Row],[Nº SS]],'CONTROLE EC'!B:B,'CONTROLE EC'!C:C,"",0,1) -> 24-0087-ES - REMOÇÃO DAS TELHAS DE PROTEÇÃO DOS PAINÉIS DO K21 E K40 | D27: =_xlfn.XLOOKUP(TB_INTEGRADA[[#This Row],[Nº SS]],'CONTROLE CRONOG'!B:B,'CONTROLE CRONOG'!D:D,"",0,1) -> SERVIÇO | E27: =_xlfn.XLOOKUP(TB_INTEGRADA[[#This Row],[Nº SS]],'CONTROLE EC'!B:B,'CONTROLE EC'!E:E,"",0,1) -> UTGC | F27: =_xlfn.XLOOKUP(TB_INTEGRADA[[#This Row],[Nº SS]],'CONTROLE EC'!B:B,'CONTROLE EC'!F:F,"",0,1) -> CONCLUÍDA | G27: =_xlfn.XLOOKUP(TB_INTEGRADA[[#This Row],[Nº SS]],'CONTROLE EC'!B:B,'CONTROLE EC'!R:R,"",0,1) -> REV.02 | H27: =IF(TB_INTEGRADA[[#This Row],[REVISÃO (EC)]]="","",_xlfn.XLOOKUP(TB_INTEGRADA[[#This Row],[Nº SS]],'CONTROLE EC'!B:B,'CONTROLE EC'!S:S,"",0,1)) -> 45972 | I27: =IF(TB_INTEGRADA[[#This Row],[REVISÃO (EC)]]="","",_xlfn.XLOOKUP(TB_INTEGRADA[[#This Row],[Nº SS]],'CONTROLE EC'!B:B,'CONTROLE EC'!U:U,"",0,1)) -> 45972 | J27: {=IF(TB_INTEGRADA[[#This Row],[DATA ENVIO. (EC)]]=IFERROR(INDEX('CONTROLE EC'!G27:Q27,MATCH(2,1/('CONTROLE EC'!G27:Q27<>""))),""),"",IFERROR(INDEX('CONTROLE EC'!G27:Q27,MATCH(2,1/('CONTROLE EC'!G27:Q27<>""))),""))} | K27: =IF(TB_INTEGRADA[[#This Row],[STATUS DEMANDA]]="NÃO EMITIDA SAMC","S/ EMISSÃO",_xlfn.XLOOKUP(TB_INTEGRADA[[#This Row],[Nº SS]],'CONTROLE EC'!B:B,'CONTROLE EC'!T:T,"",0,-1)) -> ENTREGUE | L27: =IF(TB_INTEGRADA[[#This Row],[STATUS DEMANDA]]="NÃO EMITIDA SAMC","S/ EMISSÃO",IF(TB_INTEGRADA[[#This Row],[STATUS DEMANDA]]="ON HOLD","ON HOLD",IF(TB_INTEGRADA[[#This Row],[STATUS DEMANDA]]="CANCELADA","CANCELADA",IF(TB_INTEGRADA[[#This Row],[DATA APROV. (EC)]]=0,"FISCALIZ.",IF(TB_INTEGRADA[[#This Row],[DATA APROV. (EC)]]="","PEND. FISCALIZ.",IF(TB_INTEGRADA[[#This Row],[DATA APROV. (EC)]]="N/A","APROVADO",IF(TB_INTEGRADA[[#This Row],[REVISÃO (EC)]]="","",_xlfn.XLOOKUP(TB_INTEGRADA[[#This Row],[Nº SS]],'CONTROLE EC'!B:B,'CONTROLE EC'!V:V,"",0,1)))))))) -> APROVADO | M27: {=IFERROR(_xlfn.IFS(TB_INTEGRADA[[#This Row],[STATUS DEMANDA]]="CANCELADA",0,TB_INTEGRADA[[#This Row],[DATA APROV. (EC)]]="",TODAY()-TB_INTEGRADA[[#This Row],[DATA ENVIO. (EC)]],TB_INTEGRADA[[#This Row],[DATA APROV. (EC)]]>=TB_INTEGRADA[[#This Row],[DATA ENVIO. (EC)]],0,TB_INTEGRADA[[#This Row],[DATA ENVIO. (EC)]]="",0,TB_INTEGRADA[[#This Row],[DATA ENVIO. (EC)]]>TB_INTEGRADA[[#This Row],[DATA APROV. (EC)]],TODAY()-TB_INTEGRADA[[#This Row],[DATA ENVIO. (EC)]]),"")} -> 0 | N27: =IF(TB_INTEGRADA[[#This Row],[STATUS DEMANDA]]="NÃO EMITIDA SAMC","S/ EMISSÃO",IF(TB_INTEGRADA[[#This Row],[STATUS DEMANDA]]="ON HOLD","ON HOLD",IF(F27="CANCELADA","CANCELADA",IF(L27="REPROVADO","EM PLANEJ.",IF(K27<>"ENTREGUE","EM PLANEJ.",IF(H27="","EM PLANEJ.",IF(I27="","FISCALIZ.",IF(M27<0,"EM PLANEJ.",IF(TB_INTEGRADA[[#This Row],[DATA APROV. (EC)]]>=TB_INTEGRADA[[#This Row],[DATA ENVIO. (EC)]],"RETORNO OK","FISCALIZ."))))))))) -> RETORNO OK | O27: =_xlfn.XLOOKUP(TB_INTEGRADA[[#This Row],[Nº SS]],'CONTROLE CRONOG'!B:B,'CONTROLE CRONOG'!R:R,"",0,1) -> REV.00 | P27: =IF(TB_INTEGRADA[[#This Row],[REVISÃO (CR)]]="","",_xlfn.XLOOKUP(TB_INTEGRADA[[#This Row],[Nº SS]],'CONTROLE CRONOG'!B:B,'CONTROLE CRONOG'!S:S,"",0,1)) -> N/A | Q27: =IF(TB_INTEGRADA[[#This Row],[REVISÃO (CR)]]="","",_xlfn.XLOOKUP(TB_INTEGRADA[[#This Row],[Nº SS]],'CONTROLE CRONOG'!B:B,'CONTROLE CRONOG'!U:U,"",0,1)) -> N/A | R27: {=IF(TB_INTEGRADA[[#This Row],[DATA ENVIO. (CR)]]=IFERROR(INDEX('CONTROLE CRONOG'!G27:Q27,MATCH(2,1/('CONTROLE CRONOG'!G27:Q27<>""))),""),"",IFERROR(INDEX('CONTROLE CRONOG'!G27:Q27,MATCH(2,1/('CONTROLE CRONOG'!G27:Q27<>""))),""))} | S27: =_xlfn.XLOOKUP(TB_INTEGRADA[[#This Row],[Nº SS]],'CONTROLE CRONOG'!B:B,'CONTROLE CRONOG'!T:T,"",0,-1) -> ENTREGUE | T27: =IF(TB_INTEGRADA[[#This Row],[STATUS DEMANDA]]="ON HOLD","ON HOLD",IF(TB_INTEGRADA[[#This Row],[STATUS DEMANDA]]="CANCELADA","CANCELADA",IF(TB_INTEGRADA[[#This Row],[DATA APROV. (CR)]]=0,"FISCALIZ.",IF(TB_INTEGRADA[[#This Row],[DATA APROV. (CR)]]="N/A","APROVADO",IF(TB_INTEGRADA[[#This Row],[REVISÃO (CR)]]="","",_xlfn.XLOOKUP(TB_INTEGRADA[[#This Row],[Nº SS]],'CONTROLE CRONOG'!B:B,'CONTROLE CRONOG'!V:V,"",0,1)))))) -> APROVADO | V27: 46003 | W27: 46003 | X27: =IFERROR(TB_INTEGRADA[[#This Row],[TÉRM. TD]]-TB_INTEGRADA[[#This Row],[TÉRMINO LB]],0) -> 0 | Y27: 1 | Z27: 1 | AA27: 0 | AB27: =IFERROR(TB_INTEGRADA[[#This Row],[REAL (%)]]-TB_INTEGRADA[[#This Row],[PREV (%)]],0) -> 0 | AC27: 0 | AD27: 0 | AF27: =IF(TB_INTEGRADA[[#This Row],[TOMADOR]]="EDIVIT",TB_INTEGRADA[[#This Row],[ORÇ DIG]]*1.38,IF(TB_INTEGRADA[[#This Row],[TOMADOR]]="UTGC",TB_INTEGRADA[[#This Row],[ORÇ DIG]]*1.47,IF(TB_INTEGRADA[[#This Row],[TOMADOR]]="TIMS",TB_INTEGRADA[[#This Row],[ORÇ DIG]]*1.34,IF(TB_INTEGRADA[[#This Row],[TOMADOR]]="UTGSUL",TB_INTEGRADA[[#This Row],[ORÇ DIG]]*1.37,IF(TB_INTEGRADA[[#This Row],[TOMADOR]]="REGAP",TB_INTEGRADA[[#This Row],[ORÇ DIG]]*1.36,IF(TB_INTEGRADA[[#This Row],[TOMADOR]]="UTEIBI",TB_INTEGRADA[[#This Row],[ORÇ DIG]]*1.5,"S/TOMADOR")))))) -> 158.9805 | AG27: 108.15 | AH27: =SUMIFS(Tb_HhPLAN[Hh DISC],Tb_HhPLAN[SS],TB_INTEGRADA[[#This Row],[Nº SS]],Tb_HhPLAN[DISCIPLINA],"MEC") -> 0 | AI27: =SUMIFS(Hh_EXE_TOTAL[Hh],Hh_EXE_TOTAL[Nº SS],TB_INTEGRADA[[#This Row],[Nº SS]],Hh_EXE_TOTAL[DISCIPLINA],"MEC") -> 96 | AJ27: =IF(TB_INTEGRADA[[#This Row],[TOMADOR]]="EDIVIT",TB_INTEGRADA[[#This Row],[ORÇ DIG1]]*1.38,IF(TB_INTEGRADA[[#This Row],[TOMADOR]]="UTGC",TB_INTEGRADA[[#This Row],[ORÇ DIG1]]*1.47,IF(TB_INTEGRADA[[#This Row],[TOMADOR]]="TIMS",TB_INTEGRADA[[#This Row],[ORÇ DIG1]]*1.34,IF(TB_INTEGRADA[[#This Row],[TOMADOR]]="UTGSUL",TB_INTEGRADA[[#This Row],[ORÇ DIG1]]*1.37,IF(TB_INTEGRADA[[#This Row],[TOMADOR]]="REGAP",TB_INTEGRADA[[#This Row],[ORÇ DIG1]]*1.36,IF(TB_INTEGRADA[[#This Row],[TOMADOR]]="UTEIBI",TB_INTEGRADA[[#This Row],[ORÇ DIG1]]*1.5,"S/TOMADOR")))))) -> 0 | AL27: =SUMIFS(Tb_HhPLAN[Hh DISC],Tb_HhPLAN[SS],TB_INTEGRADA[[#This Row],[Nº SS]],Tb_HhPLAN[DISCIPLINA],"CIVIL") -> 0 | AM27: =SUMIFS(Hh_EXE_TOTAL[Hh],Hh_EXE_TOTAL[Nº SS],TB_INTEGRADA[[#This Row],[Nº SS]],Hh_EXE_TOTAL[DISCIPLINA],"CIVIL") -> 0 | AN27: =IF(TB_INTEGRADA[[#This Row],[TOMADOR]]="EDIVIT",TB_INTEGRADA[[#This Row],[ORÇ DIG2]]*1.38,IF(TB_INTEGRADA[[#This Row],[TOMADOR]]="UTGC",TB_INTEGRADA[[#This Row],[ORÇ DIG2]]*1.47,IF(TB_INTEGRADA[[#This Row],[TOMADOR]]="TIMS",TB_INTEGRADA[[#This Row],[ORÇ DIG2]]*1.34,IF(TB_INTEGRADA[[#This Row],[TOMADOR]]="UTGSUL",TB_INTEGRADA[[#This Row],[ORÇ DIG2]]*1.37,IF(TB_INTEGRADA[[#This Row],[TOMADOR]]="REGAP",TB_INTEGRADA[[#This Row],[ORÇ DIG2]]*1.36,IF(TB_INTEGRADA[[#This Row],[TOMADOR]]="UTEIBI",TB_INTEGRADA[[#This Row],[ORÇ DIG2]]*1.5,"S/TOMADOR")))))) -> 0 | AP27: =SUMIFS(Tb_HhPLAN[Hh DISC],Tb_HhPLAN[SS],TB_INTEGRADA[[#This Row],[Nº SS]],Tb_HhPLAN[DISCIPLINA],"ELÉT") -> 0 | AQ27: =SUMIFS(Hh_EXE_TOTAL[Hh],Hh_EXE_TOTAL[Nº SS],TB_INTEGRADA[[#This Row],[Nº SS]],Hh_EXE_TOTAL[DISCIPLINA],"ELÉT") -> 0 | AR27: =IF(TB_INTEGRADA[[#This Row],[TOMADOR]]="EDIVIT",TB_INTEGRADA[[#This Row],[ORÇ DIG3]]*1.38,IF(TB_INTEGRADA[[#This Row],[TOMADOR]]="UTGC",TB_INTEGRADA[[#This Row],[ORÇ DIG3]]*1.47,IF(TB_INTEGRADA[[#This Row],[TOMADOR]]="TIMS",TB_INTEGRADA[[#This Row],[ORÇ DIG3]]*1.34,IF(TB_INTEGRADA[[#This Row],[TOMADOR]]="UTGSUL",TB_INTEGRADA[[#This Row],[ORÇ DIG3]]*1.37,IF(TB_INTEGRADA[[#This Row],[TOMADOR]]="REGAP",TB_INTEGRADA[[#This Row],[ORÇ DIG3]]*1.36,IF(TB_INTEGRADA[[#This Row],[TOMADOR]]="UTEIBI",TB_INTEGRADA[[#This Row],[ORÇ DIG3]]*1.5,"S/TOMADOR")))))) -> 0 | AT27: =SUMIFS(Tb_HhPLAN[Hh DISC],Tb_HhPLAN[SS],TB_INTEGRADA[[#This Row],[Nº SS]],Tb_HhPLAN[DISCIPLINA],"PINT") -> 0 | AU27: =SUMIFS(Hh_EXE_TOTAL[Hh],Hh_EXE_TOTAL[Nº SS],TB_INTEGRADA[[#This Row],[Nº SS]],Hh_EXE_TOTAL[DISCIPLINA],"PINT") -> 0 | AV27: =TB_INTEGRADA[[#This Row],[ORÇADO]]+TB_INTEGRADA[[#This Row],[ORÇADO1]]+TB_INTEGRADA[[#This Row],[ORÇADO2]]+TB_INTEGRADA[[#This Row],[ORÇADO3]] -> 158.9805 | AW27: =TB_INTEGRADA[[#This Row],[PLANEJ]]+TB_INTEGRADA[[#This Row],[PLANEJ1]]+TB_INTEGRADA[[#This Row],[PLANEJ2]]+TB_INTEGRADA[[#This Row],[PLANEJ3]] -> 0 | AX27: =TB_INTEGRADA[[#This Row],[REALIZ]]+TB_INTEGRADA[[#This Row],[REALIZ1]]+TB_INTEGRADA[[#This Row],[REALIZ2]]+TB_INTEGRADA[[#This Row],[REALIZ3]] -> 96 | AY27: =IFERROR(TB_INTEGRADA[[#This Row],[REALIZ4]]/TB_INTEGRADA[[#This Row],[ORÇADO4]],"") -> 0.60384764 | AZ27: =_xlfn.XLOOKUP(TB_INTEGRADA[[#This Row],[Nº SS]],'CONTROLE EC'!B:B,'CONTROLE EC'!W:W,"",0,1) -> 9395.5403 | BA27: =_xlfn.XLOOKUP(TB_INTEGRADA[[#This Row],[Nº SS]],'CONTROLE EC'!B:B,'CONTROLE EC'!X:X,"",0,1) -> 9395.5403 | BB27: =_xlfn.XLOOKUP(TB_INTEGRADA[[#This Row],[Nº SS]],'CONTROLE EC'!B:B,'CONTROLE EC'!Y:Y,"",0,1) -> 0
